Workbook

Sheet Audit Raw data
AW1: 6 | AX1: 4 | AY1: 4 | AZ1: 2 | BA1: 4 | BB1: 4 | BC1: 4 | BD1: 2 | BE1: 4 | BF1: 2 | BG1: 4 | BH1: 4 | BI1: 4 | BJ1: 2 | BK1: 4 | BL1: 2 | BM1: 4 | BN1: 4 | BO1: 4 | BP1: 4 | BQ1: 6 | BR1: 4 | BS1: 4 | BT1: 4 | BU1: 4 | BW1: 6 | BZ1: =SUM(AW1:BY1) -> 100
A2: Timestamp | B2: Email Address | C2: Score | D2: Auditor Name | E2: Audit Date | F2: LOB | G2: Call Date | H2: Mobile Number | I2: Duration Of Call | J2: Agent Emp ID | K2: Call Language | L2: Circle of Call | M2: Greeted Customer, Started BSNL Name, Started Call with a Smile | N2: Introduced Self (First Name) | O2: Asked Caller Name(First &Last name) | P2: Asked the Caller required Verification Question (If any) | Q2: Asked caller the purpose of the call | R2: Verified the Purpose of the caller (Paraphrase) | S2: Identified the call type & Identified the process to be followed | T2: Identified the IT Systems/tools to be used | U2: Followed all Process Steps/ Actives in Sequence ? | V2: Navigated the System Without any errors (Leading to Increase call hold time) | W2: Procure the required information from customer | X2: Utilized all information & System access before escalation | Y2: Used Approved Question/Polite language | Z2: Demonstrated active listening skills | AA2: Used confidence & empathy Wordings | AB2: Gave apology/reassurance/appropriate response | AC2: Explained hold time or Dead air | AD2: Upheld BSNL positive image | AE2: Maintained focus on caller's problem | AF2: Identified other issues raised (if any) during the call & Sequenced each issue | AG2: Give accurate information/ Next steps on each issue | AH2: Transferred call appropriately (if required) | AI2: Gave SR Number (If applicable) | AJ2: Thanked the caller for calling | AK2: Waited for caller to hangup and appropriately closed the call ? | AL2: Script adherence | AM2: Captured accurate notes in the CRM | AN2: Captured proper Notes | AO2: Tagging Accuracy | AP2: What went wrong ,required for Agent Feedback | AQ2: Call Summary | AR2: Type of Connection | AS2: Type of call | AT2: Sub Type of Call | AU2: Issues forund on call | AW2: Greeted Customer, Started BSNL Name, Started Call with a Smile | AX2: Introduced Self (First Name) | AY2: Asked Caller Name(First &Last name) | AZ2: Asked the Caller required Verification Question (If any) | BA2: Asked caller the purpose of the call | BB2: Verified the Purpose of the caller (Paraphrase) | BC2: Identified the call type & Identified the process to be followed | BD2: Identified the IT Systems/tools to be used | BE2: Followed all Process Steps/ Actives in Sequence ? | BF2: Navigated the System Without any errors (Leading to Increase call hold time) | BG2: Procure the required information from customer | BH2: Utilized all information & System access before escalation | BI2: Used Approved Question/Polite language | BJ2: Demonstrated active listening skills | BK2: Used confidence & empathy Wordings | BL2: Gave apology/reassurance/appropriate response | BM2: Explained hold time or Dead air | BN2: Upheld BSNL positive image | BO2: Maintained focus on caller's problem | BP2: Identified other issues raised (if any) during the call & Sequenced each issue | BQ2: Give accurate information/ Next steps on each issue | BR2: Transferred call appropriately (if required) | BS2: Gave SR Number (If applicable) | BT2: Thanked the caller for calling | BU2: Waited for caller to hangup and appropriately closed the call ? | BV2: Script adherence | BW2: Captured accurate notes in the CRM | BX2: Captured proper Notes | BY2: Tagging Accuracy | BZ2: SCORE | CA2: TL | CB2: Date | CC2: Quality status
A3: 45667.455 | B3: sshinyc117@gmail.com | C3: 0 / 40 | D3: Shiny | E3: 45931 | F3: Wireless | G3: 9/30/2025 | H3: 9496826734 | I3: 220 | J3: SBM150 | K3: Malayalam | L3: Kerala | M3: Yes | N3: Yes | O3: Yes | P3: Yes | Q3: Yes | R3: No | S3: Yes | T3: Yes | U3: Yes | V3: Yes | W3: Yes | X3: Yes | Y3: Yes | Z3: Yes | AA3: Yes | AB3: Yes | AC3: Not Applicable | AD3: Yes | AE3: No | AF3: Not Applicable | AG3: Yes | AH3: Not Applicable | AI3: Not Applicable | AJ3: Yes | AK3: Not Applicable | AL3: No | AM3: No | AN3: Yes | AO3: Yes | AP3: Complete probing not done, interruption, correct remark not mentioned | AQ3: Customer having network connectivity issue. Advisor complete probing to customer as per call and register complaint for weak signal issue. | AR3: Prepaid | AS3: NETWORK | AT3: POOR NETWORK COVERAGE | AW3: =IF(OR(M3="YES", M3="Not Applicable"), AW$1, "0") -> 6 | AX3: =IF(OR(N3="YES", N3="Not Applicable"), AX$1, "0") -> 4 | AY3: =IF(OR(O3="YES", O3="Not Applicable"), AY$1, "0") -> 4 | AZ3: =IF(OR(P3="YES", P3="Not Applicable"), AZ$1, "0") -> 2 | BA3: =IF(OR(Q3="YES", Q3="Not Applicable"), BA$1, "0") -> 4 | BB3: =IF(OR(R3="YES", R3="Not Applicable"), BB$1, "0") -> 0 | BC3: =IF(OR(S3="YES", S3="Not Applicable"), BC$1, "0") -> 4 | BD3: =IF(OR(T3="YES", T3="Not Applicable"), BD$1, "0") -> 2 | ... BY3: =IF(OR(AO3="YES", AO3="Not Applicable"), BY$1, "0") -> 0 | BZ3: =SUM(AW3:BY3) -> 86 | CA3: =VLOOKUP(J:J,'Agent wise'!A:C,3,0) -> Saran S | CB3: =INT(E3) -> 45931 | CC3: =IF(BZ3>=94.5, "Excellent", IF(BZ3>89.5, "Good", IF(BZ3>84.5, "Average", "FC"))) -> Average | CJ3: =DAY(E3) -> 1 | CK3: =MONTH(E3) -> 10 | CL3: =YEAR(E3) -> 2025
A4: 45667.46 | B4: sshinyc117@gmail.com | C4: 0 / 40 | D4: Shiny | E4: 45931 | F4: Wireless | G4: 9/30/2025 | H4: 9048626079 | I4: 148 | J4: SBM157 | K4: Malayalam | L4: Kerala | M4: Yes | N4: Yes | O4: Yes | P4: Yes | Q4: Yes | R4: No | S4: Yes | T4: Yes | U4: Yes | V4: Yes | W4: Yes | X4: Yes | Y4: Yes | Z4: Yes | AA4: Yes | AB4: Yes | AC4: Not Applicable | AD4: Yes | AE4: Yes | AF4: Yes | AG4: Yes | AH4: Not Applicable | AI4: No | AJ4: Yes | AK4: Not Applicable | AL4: No | AM4: Yes | AN4: Yes | AO4: Yes | AP4: Complete probing not done | AQ4: Customer having call and data connectivity issue. Advisor complete probing to customer as per call and register complaint for weak signal issue , | AR4: Prepaid | AS4: NETWORK | AT4: POOR NETWORK COVERAGE | AW4: =IF(OR(M4="YES", M4="Not Applicable"), AW$1, "0") -> 6 | AX4: =IF(OR(N4="YES", N4="Not Applicable"), AX$1, "0") -> 4 | AY4: =IF(OR(O4="YES", O4="Not Applicable"), AY$1, "0") -> 4 | AZ4: =IF(OR(P4="YES", P4="Not Applicable"), AZ$1, "0") -> 2 | BA4: =IF(OR(Q4="YES", Q4="Not Applicable"), BA$1, "0") -> 4 | BB4: =IF(OR(R4="YES", R4="Not Applicable"), BB$1, "0") -> 0 | BC4: =IF(OR(S4="YES", S4="Not Applicable"), BC$1, "0") -> 4 | BD4: =IF(OR(T4="YES", T4="Not Applicable"), BD$1, "0") -> 2 | ... BY4: =IF(OR(AO4="YES", AO4="Not Applicable"), BY$1, "0") -> 0 | BZ4: =SUM(AW4:BY4) -> 92 | CA4: =VLOOKUP(J:J,'Agent wise'!A:C,3,0) -> Saran S | CB4: =INT(E4) -> 45931 | CC4: =IF(BZ4>=94.5, "Excellent", IF(BZ4>89.5, "Good", IF(BZ4>84.5, "Average", "FC"))) -> Good | CJ4: =DAY(E4) -> 1 | CK4: =MONTH(E4) -> 10 | CL4: =YEAR(E4) -> 2025
A5: 45667.491 | B5: sshinyc117@gmail.com | C5: 0 / 40 | D5: Shiny | E5: 45931 | F5: Wireless | G5: 9/30/2025 | H5: 9445185748 | I5: 217 | J5: SBM363 | K5: Tamil | L5: Tamil Nadu | M5: No | N5: Yes | O5: Yes | P5: Yes | Q5: Yes | R5: No | S5: Yes | T5: Yes | U5: No | V5: Yes | W5: Yes | X5: Yes | Y5: Yes | Z5: Yes | AA5: Yes | AB5: No | AC5: Not Applicable | AD5: Yes | AE5: Yes | AF5: Not Applicable | AG5: Yes | AH5: Not Applicable | AI5: No | AJ5: Yes | AK5: Not Applicable | AL5: No | AM5: Yes | AN5: Yes | AO5: No | AP5: apology missing, correct tagging not done, dead air, complete probing not done | AQ5: Customer having call and data connectivity issue. Advisor complete probing to customer as per call and register complaint for weak signal issue , | AR5: Prepaid | AS5: NETWORK | AT5: POOR VOICE QUALITY | AW5: =IF(OR(M5="YES", M5="Not Applicable"), AW$1, "0") -> 0 | AX5: =IF(OR(N5="YES", N5="Not Applicable"), AX$1, "0") -> 4 | AY5: =IF(OR(O5="YES", O5="Not Applicable"), AY$1, "0") -> 4 | AZ5: =IF(OR(P5="YES", P5="Not Applicable"), AZ$1, "0") -> 2 | BA5: =IF(OR(Q5="YES", Q5="Not Applicable"), BA$1, "0") -> 4 | BB5: =IF(OR(R5="YES", R5="Not Applicable"), BB$1, "0") -> 0 | BC5: =IF(OR(S5="YES", S5="Not Applicable"), BC$1, "0") -> 4 | BD5: =IF(OR(T5="YES", T5="Not Applicable"), BD$1, "0") -> 2 | ... BY5: =IF(OR(AO5="YES", AO5="Not Applicable"), BY$1, "0") -> 0 | BZ5: =SUM(AW5:BY5) -> 80 | CA5: =VLOOKUP(J:J,'Agent wise'!A:C,3,0) -> Saran S | CB5: =INT(E5) -> 45931 | CC5: =IF(BZ5>=94.5, "Excellent", IF(BZ5>89.5, "Good", IF(BZ5>84.5, "Average", "FC"))) -> FC | CJ5: =DAY(E5) -> 1 | CK5: =MONTH(E5) -> 10 | CL5: =YEAR(E5) -> 2025
A6: 45667.494 | B6: sshinyc117@gmail.com | C6: 0 / 40 | D6: Shiny | E6: 45931 | F6: Wireless | G6: 9/30/2025 | H6: 8606790086 | I6: 195 | J6: SBM373 | K6: Malayalam | L6: Kerala | M6: Yes | N6: Yes | O6: Yes | P6: Yes | Q6: Yes | R6: No | S6: Yes | T6: Yes | U6: Yes | V6: Yes | W6: Yes | X6: Yes | Y6: Yes | Z6: Yes | AA6: Yes | AB6: Yes | AC6: No | AD6: Yes | AE6: Yes | AF6: Not Applicable | AG6: Yes | AH6: Not Applicable | AI6: No | AJ6: Yes | AK6: Not Applicable | AL6: No | AM6: Yes | AN6: Yes | AO6: Yes | AP6: Dead air, complete probing not done, further assistance not done | AQ6: Customer having weak signal and data connectivity issue. Advisor complete probing to customer as per call and register complaint for weak signal issue , | AR6: Prepaid | AS6: NETWORK | AT6: NO SIGNAL | AW6: =IF(OR(M6="YES", M6="Not Applicable"), AW$1, "0") -> 6 | AX6: =IF(OR(N6="YES", N6="Not Applicable"), AX$1, "0") -> 4 | AY6: =IF(OR(O6="YES", O6="Not Applicable"), AY$1, "0") -> 4 | AZ6: =IF(OR(P6="YES", P6="Not Applicable"), AZ$1, "0") -> 2 | BA6: =IF(OR(Q6="YES", Q6="Not Applicable"), BA$1, "0") -> 4 | BB6: =IF(OR(R6="YES", R6="Not Applicable"), BB$1, "0") -> 0 | BC6: =IF(OR(S6="YES", S6="Not Applicable"), BC$1, "0") -> 4 | BD6: =IF(OR(T6="YES", T6="Not Applicable"), BD$1, "0") -> 2 | ... BY6: =IF(OR(AO6="YES", AO6="Not Applicable"), BY$1, "0") -> 0 | BZ6: =SUM(AW6:BY6) -> 88 | CA6: =VLOOKUP(J:J,'Agent wise'!A:C,3,0) -> Saran S | CB6: =INT(E6) -> 45931 | CC6: =IF(BZ6>=94.5, "Excellent", IF(BZ6>89.5, "Good", IF(BZ6>84.5, "Average", "FC"))) -> Average | CJ6: =DAY(E6) -> 1 | CK6: =MONTH(E6) -> 10 | CL6: =YEAR(E6) -> 2025
A7: 45667.497 | B7: sshinyc117@gmail.com | C7: 0 / 40 | D7: Shiny | E7: 45931 | F7: Wireless | G7: 9/30/2025 | H7: 9447997090 | I7: 156 | J7: SBM485 | K7: Malayalam | L7: Kerala | M7: No | N7: Yes | O7: Yes | P7: Yes | Q7: Yes | R7: No | S7: Yes | T7: Yes | U7: Yes | V7: Yes | W7: Yes | X7: Yes | Y7: Yes | Z7: Yes | AA7: No | AB7: Yes | AC7: No | AD7: Yes | AE7: Yes | AF7: Not Applicable | AG7: No | AH7: Not Applicable | AI7: Not Applicable | AJ7: Yes | AK7: Not Applicable | AL7: No | AM7: Yes | AN7: Yes | AO7: Yes | AP7: correct greeting not used, empathy missing, correct information not shared, dead air | AQ7: Customer having data connectivity issue. Advisor complete probing to customer as per call and given APN settings. | AR7: Prepaid | AS7: DATA SERVICES | AT7: UNABLE TO BROWSE DATA | AW7: =IF(OR(M7="YES", M7="Not Applicable"), AW$1, "0") -> 0 | AX7: =IF(OR(N7="YES", N7="Not Applicable"), AX$1, "0") -> 4 | AY7: =IF(OR(O7="YES", O7="Not Applicable"), AY$1, "0") -> 4 | AZ7: =IF(OR(P7="YES", P7="Not Applicable"), AZ$1, "0") -> 2 | BA7: =IF(OR(Q7="YES", Q7="Not Applicable"), BA$1, "0") -> 4 | BB7: =IF(OR(R7="YES", R7="Not Applicable"), BB$1, "0") -> 0 | BC7: =IF(OR(S7="YES", S7="Not Applicable"), BC$1, "0") -> 4 | BD7: =IF(OR(T7="YES", T7="Not Applicable"), BD$1, "0") -> 2 | ... BY7: =IF(OR(AO7="YES", AO7="Not Applicable"), BY$1, "0") -> 0 | BZ7: =SUM(AW7:BY7) -> 76 | CA7: =VLOOKUP(J:J,'Agent wise'!A:C,3,0) -> Saran S | CB7: =INT(E7) -> 45931 | CC7: =IF(BZ7>=94.5, "Excellent", IF(BZ7>89.5, "Good", IF(BZ7>84.5, "Average", "FC"))) -> FC | CJ7: =DAY(E7) -> 1 | CK7: =MONTH(E7) -> 10 | CL7: =YEAR(E7) -> 2025
A8: 45667.502 | B8: sshinyc117@gmail.com | C8: 0 / 40 | D8: Shiny | E8: 45931 | F8: Wireless | G8: 9/30/2025 | H8: 9445365382 | I8: 168 | J8: SBM692 | K8: English | L8: Tamil Nadu | M8: No | N8: Yes | O8: Yes | P8: Yes | Q8: Yes | R8: Yes | S8: Yes | T8: Yes | U8: Yes | V8: Yes | W8: Yes | X8: Yes | Y8: Yes | Z8: Yes | AA8: Yes | AB8: Yes | AC8: Not Applicable | AD8: Yes | AE8: Yes | AF8: Not Applicable | AG8: Yes | AH8: Not Applicable | AI8: Not Applicable | AJ8: Yes | AK8: Not Applicable | AL8: No | AM8: Yes | AN8: Yes | AO8: Yes | AP8: correct greeting not used | AQ8: Customer having 4G and volte related enquiry. Advisor complete probing to customer as per call and register request for volte activation , | AR8: Prepaid | AS8: DATA SERVICES | AT8: UNABLE TO BROWSE DATA | AW8: =IF(OR(M8="YES", M8="Not Applicable"), AW$1, "0") -> 0 | AX8: =IF(OR(N8="YES", N8="Not Applicable"), AX$1, "0") -> 4 | AY8: =IF(OR(O8="YES", O8="Not Applicable"), AY$1, "0") -> 4 | AZ8: =IF(OR(P8="YES", P8="Not Applicable"), AZ$1, "0") -> 2 | BA8: =IF(OR(Q8="YES", Q8="Not Applicable"), BA$1, "0") -> 4 | BB8: =IF(OR(R8="YES", R8="Not Applicable"), BB$1, "0") -> 4 | BC8: =IF(OR(S8="YES", S8="Not Applicable"), BC$1, "0") -> 4 | BD8: =IF(OR(T8="YES", T8="Not Applicable"), BD$1, "0") -> 2 | ... BY8: =IF(OR(AO8="YES", AO8="Not Applicable"), BY$1, "0") -> 0 | BZ8: =SUM(AW8:BY8) -> 94 | CA8: =VLOOKUP(J:J,'Agent wise'!A:C,3,0) -> Saran S | CB8: =INT(E8) -> 45931 | CC8: =IF(BZ8>=94.5, "Excellent", IF(BZ8>89.5, "Good", IF(BZ8>84.5, "Average", "FC"))) -> Good | CJ8: =DAY(E8) -> 1 | CK8: =MONTH(E8) -> 10 | CL8: =YEAR(E8) -> 2025
A9: 45667.541 | B9: sshinyc117@gmail.com | C9: 0 / 40 | D9: Shiny | E9: 45931 | F9: MNP OBD | G9: 9/30/2025 | H9: 9443178739 | I9: 211 | J9: SBM267 | K9: Tamil | L9: Tamil Nadu | M9: Yes | N9: Yes | O9: Yes | P9: Yes | Q9: Yes | R9: Yes | S9: Yes | T9: Yes | U9: Yes | V9: Yes | W9: Yes | X9: Yes | Y9: Yes | Z9: Yes | AA9: No | AB9: No | AC9: No | AD9: Yes | AE9: Yes | AF9: Not Applicable | AG9: Yes | AH9: Not Applicable | AI9: Not Applicable | AJ9: Yes | AK9: Not Applicable | AL9: No | AM9: Yes | AN9: Yes | AO9: Yes | AP9: empathy & apology missing, dead air | AQ9: Customer having network connectivity issue in Abroad . Advisor complete probing to customer as per call and collect information regarding port out , | AR9: Prepaid | AS9: COMPLETE CALL | AT9: NOT AGREED | AW9: =IF(OR(M9="YES", M9="Not Applicable"), AW$1, "0") -> 6 | AX9: =IF(OR(N9="YES", N9="Not Applicable"), AX$1, "0") -> 4 | AY9: =IF(OR(O9="YES", O9="Not Applicable"), AY$1, "0") -> 4 | AZ9: =IF(OR(P9="YES", P9="Not Applicable"), AZ$1, "0") -> 2 | BA9: =IF(OR(Q9="YES", Q9="Not Applicable"), BA$1, "0") -> 4 | BB9: =IF(OR(R9="YES", R9="Not Applicable"), BB$1, "0") -> 4 | BC9: =IF(OR(S9="YES", S9="Not Applicable"), BC$1, "0") -> 4 | BD9: =IF(OR(T9="YES", T9="Not Applicable"), BD$1, "0") -> 2 | ... BY9: =IF(OR(AO9="YES", AO9="Not Applicable"), BY$1, "0") -> 0 | BZ9: =SUM(AW9:BY9) -> 90 | CA9: =VLOOKUP(J:J,'Agent wise'!A:C,3,0) -> Saran S | CB9: =INT(E9) -> 45931 | CC9: =IF(BZ9>=94.5, "Excellent", IF(BZ9>89.5, "Good", IF(BZ9>84.5, "Average", "FC"))) -> Good | CJ9: =DAY(E9) -> 1 | CK9: =MONTH(E9) -> 10 | CL9: =YEAR(E9) -> 2025
A10: 45667.584 | B10: sshinyc117@gmail.com | C10: 0 / 40 | D10: Shiny | E10: 45931 | F10: MNP OBD | G10: 9/30/2025 | H10: 9698886964 | I10: 189 | J10: SBM744 | K10: Tamil | L10: Tamil Nadu | M10: Yes | N10: Yes | O10: Yes | P10: Yes | Q10: Yes | R10: Yes | S10: Yes | T10: Yes | U10: Yes | V10: Yes | W10: Yes | X10: Yes | Y10: Yes | Z10: Yes | AA10: No | AB10: No | AC10: Not Applicable | AD10: No | AE10: Yes | AF10: Not Applicable | AG10: Yes | AH10: Not Applicable | AI10: No | AJ10: Yes | AK10: Not Applicable | AL10: No | AM10: Yes | AN10: Yes | AO10: Yes | AP10: empathy & apology missing | AQ10: Customer having weak signal and data connectivity issue. Advisor complete probing to customer as per call and capture port out reason , | AR10: Prepaid | AS10: COMPLETE CALL | AT10: NOT AGREED | AW10: =IF(OR(M10="YES", M10="Not Applicable"), AW$1, "0") -> 6 | AX10: =IF(OR(N10="YES", N10="Not Applicable"), AX$1, "0") -> 4 | AY10: =IF(OR(O10="YES", O10="Not Applicable"), AY$1, "0") -> 4 | AZ10: =IF(OR(P10="YES", P10="Not Applicable"), AZ$1, "0") -> 2 | BA10: =IF(OR(Q10="YES", Q10="Not Applicable"), BA$1, "0") -> 4 | BB10: =IF(OR(R10="YES", R10="Not Applicable"), BB$1, "0") -> 4 | BC10: =IF(OR(S10="YES", S10="Not Applicable"), BC$1, "0") -> 4 | BD10: =IF(OR(T10="YES", T10="Not Applicable"), BD$1, "0") -> 2 | ... BY10: =IF(OR(AO10="YES", AO10="Not Applicable"), BY$1, "0") -> 0 | BZ10: =SUM(AW10:BY10) -> 86 | CA10: =VLOOKUP(J:J,'Agent wise'!A:C,3,0) -> Shiny | CB10: =INT(E10) -> 45931 | CC10: =IF(BZ10>=94.5, "Excellent", IF(BZ10>89.5, "Good", IF(BZ10>84.5, "Average", "FC"))) -> Average | CJ10: =DAY(E10) -> 1 | CK10: =MONTH(E10) -> 10 | CL10: =YEAR(E10) -> 2025
A11: 45667.732 | B11: priyankajino2013@gmail.com | C11: 0 / 40 | D11: Priyanka | E11: 45931 | F11: Wireless | G11: 9/30/2025 | H11: 8078889156 | I11: 197 | J11: VPS259 | K11: Malayalam | L11: Kerala | M11: Yes | N11: Yes | O11: Yes | P11: Yes | Q11: Yes | R11: No | S11: Yes | T11: Yes | U11: No | V11: Yes | W11: Yes | X11: Yes | Y11: Yes | Z11: Yes | AA11: No | AB11: No | AC11: No | AD11: Yes | AE11: No | AF11: Not Applicable | AG11: No | AH11: Yes | AI11: Not Applicable | AJ11: Yes | AK11: Yes | AL11: No | AM11: Yes | AN11: Yes | AO11: No | AP11: AOI-dead air,empathy missing,aplology missing | AQ11: Opening & Introduction â€“ Done Customer details captured â€“Done Customer concern -Customer ask network issue Resolution shared - Advisor complete probing to customers as per call setting provide Closing as per standard - Done. AOI-dead air,empathy missing,aplology missing | AR11: Prepaid | AS11: DATA SERVICES | AT11: DATA DEACTIVATION | AW11: =IF(OR(M11="YES", M11="Not Applicable"), AW$1, "0") -> 6 | AX11: =IF(OR(N11="YES", N11="Not Applicable"), AX$1, "0") -> 4 | AY11: =IF(OR(O11="YES", O11="Not Applicable"), AY$1, "0") -> 4 | AZ11: =IF(OR(P11="YES", P11="Not Applicable"), AZ$1, "0") -> 2 | BA11: =IF(OR(Q11="YES", Q11="Not Applicable"), BA$1, "0") -> 4 | BB11: =IF(OR(R11="YES", R11="Not Applicable"), BB$1, "0") -> 0 | BC11: =IF(OR(S11="YES", S11="Not Applicable"), BC$1, "0") -> 4 | BD11: =IF(OR(T11="YES", T11="Not Applicable"), BD$1, "0") -> 2 | ... BY11: =IF(OR(AO11="YES", AO11="Not Applicable"), BY$1, "0") -> 0 | BZ11: =SUM(AW11:BY11) -> 72 | CA11: =VLOOKUP(J:J,'Agent wise'!A:C,3,0) -> Shakeer | CB11: =INT(E11) -> 45931 | CC11: =IF(BZ11>=94.5, "Excellent", IF(BZ11>89.5, "Good", IF(BZ11>84.5, "Average", "FC"))) -> FC | CJ11: =DAY(E11) -> 1 | CK11: =MONTH(E11) -> 10 | CL11: =YEAR(E11) -> 2025
A12: 45667.933 | B12: shakeerfazal11@gmail.com | C12: 0 / 40 | D12: Shakeer | E12: 45931 | F12: Wireless | G12: 45667 | H12: 9443654944 | I12: 145 | J12: VPS111 | K12: Tamil | L12: Tamil Nadu | M12: Yes | N12: Yes | O12: No | P12: Yes | Q12: Yes | R12: Yes | S12: Yes | T12: Yes | U12: No | V12: Yes | W12: Yes | X12: Not Applicable | Y12: Yes | Z12: Yes | AA12: No | AB12: No | AC12: Not Applicable | AD12: Yes | AE12: Yes | AF12: Not Applicable | AG12: Yes | AH12: Not Applicable | AI12: Not Applicable | AJ12: Yes | AK12: Yes | AL12: No | AM12: Yes | AN12: Yes | AO12: Yes | AP12: Not asked customer name, Not used empathy and apology words, No further assistance | AQ12: Customer called and inquired about Validity and plans related issue, Agent checked and given validity and plans details correctly. but not followed required quality parameter properly. | AR12: Prepaid | AS12: PLANS AND VALIDITY DETAILS | AT12: ENQUIRY ON BALANCE AND VALIDITY | AW12: =IF(OR(M12="YES", M12="Not Applicable"), AW$1, "0") -> 6 | AX12: =IF(OR(N12="YES", N12="Not Applicable"), AX$1, "0") -> 4 | AY12: =IF(OR(O12="YES", O12="Not Applicable"), AY$1, "0") -> 0 | AZ12: =IF(OR(P12="YES", P12="Not Applicable"), AZ$1, "0") -> 2 | BA12: =IF(OR(Q12="YES", Q12="Not Applicable"), BA$1, "0") -> 4 | BB12: =IF(OR(R12="YES", R12="Not Applicable"), BB$1, "0") -> 4 | BC12: =IF(OR(S12="YES", S12="Not Applicable"), BC$1, "0") -> 4 | BD12: =IF(OR(T12="YES", T12="Not Applicable"), BD$1, "0") -> 2 | ... BY12: =IF(OR(AO12="YES", AO12="Not Applicable"), BY$1, "0") -> 0 | BZ12: =SUM(AW12:BY12) -> 86 | CA12: =VLOOKUP(J:J,'Agent wise'!A:C,3,0) -> Shiny | CB12: =INT(E12) -> 45931 | CC12: =IF(BZ12>=94.5, "Excellent", IF(BZ12>89.5, "Good", IF(BZ12>84.5, "Average", "FC"))) -> Average | CJ12: =DAY(E12) -> 1 | CK12: =MONTH(E12) -> 10 | CL12: =YEAR(E12) -> 2025
A13: 45667.935 | B13: shakeerfazal11@gmail.com | C13: 0 / 40 | D13: Shakeer | E13: 45931 | F13: Wireless | G13: 45667 | H13: 7550281435 | I13: 145 | J13: VPS111 | K13: Tamil | L13: Tamil Nadu | M13: Yes | N13: Yes | O13: Yes | P13: Yes | Q13: Yes | R13: Yes | S13: Yes | T13: Yes | U13: No | V13: Yes | W13: Yes | X13: Not Applicable | Y13: Yes | Z13: No | AA13: No | AB13: No | AC13: Not Applicable | AD13: Not Applicable | AE13: Yes | AF13: Not Applicable | AG13: Yes | AH13: Not Applicable | AI13: Not Applicable | AJ13: Yes | AK13: Yes | AL13: No | AM13: Yes | AN13: Yes | AO13: Yes | AP13: No active listening skill, Not used empathy and apology words, No further assistance | AQ13: Customer called and inquired about PUK related issue, Agent checked and given proper information but not followed required quality parameter properly. | AR13: Prepaid | AS13: BSNL SELF CARE SERVICES | AT13: PUK CODE | AW13: =IF(OR(M13="YES", M13="Not Applicable"), AW$1, "0") -> 6 | AX13: =IF(OR(N13="YES", N13="Not Applicable"), AX$1, "0") -> 4 | AY13: =IF(OR(O13="YES", O13="Not Applicable"), AY$1, "0") -> 4 | AZ13: =IF(OR(P13="YES", P13="Not Applicable"), AZ$1, "0") -> 2 | BA13: =IF(OR(Q13="YES", Q13="Not Applicable"), BA$1, "0") -> 4 | BB13: =IF(OR(R13="YES", R13="Not Applicable"), BB$1, "0") -> 4 | BC13: =IF(OR(S13="YES", S13="Not Applicable"), BC$1, "0") -> 4 | BD13: =IF(OR(T13="YES", T13="Not Applicable"), BD$1, "0") -> 2 | ... BY13: =IF(OR(AO13="YES", AO13="Not Applicable"), BY$1, "0") -> 0 | BZ13: =SUM(AW13:BY13) -> 88 | CA13: =VLOOKUP(J:J,'Agent wise'!A:C,3,0) -> Shiny | CB13: =INT(E13) -> 45931 | CC13: =IF(BZ13>=94.5, "Excellent", IF(BZ13>89.5, "Good", IF(BZ13>84.5, "Average", "FC"))) -> Average | CJ13: =DAY(E13) -> 1 | CK13: =MONTH(E13) -> 10 | CL13: =YEAR(E13) -> 2025
A14: 45667.941 | B14: shakeerfazal11@gmail.com | C14: 0 / 40 | D14: Shakeer | E14: 45931 | F14: Wireless | G14: 45667 | H14: 9495225276 | I14: 155 | J14: VPS184 | K14: Malayalam | L14: Kerala | M14: Yes | N14: Yes | O14: Yes | P14: Yes | Q14: Yes | R14: Yes | S14: Yes | T14: Yes | U14: No | V14: Yes | W14: Yes | X14: Not Applicable | Y14: Yes | Z14: Yes | AA14: No | AB14: No | AC14: No | AD14: Not Applicable | AE14: Yes | AF14: Not Applicable | AG14: Yes | AH14: Not Applicable | AI14: Not Applicable | AJ14: Yes | AK14: Yes | AL14: No | AM14: Yes | AN14: Yes | AO14: Yes | AP14: Not used empathy and apology words, Dead air, No further assistance | AQ14: Customer called and inquired about Validity related issue, Agent checked and given Validity details, but not followed required quality parameter properly. | AR14: Prepaid | AS14: PLANS AND VALIDITY DETAILS | AT14: ENQUIRY ON BALANCE AND VALIDITY | AW14: =IF(OR(M14="YES", M14="Not Applicable"), AW$1, "0") -> 6 | AX14: =IF(OR(N14="YES", N14="Not Applicable"), AX$1, "0") -> 4 | AY14: =IF(OR(O14="YES", O14="Not Applicable"), AY$1, "0") -> 4 | AZ14: =IF(OR(P14="YES", P14="Not Applicable"), AZ$1, "0") -> 2 | BA14: =IF(OR(Q14="YES", Q14="Not Applicable"), BA$1, "0") -> 4 | BB14: =IF(OR(R14="YES", R14="Not Applicable"), BB$1, "0") -> 4 | BC14: =IF(OR(S14="YES", S14="Not Applicable"), BC$1, "0") -> 4 | BD14: =IF(OR(T14="YES", T14="Not Applicable"), BD$1, "0") -> 2 | ... BY14: =IF(OR(AO14="YES", AO14="Not Applicable"), BY$1, "0") -> 0 | BZ14: =SUM(AW14:BY14) -> 86 | CA14: =VLOOKUP(J:J,'Agent wise'!A:C,3,0) -> Saran S | CB14: =INT(E14) -> 45931 | CC14: =IF(BZ14>=94.5, "Excellent", IF(BZ14>89.5, "Good", IF(BZ14>84.5, "Average", "FC"))) -> Average | CJ14: =DAY(E14) -> 1 | CK14: =MONTH(E14) -> 10 | CL14: =YEAR(E14) -> 2025
A15: 45667.948 | B15: shakeerfazal11@gmail.com | C15: 0 / 40 | D15: Shakeer | E15: 45931 | F15: Wireless | G15: 45667 | H15: 9496541608 | I15: 161 | J15: VPS184 | K15: Malayalam | L15: Kerala | M15: Yes | N15: Yes | O15: Yes | P15: Yes | Q15: Yes | R15: Yes | S15: Yes | T15: Yes | U15: No | V15: Yes | W15: Yes | X15: Not Applicable | Y15: Yes | Z15: Yes | AA15: No | AB15: No | AC15: No | AD15: Not Applicable | AE15: Yes | AF15: Not Applicable | AG15: Yes | AH15: Not Applicable | AI15: Yes | AJ15: Yes | AK15: Yes | AL15: No | AM15: Yes | AN15: Yes | AO15: Yes | AP15: Not used empathy and apology words, Dead air, No further assistance | AQ15: Customer called and inquired about Weak signal related issue, Agent checked and taken poor coverage related complaint. But not followed required quality parameter properly | AR15: Prepaid | AS15: COMPLAINT | AT15: POOR NETWORK COVERAGE | AW15: =IF(OR(M15="YES", M15="Not Applicable"), AW$1, "0") -> 6 | AX15: =IF(OR(N15="YES", N15="Not Applicable"), AX$1, "0") -> 4 | AY15: =IF(OR(O15="YES", O15="Not Applicable"), AY$1, "0") -> 4 | AZ15: =IF(OR(P15="YES", P15="Not Applicable"), AZ$1, "0") -> 2 | BA15: =IF(OR(Q15="YES", Q15="Not Applicable"), BA$1, "0") -> 4 | BB15: =IF(OR(R15="YES", R15="Not Applicable"), BB$1, "0") -> 4 | BC15: =IF(OR(S15="YES", S15="Not Applicable"), BC$1, "0") -> 4 | BD15: =IF(OR(T15="YES", T15="Not Applicable"), BD$1, "0") -> 2 | ... BY15: =IF(OR(AO15="YES", AO15="Not Applicable"), BY$1, "0") -> 0 | BZ15: =SUM(AW15:BY15) -> 86 | CA15: =VLOOKUP(J:J,'Agent wise'!A:C,3,0) -> Saran S | CB15: =INT(E15) -> 45931 | CC15: =IF(BZ15>=94.5, "Excellent", IF(BZ15>89.5, "Good", IF(BZ15>84.5, "Average", "FC"))) -> Average | CJ15: =DAY(E15) -> 1 | CK15: =MONTH(E15) -> 10 | CL15: =YEAR(E15) -> 2025
A16: 45667.95 | B16: shakeerfazal11@gmail.com | C16: 0 / 40 | D16: Shakeer | E16: 45931 | F16: Wireless | G16: 45667 | H16: 8122448625 | I16: 148 | J16: SBM958 | K16: Tamil | L16: Tamil Nadu | M16: Yes | N16: Yes | O16: Yes | P16: Yes | Q16: Yes | R16: Yes | S16: Yes | T16: Yes | U16: No | V16: Yes | W16: Yes | X16: Not Applicable | Y16: Yes | Z16: Yes | AA16: No | AB16: No | AC16: Not Applicable | AD16: Yes | AE16: Yes | AF16: Not Applicable | AG16: Yes | AH16: Not Applicable | AI16: Not Applicable | AJ16: Yes | AK16: Yes | AL16: No | AM16: Yes | AN16: Yes | AO16: Yes | AP16: Not used empathy and apology words, No further assistance | AQ16: Customer called and inquired about Sim Lost related issue, Agent checked and given taken SIM block request properly. But not followed required quality parameter properly. | AR16: Prepaid | AS16: SIM BLOCK | AT16: SIM BLOCKDUE TO SIM LOST | AW16: =IF(OR(M16="YES", M16="Not Applicable"), AW$1, "0") -> 6 | AX16: =IF(OR(N16="YES", N16="Not Applicable"), AX$1, "0") -> 4 | AY16: =IF(OR(O16="YES", O16="Not Applicable"), AY$1, "0") -> 4 | AZ16: =IF(OR(P16="YES", P16="Not Applicable"), AZ$1, "0") -> 2 | BA16: =IF(OR(Q16="YES", Q16="Not Applicable"), BA$1, "0") -> 4 | BB16: =IF(OR(R16="YES", R16="Not Applicable"), BB$1, "0") -> 4 | BC16: =IF(OR(S16="YES", S16="Not Applicable"), BC$1, "0") -> 4 | BD16: =IF(OR(T16="YES", T16="Not Applicable"), BD$1, "0") -> 2 | ... BY16: =IF(OR(AO16="YES", AO16="Not Applicable"), BY$1, "0") -> 0 | BZ16: =SUM(AW16:BY16) -> 90 | CA16: =VLOOKUP(J:J,'Agent wise'!A:C,3,0) -> Saran S | CB16: =INT(E16) -> 45931 | CC16: =IF(BZ16>=94.5, "Excellent", IF(BZ16>89.5, "Good", IF(BZ16>84.5, "Average", "FC"))) -> Good | CJ16: =DAY(E16) -> 1 | CK16: =MONTH(E16) -> 10 | CL16: =YEAR(E16) -> 2025
A17: 45667.955 | B17: shakeerfazal11@gmail.com | C17: 0 / 40 | D17: Shakeer | E17: 45931 | F17: Wireless | G17: 45667 | H17: 9965913212 | I17: 153 | J17: SBM958 | K17: Tamil | L17: Tamil Nadu | M17: No | N17: Yes | O17: Yes | P17: Yes | Q17: Yes | R17: Yes | S17: Yes | T17: Yes | U17: No | V17: Yes | W17: Yes | X17: Not Applicable | Y17: Yes | Z17: Yes | AA17: No | AB17: No | AC17: No | AD17: Yes | AE17: Yes | AF17: Not Applicable | AG17: Yes | AH17: Not Applicable | AI17: Not Applicable | AJ17: Yes | AK17: Yes | AL17: No | AM17: Yes | AN17: Yes | AO17: Yes | AP17: Not used empathy and apology words, Dead air, No further assistance | AQ17: Customer called and inquired about Validity related issue, Agent checked and given Validity details. but not followed required quality parameter properly. | AR17: Prepaid | AS17: PLANS AND VALIDITY DETAILS | AT17: ENQUIRY ON BALANCE AND VALIDITY | AW17: =IF(OR(M17="YES", M17="Not Applicable"), AW$1, "0") -> 0 | AX17: =IF(OR(N17="YES", N17="Not Applicable"), AX$1, "0") -> 4 | AY17: =IF(OR(O17="YES", O17="Not Applicable"), AY$1, "0") -> 4 | AZ17: =IF(OR(P17="YES", P17="Not Applicable"), AZ$1, "0") -> 2 | BA17: =IF(OR(Q17="YES", Q17="Not Applicable"), BA$1, "0") -> 4 | BB17: =IF(OR(R17="YES", R17="Not Applicable"), BB$1, "0") -> 4 | BC17: =IF(OR(S17="YES", S17="Not Applicable"), BC$1, "0") -> 4 | BD17: =IF(OR(T17="YES", T17="Not Applicable"), BD$1, "0") -> 2 | ... BY17: =IF(OR(AO17="YES", AO17="Not Applicable"), BY$1, "0") -> 0 | BZ17: =SUM(AW17:BY17) -> 80 | CA17: =VLOOKUP(J:J,'Agent wise'!A:C,3,0) -> Saran S | CB17: =INT(E17) -> 45931 | CC17: =IF(BZ17>=94.5, "Excellent", IF(BZ17>89.5, "Good", IF(BZ17>84.5, "Average", "FC"))) -> FC | CJ17: =DAY(E17) -> 1 | CK17: =MONTH(E17) -> 10 | CL17: =YEAR(E17) -> 2025
A18: 45667.956 | B18: saranchirayinkeezhu720@gmail.com | C18: 0 / 40 | D18: Saran | E18: 45931 | F18: Wireless | G18: 45667 | H18: 8086771246 | I18: 128 | J18: SBM314 | K18: Malayalam | L18: Kerala | M18: No | N18: Yes | O18: Yes | P18: Yes | Q18: Yes | R18: Yes | S18: Yes | T18: Yes | U18: No | V18: Yes | W18: Yes | X18: Yes | Y18: Yes | Z18: Yes | AA18: Yes | AB18: Yes | AC18: Yes | AD18: Yes | AE18: Yes | AF18: Not Applicable | AG18: No | AH18: Not Applicable | AI18: Not Applicable | AJ18: Yes | AK18: Yes | AL18: Yes | AM18: Yes | AN18: Yes | AO18: Yes | AP18: Not given accurate information | AQ18: Customer concern -Customer called for unable to get sms . Resolution shared - Advisor done complete probing to customer as per call. | AR18: Prepaid | AS18: SMS SERVICES | AT18: UNABLE TO RECEIVE SMS | AW18: =IF(OR(M18="YES", M18="Not Applicable"), AW$1, "0") -> 0 | AX18: =IF(OR(N18="YES", N18="Not Applicable"), AX$1, "0") -> 4 | AY18: =IF(OR(O18="YES", O18="Not Applicable"), AY$1, "0") -> 4 | AZ18: =IF(OR(P18="YES", P18="Not Applicable"), AZ$1, "0") -> 2 | BA18: =IF(OR(Q18="YES", Q18="Not Applicable"), BA$1, "0") -> 4 | BB18: =IF(OR(R18="YES", R18="Not Applicable"), BB$1, "0") -> 4 | BC18: =IF(OR(S18="YES", S18="Not Applicable"), BC$1, "0") -> 4 | BD18: =IF(OR(T18="YES", T18="Not Applicable"), BD$1, "0") -> 2 | ... BY18: =IF(OR(AO18="YES", AO18="Not Applicable"), BY$1, "0") -> 0 | BZ18: =SUM(AW18:BY18) -> 84 | CA18: =VLOOKUP(J:J,'Agent wise'!A:C,3,0) -> Shakeer | CB18: =INT(E18) -> 45931 | CC18: =IF(BZ18>=94.5, "Excellent", IF(BZ18>89.5, "Good", IF(BZ18>84.5, "Average", "FC"))) -> FC | CJ18: =DAY(E18) -> 1 | CK18: =MONTH(E18) -> 10 | CL18: =YEAR(E18) -> 2025
A19: 45667.959 | B19: shakeerfazal11@gmail.com | C19: 0 / 40 | D19: Shakeer | E19: 45931 | F19: Wireless | G19: 45667 | H19: 9965913212 | I19: 153 | J19: SBM958 | K19: Tamil | L19: Tamil Nadu | M19: No | N19: Yes | O19: Yes | P19: Yes | Q19: Yes | R19: Yes | S19: Yes | T19: Yes | U19: No | V19: Yes | W19: Yes | X19: Not Applicable | Y19: Yes | Z19: Yes | AA19: No | AB19: No | AC19: No | AD19: Not Applicable | AE19: Yes | AF19: Not Applicable | AG19: Yes | AH19: Not Applicable | AI19: Not Applicable | AJ19: Yes | AK19: Yes | AL19: No | AM19: Yes | AN19: Yes | AO19: Yes | AP19: Not used empathy and apology words, Dead air, Delay opening the call, No further assistance | AQ19: Customer called and inquired about Validity related issue, Agent checked and given SIM validity details. but not followed required quality parameter properly. | AR19: Prepaid | AS19: PLANS AND VALIDITY DETAILS | AT19: ENQUIRY ON BALANCE AND VALIDITY | AW19: =IF(OR(M19="YES", M19="Not Applicable"), AW$1, "0") -> 0 | AX19: =IF(OR(N19="YES", N19="Not Applicable"), AX$1, "0") -> 4 | AY19: =IF(OR(O19="YES", O19="Not Applicable"), AY$1, "0") -> 4 | AZ19: =IF(OR(P19="YES", P19="Not Applicable"), AZ$1, "0") -> 2 | BA19: =IF(OR(Q19="YES", Q19="Not Applicable"), BA$1, "0") -> 4 | BB19: =IF(OR(R19="YES", R19="Not Applicable"), BB$1, "0") -> 4 | BC19: =IF(OR(S19="YES", S19="Not Applicable"), BC$1, "0") -> 4 | BD19: =IF(OR(T19="YES", T19="Not Applicable"), BD$1, "0") -> 2 | ... BY19: =IF(OR(AO19="YES", AO19="Not Applicable"), BY$1, "0") -> 0 | BZ19: =SUM(AW19:BY19) -> 80 | CA19: =VLOOKUP(J:J,'Agent wise'!A:C,3,0) -> Saran S | CB19: =INT(E19) -> 45931 | CC19: =IF(BZ19>=94.5, "Excellent", IF(BZ19>89.5, "Good", IF(BZ19>84.5, "Average", "FC"))) -> FC | CJ19: =DAY(E19) -> 1 | CK19: =MONTH(E19) -> 10 | CL19: =YEAR(E19) -> 2025
A20: 45667.96 | B20: saranchirayinkeezhu720@gmail.com | C20: 0 / 40 | D20: Saran | E20: 45931 | F20: Wireless | G20: 45667 | H20: 9884511639 | I20: 128 | J20: SBM550 | K20: Tamil | L20: Tamil Nadu | M20: Yes | N20: Yes | O20: Yes | P20: Yes | Q20: Yes | R20: Yes | S20: Yes | T20: Yes | U20: No | V20: Yes | W20: Yes | X20: Yes | Y20: Yes | Z20: Yes | AA20: Yes | AB20: No | AC20: Yes | AD20: Yes | AE20: Yes | AF20: Not Applicable | AG20: Yes | AH20: Not Applicable | AI20: No | AJ20: Yes | AK20: Yes | AL20: No | AM20: Yes | AN20: Yes | AO20: Yes | AP20: Not taken complaint for customer, No apology | AQ20: Customer concern -Customer called for network issue . Resolution shared - Advisor done complete probing to customer as per call. | AR20: Prepaid | AS20: VOICE SERVICES | AT20: WRONG ROUTING OF CALL | AW20: =IF(OR(M20="YES", M20="Not Applicable"), AW$1, "0") -> 6 | AX20: =IF(OR(N20="YES", N20="Not Applicable"), AX$1, "0") -> 4 | AY20: =IF(OR(O20="YES", O20="Not Applicable"), AY$1, "0") -> 4 | AZ20: =IF(OR(P20="YES", P20="Not Applicable"), AZ$1, "0") -> 2 | BA20: =IF(OR(Q20="YES", Q20="Not Applicable"), BA$1, "0") -> 4 | BB20: =IF(OR(R20="YES", R20="Not Applicable"), BB$1, "0") -> 4 | BC20: =IF(OR(S20="YES", S20="Not Applicable"), BC$1, "0") -> 4 | BD20: =IF(OR(T20="YES", T20="Not Applicable"), BD$1, "0") -> 2 | ... BY20: =IF(OR(AO20="YES", AO20="Not Applicable"), BY$1, "0") -> 0 | BZ20: =SUM(AW20:BY20) -> 90 | CA20: =VLOOKUP(J:J,'Agent wise'!A:C,3,0) -> Shakeer | CB20: =INT(E20) -> 45931 | CC20: =IF(BZ20>=94.5, "Excellent", IF(BZ20>89.5, "Good", IF(BZ20>84.5, "Average", "FC"))) -> Good | CJ20: =DAY(E20) -> 1 | CK20: =MONTH(E20) -> 10 | CL20: =YEAR(E20) -> 2025
A21: 45667.961 | B21: shakeerfazal11@gmail.com | C21: 0 / 40 | D21: Shakeer | E21: 45931 | F21: Wireless | G21: 45667 | H21: 9745718491 | I21: 199 | J21: SBM724 | K21: Malayalam | L21: Kerala | M21: Yes | N21: Yes | O21: Yes | P21: Yes | Q21: Yes | R21: Yes | S21: Yes | T21: Yes | U21: No | V21: Yes | W21: Yes | X21: Not Applicable | Y21: Yes | Z21: Yes | AA21: Yes | AB21: Yes | AC21: No | AD21: Yes | AE21: Yes | AF21: Not Applicable | AG21: Yes | AH21: Not Applicable | AI21: Yes | AJ21: Yes | AK21: Yes | AL21: No | AM21: Yes | AN21: Yes | AO21: Yes | AP21: Dead air, No further assistance | AQ21: Customer called and inquired about Weak signal related issue, Agent checked and taken poor coverage related complaint. but not followed required quality parameter properly. | AR21: Prepaid | AS21: COMPLAINT | AT21: POOR NETWORK COVERAGE | AW21: =IF(OR(M21="YES", M21="Not Applicable"), AW$1, "0") -> 6 | AX21: =IF(OR(N21="YES", N21="Not Applicable"), AX$1, "0") -> 4 | AY21: =IF(OR(O21="YES", O21="Not Applicable"), AY$1, "0") -> 4 | AZ21: =IF(OR(P21="YES", P21="Not Applicable"), AZ$1, "0") -> 2 | BA21: =IF(OR(Q21="YES", Q21="Not Applicable"), BA$1, "0") -> 4 | BB21: =IF(OR(R21="YES", R21="Not Applicable"), BB$1, "0") -> 4 | BC21: =IF(OR(S21="YES", S21="Not Applicable"), BC$1, "0") -> 4 | BD21: =IF(OR(T21="YES", T21="Not Applicable"), BD$1, "0") -> 2 | ... BY21: =IF(OR(AO21="YES", AO21="Not Applicable"), BY$1, "0") -> 0 | BZ21: =SUM(AW21:BY21) -> 92 | CA21: =VLOOKUP(J:J,'Agent wise'!A:C,3,0) -> Shiny | CB21: =INT(E21) -> 45931 | CC21: =IF(BZ21>=94.5, "Excellent", IF(BZ21>89.5, "Good", IF(BZ21>84.5, "Average", "FC"))) -> Good | CJ21: =DAY(E21) -> 1 | CK21: =MONTH(E21) -> 10 | CL21: =YEAR(E21) -> 2025
A22: 45667.964 | B22: shakeerfazal11@gmail.com | C22: 0 / 40 | D22: Shakeer | E22: 45931 | F22: Wireless | G22: 45667 | H22: 9446148925 | I22: 141 | J22: SBM724 | K22: Malayalam | L22: Kerala | M22: Yes | N22: Yes | O22: Yes | P22: Yes | Q22: Yes | R22: Yes | S22: Yes | T22: Yes | U22: No | V22: Yes | W22: Yes | X22: Not Applicable | Y22: Yes | Z22: Yes | AA22: Yes | AB22: Yes | AC22: No | AD22: Not Applicable | AE22: Yes | AF22: Not Applicable | AG22: Yes | AH22: Not Applicable | AI22: Yes | AJ22: Yes | AK22: Yes | AL22: No | AM22: Yes | AN22: Yes | AO22: Yes | AP22: No further assistance, Dead air observed | AQ22: Customer called and inquired about Weak signal related issue, Agent checked and taken poor coverage related complaint. But not followed required quality parameter properly. | AR22: Prepaid | AS22: COMPLAINT | AT22: POOR NETWORK COVERAGE | AW22: =IF(OR(M22="YES", M22="Not Applicable"), AW$1, "0") -> 6 | AX22: =IF(OR(N22="YES", N22="Not Applicable"), AX$1, "0") -> 4 | AY22: =IF(OR(O22="YES", O22="Not Applicable"), AY$1, "0") -> 4 | AZ22: =IF(OR(P22="YES", P22="Not Applicable"), AZ$1, "0") -> 2 | BA22: =IF(OR(Q22="YES", Q22="Not Applicable"), BA$1, "0") -> 4 | BB22: =IF(OR(R22="YES", R22="Not Applicable"), BB$1, "0") -> 4 | BC22: =IF(OR(S22="YES", S22="Not Applicable"), BC$1, "0") -> 4 | BD22: =IF(OR(T22="YES", T22="Not Applicable"), BD$1, "0") -> 2 | ... BY22: =IF(OR(AO22="YES", AO22="Not Applicable"), BY$1, "0") -> 0 | BZ22: =SUM(AW22:BY22) -> 92 | CA22: =VLOOKUP(J:J,'Agent wise'!A:C,3,0) -> Shiny | CB22: =INT(E22) -> 45931 | CC22: =IF(BZ22>=94.5, "Excellent", IF(BZ22>89.5, "Good", IF(BZ22>84.5, "Average", "FC"))) -> Good | CJ22: =DAY(E22) -> 1 | CK22: =MONTH(E22) -> 10 | CL22: =YEAR(E22) -> 2025
A23: 45667.965 | B23: saranchirayinkeezhu720@gmail.com | C23: 0 / 40 | D23: Saran | E23: 45931 | F23: Wireless | G23: 45667 | H23: 8547100648 | I23: 160 | J23: SBM963 | K23: Malayalam | L23: Kerala | M23: Yes | N23: Yes | O23: Yes | P23: Yes | Q23: Yes | R23: Yes | S23: Yes | T23: Yes | U23: No | V23: Yes | W23: Yes | X23: Yes | Y23: Yes | Z23: Yes | AA23: Yes | AB23: Not Applicable | AC23: Not Applicable | AD23: Yes | AE23: Yes | AF23: Not Applicable | AG23: Yes | AH23: Not Applicable | AI23: Not Applicable | AJ23: Yes | AK23: Yes | AL23: No | AM23: Yes | AN23: Yes | AO23: Yes | AP23: No further assistance | AQ23: Customer concern -Customer called for wrong recharge issue. Resolution shared - Advisor done complete probing to customer as per call. | AR23: Prepaid | AS23: RECHARGE ISSUE | AT23: WRONG RECHARGE | AW23: =IF(OR(M23="YES", M23="Not Applicable"), AW$1, "0") -> 6 | AX23: =IF(OR(N23="YES", N23="Not Applicable"), AX$1, "0") -> 4 | AY23: =IF(OR(O23="YES", O23="Not Applicable"), AY$1, "0") -> 4 | AZ23: =IF(OR(P23="YES", P23="Not Applicable"), AZ$1, "0") -> 2 | BA23: =IF(OR(Q23="YES", Q23="Not Applicable"), BA$1, "0") -> 4 | BB23: =IF(OR(R23="YES", R23="Not Applicable"), BB$1, "0") -> 4 | BC23: =IF(OR(S23="YES", S23="Not Applicable"), BC$1, "0") -> 4 | BD23: =IF(OR(T23="YES", T23="Not Applicable"), BD$1, "0") -> 2 | ... BY23: =IF(OR(AO23="YES", AO23="Not Applicable"), BY$1, "0") -> 0 | BZ23: =SUM(AW23:BY23) -> 96 | CA23: =VLOOKUP(J:J,'Agent wise'!A:C,3,0) -> Shakeer | CB23: =INT(E23) -> 45931 | CC23: =IF(BZ23>=94.5, "Excellent", IF(BZ23>89.5, "Good", IF(BZ23>84.5, "Average", "FC"))) -> Excellent | CJ23: =DAY(E23) -> 1 | CK23: =MONTH(E23) -> 10 | CL23: =YEAR(E23) -> 2025
... A28: 45698.006 | B28: saranchirayinkeezhu720@gmail.com | C28: 0 / 40 | D28: Saran | E28: 45931 | F28: Wireless | G28: 45667 | H28: 7845308011 | I28: 128 | J28: VPS229 | K28: Tamil | L28: Tamil Nadu | M28: Yes | N28: Yes | O28: Yes | P28: Yes | Q28: Yes | R28: Yes | S28: Yes | T28: Yes | U28: No | V28: Yes | W28: Yes | X28: Yes | Y28: Yes | Z28: Yes | AA28: No | AB28: No | AC28: No | AD28: Yes | AE28: Yes | AF28: Not Applicable | AG28: Yes | AH28: Not Applicable | AI28: Not Applicable | AJ28: Yes | AK28: Yes | AL28: No | AM28: Yes | AN28: Yes | AO28: Yes | AP28: Not use empathy and apology, Dead air. | AQ28: Customer concern -Customer called for not getting incoming calls . Resolution shared - Advisor done complete probing to customer as per call. | AR28: Prepaid | AS28: CALL SERVICES | AT28: RECHARGE PLAN NOT AVAILABLE | AW28: =IF(OR(M28="YES", M28="Not Applicable"), AW$1, "0") -> 6 | AX28: =IF(OR(N28="YES", N28="Not Applicable"), AX$1, "0") -> 4 | AY28: =IF(OR(O28="YES", O28="Not Applicable"), AY$1, "0") -> 4 | AZ28: =IF(OR(P28="YES", P28="Not Applicable"), AZ$1, "0") -> 2 | BA28: =IF(OR(Q28="YES", Q28="Not Applicable"), BA$1, "0") -> 4 | BB28: =IF(OR(R28="YES", R28="Not Applicable"), BB$1, "0") -> 4 | BC28: =IF(OR(S28="YES", S28="Not Applicable"), BC$1, "0") -> 4 | BD28: =IF(OR(T28="YES", T28="Not Applicable"), BD$1, "0") -> 2 | ... BY28: =IF(OR(AO28="YES", AO28="Not Applicable"), BY$1, "0") -> 0 | BZ28: =SUM(AW28:BY28) -> 86 | CA28: =VLOOKUP(J:J,'Agent wise'!A:C,3,0) -> Shakeer | CB28: =INT(E28) -> 45931 | CC28: =IF(BZ28>=94.5, "Excellent", IF(BZ28>89.5, "Good", IF(BZ28>84.5, "Average", "FC"))) -> Average | CJ28: =DAY(E28) -> 1 | CK28: =MONTH(E28) -> 10 | CL28: =YEAR(E28) -> 2025
A29: 45698.427 | B29: adharshleewvan003@gmail.com | C29: 0 / 40 | D29: Adharsh | E29: 45931 | F29: MNP OBD | G29: 9/30/2025 | H29: 9751204478 | I29: 181 | J29: SBM792 | K29: Tamil | L29: Tamil Nadu | M29: Yes | N29: Yes | O29: Yes | P29: Yes | Q29: Yes | R29: Yes | S29: Yes | T29: Yes | U29: Yes | V29: Yes | W29: Yes | X29: Yes | Y29: Yes | Z29: Yes | AA29: Yes | AB29: Yes | AC29: Not Applicable | AD29: Yes | AE29: No | AF29: Yes | AG29: Yes | AH29: Not Applicable | AI29: Not Applicable | AJ29: Yes | AK29: Yes | AL29: Yes | AM29: Yes | AN29: Yes | AO29: Yes | AP29: Maintained focus on caller's problem | AQ29: Reason for PORTING request: Has two SIM CARD in BSNL, so customer porting out to other network Resolution provided: Didn't completely Convinced customer to keep both the SIM in BSNL | AR29: Prepaid | AS29: QUERY | AT29: NOT AGREED | AW29: =IF(OR(M29="YES", M29="Not Applicable"), AW$1, "0") -> 6 | AX29: =IF(OR(N29="YES", N29="Not Applicable"), AX$1, "0") -> 4 | AY29: =IF(OR(O29="YES", O29="Not Applicable"), AY$1, "0") -> 4 | AZ29: =IF(OR(P29="YES", P29="Not Applicable"), AZ$1, "0") -> 2 | BA29: =IF(OR(Q29="YES", Q29="Not Applicable"), BA$1, "0") -> 4 | BB29: =IF(OR(R29="YES", R29="Not Applicable"), BB$1, "0") -> 4 | BC29: =IF(OR(S29="YES", S29="Not Applicable"), BC$1, "0") -> 4 | BD29: =IF(OR(T29="YES", T29="Not Applicable"), BD$1, "0") -> 2 | ... BY29: =IF(OR(AO29="YES", AO29="Not Applicable"), BY$1, "0") -> 0 | BZ29: =SUM(AW29:BY29) -> 96 | CA29: =VLOOKUP(J:J,'Agent wise'!A:C,3,0) -> Adharsh | CB29: =INT(E29) -> 45931 | CC29: =IF(BZ29>=94.5, "Excellent", IF(BZ29>89.5, "Good", IF(BZ29>84.5, "Average", "FC"))) -> Excellent | CJ29: =DAY(E29) -> 1 | CK29: =MONTH(E29) -> 10 | CL29: =YEAR(E29) -> 2025
A30: 45698.444 | B30: priyankajino2013@gmail.com | C30: 0 / 40 | D30: Priyanka | E30: 45932 | F30: Wireless | G30: 45667 | H30: 8330068261 | I30: 157 | J30: VPS258 | K30: Malayalam | L30: Kerala | M30: Yes | N30: Yes | O30: Yes | P30: Yes | Q30: Yes | R30: No | S30: Yes | T30: Yes | U30: No | V30: Yes | W30: Yes | X30: No | Y30: Yes | Z30: Yes | AA30: No | AB30: Not Applicable | AC30: Not Applicable | AD30: Yes | AE30: No | AF30: Yes | AG30: No | AH30: Yes | AI30: Not Applicable | AJ30: Yes | AK30: Yes | AL30: No | AM30: Yes | AN30: Yes | AO30: No | AP30: AOI-dead air,empathy missing, | AQ30: Opening & Introduction â€“ Done Customer details captured â€“Done Customer concern -Customer ask data issue Resolution shared - Advisor complete probing to customers as per call setting provide Closing as per standard - Done. AOI-dead air,empathy missing,accurent information not done | AR30: Prepaid | AS30: RECHARGE ISSUE | AT30: DOUBLE RECHARGE | AW30: =IF(OR(M30="YES", M30="Not Applicable"), AW$1, "0") -> 6 | AX30: =IF(OR(N30="YES", N30="Not Applicable"), AX$1, "0") -> 4 | AY30: =IF(OR(O30="YES", O30="Not Applicable"), AY$1, "0") -> 4 | AZ30: =IF(OR(P30="YES", P30="Not Applicable"), AZ$1, "0") -> 2 | BA30: =IF(OR(Q30="YES", Q30="Not Applicable"), BA$1, "0") -> 4 | BB30: =IF(OR(R30="YES", R30="Not Applicable"), BB$1, "0") -> 0 | BC30: =IF(OR(S30="YES", S30="Not Applicable"), BC$1, "0") -> 4 | BD30: =IF(OR(T30="YES", T30="Not Applicable"), BD$1, "0") -> 2 | ... BY30: =IF(OR(AO30="YES", AO30="Not Applicable"), BY$1, "0") -> 0 | BZ30: =SUM(AW30:BY30) -> 74 | CA30: =VLOOKUP(J:J,'Agent wise'!A:C,3,0) -> Adharsh | CB30: =INT(E30) -> 45932 | CC30: =IF(BZ30>=94.5, "Excellent", IF(BZ30>89.5, "Good", IF(BZ30>84.5, "Average", "FC"))) -> FC | CJ30: =DAY(E30) -> 2 | CK30: =MONTH(E30) -> 10 | CL30: =YEAR(E30) -> 2025
A31: 45698.452 | B31: priyankajino2013@gmail.com | C31: 0 / 40 | D31: Priyanka | E31: 45932 | F31: Wireless | G31: 45667 | H31: 8089911694 | I31: 145 | J31: SBM482 | K31: Malayalam | L31: Kerala | M31: Yes | N31: Yes | O31: Yes | P31: Yes | Q31: Yes | R31: No | S31: Yes | T31: Yes | U31: Yes | V31: Yes | W31: Yes | X31: Yes | Y31: Yes | Z31: Yes | AA31: No | AB31: Yes | AC31: Yes | AD31: Yes | AE31: Yes | AF31: Yes | AG31: Yes | AH31: Yes | AI31: Not Applicable | AJ31: Yes | AK31: Yes | AL31: Yes | AM31: Yes | AN31: Yes | AO31: Yes | AP31: AOI-empathy missing, | AQ31: Opening & Introduction â€“ Done Customer details captured â€“Done Customer concern -Customer ask recharge issue Resolution shared - Advisor complete probing to customers as per call inactive stage Closing as per standard - Done. AOI-empathy missing, | AR31: Prepaid | AS31: PLANS AND VALIDITY DETAILS | AT31: ENQUIRY ON BALANCE AND VALIDITY | AW31: =IF(OR(M31="YES", M31="Not Applicable"), AW$1, "0") -> 6 | AX31: =IF(OR(N31="YES", N31="Not Applicable"), AX$1, "0") -> 4 | AY31: =IF(OR(O31="YES", O31="Not Applicable"), AY$1, "0") -> 4 | AZ31: =IF(OR(P31="YES", P31="Not Applicable"), AZ$1, "0") -> 2 | BA31: =IF(OR(Q31="YES", Q31="Not Applicable"), BA$1, "0") -> 4 | BB31: =IF(OR(R31="YES", R31="Not Applicable"), BB$1, "0") -> 0 | BC31: =IF(OR(S31="YES", S31="Not Applicable"), BC$1, "0") -> 4 | BD31: =IF(OR(T31="YES", T31="Not Applicable"), BD$1, "0") -> 2 | ... BY31: =IF(OR(AO31="YES", AO31="Not Applicable"), BY$1, "0") -> 0 | BZ31: =SUM(AW31:BY31) -> 92 | CA31: =VLOOKUP(J:J,'Agent wise'!A:C,3,0) -> #N/A | CB31: =INT(E31) -> 45932 | CC31: =IF(BZ31>=94.5, "Excellent", IF(BZ31>89.5, "Good", IF(BZ31>84.5, "Average", "FC"))) -> Good | CJ31: =DAY(E31) -> 2 | CK31: =MONTH(E31) -> 10 | CL31: =YEAR(E31) -> 2025
A32: 45698.47 | B32: priyankajino2013@gmail.com | C32: 0 / 40 | D32: Priyanka | E32: 45932 | F32: Wireless | G32: 45667 | H32: 8056585548 | I32: 248 | J32: VPS256 | K32: Tamil | L32: Tamil Nadu | M32: No | N32: Yes | O32: Yes | P32: Yes | Q32: Yes | R32: No | S32: Yes | T32: Yes | U32: Yes | V32: Yes | W32: Yes | X32: Yes | Y32: Yes | Z32: Yes | AA32: No | AB32: Yes | AC32: Yes | AD32: Yes | AE32: Yes | AF32: Yes | AG32: No | AH32: Yes | AI32: Not Applicable | AJ32: Yes | AK32: Yes | AL32: Yes | AM32: Yes | AN32: Yes | AO32: No | AP32: AOI-empathy missing,Greeted Customer | AQ32: Opening & Introduction â€“ Done Customer details captured â€“Done Customer concern -Customer ask recharge issue Resolution shared - Advisor complete probing to customers as per call inactive stage Closing as per standard - Done. AOI-empathy missing,Greeted Customer | AR32: Prepaid | AS32: SMS SERVICES | AT32: UNABLE TO SEND SMS | AW32: =IF(OR(M32="YES", M32="Not Applicable"), AW$1, "0") -> 0 | AX32: =IF(OR(N32="YES", N32="Not Applicable"), AX$1, "0") -> 4 | AY32: =IF(OR(O32="YES", O32="Not Applicable"), AY$1, "0") -> 4 | AZ32: =IF(OR(P32="YES", P32="Not Applicable"), AZ$1, "0") -> 2 | BA32: =IF(OR(Q32="YES", Q32="Not Applicable"), BA$1, "0") -> 4 | BB32: =IF(OR(R32="YES", R32="Not Applicable"), BB$1, "0") -> 0 | BC32: =IF(OR(S32="YES", S32="Not Applicable"), BC$1, "0") -> 4 | BD32: =IF(OR(T32="YES", T32="Not Applicable"), BD$1, "0") -> 2 | ... BY32: =IF(OR(AO32="YES", AO32="Not Applicable"), BY$1, "0") -> 0 | BZ32: =SUM(AW32:BY32) -> 80 | CA32: =VLOOKUP(J:J,'Agent wise'!A:C,3,0) -> Saran S | CB32: =INT(E32) -> 45932 | CC32: =IF(BZ32>=94.5, "Excellent", IF(BZ32>89.5, "Good", IF(BZ32>84.5, "Average", "FC"))) -> FC | CJ32: =DAY(E32) -> 2 | CK32: =MONTH(E32) -> 10 | CL32: =YEAR(E32) -> 2025
A33: 45698.478 | B33: priyankajino2013@gmail.com | C33: 0 / 40 | D33: Priyanka | E33: 45932 | F33: Wireless | G33: 45667 | H33: 9400647054 | I33: 161 | J33: VPS253 | K33: Malayalam | L33: Kerala | M33: Yes | N33: Yes | O33: Yes | P33: Yes | Q33: Yes | R33: No | S33: Yes | T33: Yes | U33: Yes | V33: Yes | W33: Yes | X33: Yes | Y33: Yes | Z33: Yes | AA33: No | AB33: Yes | AC33: Yes | AD33: Yes | AE33: Yes | AF33: Yes | AG33: Yes | AH33: Yes | AI33: Yes | AJ33: Yes | AK33: Yes | AL33: Yes | AM33: Yes | AN33: Yes | AO33: Yes | AP33: AOI-empathy missing, | AQ33: Opening & Introduction â€“ Done Customer details captured â€“Done Customer concern -Customer ask sim converted Resolution shared - Advisor complete probing to customers as per call unified sim Closing as per standard - Done. AOI-empathy missing, | AR33: Prepaid | AS33: SIM | AT33: NEW SIM ACTIVATION PROCESS | AW33: =IF(OR(M33="YES", M33="Not Applicable"), AW$1, "0") -> 6 | AX33: =IF(OR(N33="YES", N33="Not Applicable"), AX$1, "0") -> 4 | AY33: =IF(OR(O33="YES", O33="Not Applicable"), AY$1, "0") -> 4 | AZ33: =IF(OR(P33="YES", P33="Not Applicable"), AZ$1, "0") -> 2 | BA33: =IF(OR(Q33="YES", Q33="Not Applicable"), BA$1, "0") -> 4 | BB33: =IF(OR(R33="YES", R33="Not Applicable"), BB$1, "0") -> 0 | BC33: =IF(OR(S33="YES", S33="Not Applicable"), BC$1, "0") -> 4 | BD33: =IF(OR(T33="YES", T33="Not Applicable"), BD$1, "0") -> 2 | ... BY33: =IF(OR(AO33="YES", AO33="Not Applicable"), BY$1, "0") -> 0 | BZ33: =SUM(AW33:BY33) -> 92 | CA33: =VLOOKUP(J:J,'Agent wise'!A:C,3,0) -> Adharsh | CB33: =INT(E33) -> 45932 | CC33: =IF(BZ33>=94.5, "Excellent", IF(BZ33>89.5, "Good", IF(BZ33>84.5, "Average", "FC"))) -> Good | CJ33: =DAY(E33) -> 2 | CK33: =MONTH(E33) -> 10 | CL33: =YEAR(E33) -> 2025
A34: 45698.479 | B34: adharshleewvan003@gmail.com | C34: 0 / 40 | D34: Adharsh | E34: 45931 | F34: MNP OBD | G34: 9/30/2025 | H34: 9894713944 | I34: 198 | J34: SBM744 | K34: Tamil | L34: Tamil Nadu | M34: Yes | N34: Yes | O34: Yes | P34: Yes | Q34: Yes | R34: Yes | S34: Yes | T34: Yes | U34: Yes | V34: Yes | W34: Yes | X34: Yes | Y34: Yes | Z34: Yes | AA34: Yes | AB34: Yes | AC34: Yes | AD34: Yes | AE34: No | AF34: Yes | AG34: Yes | AH34: Yes | AI34: Not Applicable | AJ34: Yes | AK34: Yes | AL34: Yes | AM34: Yes | AN34: Yes | AO34: No | AP34: Maintained focus on caller's problem, Tagging Accuracy | AQ34: Reason for PORTING request: Network issue Resolution provided: Complaint not taken, customer requested for call back | AR34: Prepaid | AS34: INCOMPLETE CALL | AT34: DISCONNECTED BY CUSTOMER | AW34: =IF(OR(M34="YES", M34="Not Applicable"), AW$1, "0") -> 6 | AX34: =IF(OR(N34="YES", N34="Not Applicable"), AX$1, "0") -> 4 | AY34: =IF(OR(O34="YES", O34="Not Applicable"), AY$1, "0") -> 4 | AZ34: =IF(OR(P34="YES", P34="Not Applicable"), AZ$1, "0") -> 2 | BA34: =IF(OR(Q34="YES", Q34="Not Applicable"), BA$1, "0") -> 4 | BB34: =IF(OR(R34="YES", R34="Not Applicable"), BB$1, "0") -> 4 | BC34: =IF(OR(S34="YES", S34="Not Applicable"), BC$1, "0") -> 4 | BD34: =IF(OR(T34="YES", T34="Not Applicable"), BD$1, "0") -> 2 | ... BY34: =IF(OR(AO34="YES", AO34="Not Applicable"), BY$1, "0") -> 0 | BZ34: =SUM(AW34:BY34) -> 96 | CA34: =VLOOKUP(J:J,'Agent wise'!A:C,3,0) -> Shiny | CB34: =INT(E34) -> 45931 | CC34: =IF(BZ34>=94.5, "Excellent", IF(BZ34>89.5, "Good", IF(BZ34>84.5, "Average", "FC"))) -> Excellent | CJ34: =DAY(E34) -> 1 | CK34: =MONTH(E34) -> 10 | CL34: =YEAR(E34) -> 2025
A35: 45698.496 | B35: priyankajino2013@gmail.com | C35: 0 / 40 | D35: Priyanka | E35: 45932 | F35: Wireless | G35: 45667 | H35: 8943722655 | I35: 163 | J35: VPS252 | K35: Malayalam | L35: Kerala | M35: Yes | N35: Yes | O35: Yes | P35: Yes | Q35: Yes | R35: No | S35: Yes | T35: Yes | U35: Yes | V35: Yes | W35: Yes | X35: Yes | Y35: Yes | Z35: Yes | AA35: No | AB35: Yes | AC35: No | AD35: Yes | AE35: Yes | AF35: Yes | AG35: No | AH35: Yes | AI35: Not Applicable | AJ35: Yes | AK35: Yes | AL35: Yes | AM35: Yes | AN35: Yes | AO35: Yes | AP35: AOI-empathy missing, probing not done,dead air | AQ35: Opening & Introduction â€“ Done Customer details captured â€“Done Customer concern -Customer ask sim converted Resolution shared - Advisor complete probing to customers as per call sim deactive Closing as per standard - Done. AOI-empathy missing, probing not done,dead air | AR35: Prepaid | AS35: SIM | AT35: SIM REPLACEMENT PROCESS | AW35: =IF(OR(M35="YES", M35="Not Applicable"), AW$1, "0") -> 6 | AX35: =IF(OR(N35="YES", N35="Not Applicable"), AX$1, "0") -> 4 | AY35: =IF(OR(O35="YES", O35="Not Applicable"), AY$1, "0") -> 4 | AZ35: =IF(OR(P35="YES", P35="Not Applicable"), AZ$1, "0") -> 2 | BA35: =IF(OR(Q35="YES", Q35="Not Applicable"), BA$1, "0") -> 4 | BB35: =IF(OR(R35="YES", R35="Not Applicable"), BB$1, "0") -> 0 | BC35: =IF(OR(S35="YES", S35="Not Applicable"), BC$1, "0") -> 4 | BD35: =IF(OR(T35="YES", T35="Not Applicable"), BD$1, "0") -> 2 | ... BY35: =IF(OR(AO35="YES", AO35="Not Applicable"), BY$1, "0") -> 0 | BZ35: =SUM(AW35:BY35) -> 82 | CA35: =VLOOKUP(J:J,'Agent wise'!A:C,3,0) -> Shiny | CB35: =INT(E35) -> 45932 | CC35: =IF(BZ35>=94.5, "Excellent", IF(BZ35>89.5, "Good", IF(BZ35>84.5, "Average", "FC"))) -> FC | CJ35: =DAY(E35) -> 2 | CK35: =MONTH(E35) -> 10 | CL35: =YEAR(E35) -> 2025
A36: 45698.503 | B36: adharshleewvan003@gmail.com | C36: 0 / 40 | D36: Adharsh | E36: 45932 | F36: MNP OBD | G36: 45667 | H36: 9487716094 | I36: 196 | J36: SBM554 | K36: Tamil | L36: Tamil Nadu | M36: Yes | N36: Yes | O36: Yes | P36: Yes | Q36: Yes | R36: Yes | S36: Yes | T36: Yes | U36: Yes | V36: Yes | W36: Yes | X36: Yes | Y36: Yes | Z36: Yes | AA36: Yes | AB36: Yes | AC36: Yes | AD36: Yes | AE36: Yes | AF36: Yes | AG36: Yes | AH36: Not Applicable | AI36: Not Applicable | AJ36: Yes | AK36: Yes | AL36: Yes | AM36: Yes | AN36: Yes | AO36: Yes | AP36: Good call | AQ36: Reason for PORTING request: Network issue Resolution provided: Complaint not taken, customer requested for call back | AR36: Prepaid | AS36: CALL BACK | AT36: REQUESTED TO CALLBACK | AW36: =IF(OR(M36="YES", M36="Not Applicable"), AW$1, "0") -> 6 | AX36: =IF(OR(N36="YES", N36="Not Applicable"), AX$1, "0") -> 4 | AY36: =IF(OR(O36="YES", O36="Not Applicable"), AY$1, "0") -> 4 | AZ36: =IF(OR(P36="YES", P36="Not Applicable"), AZ$1, "0") -> 2 | BA36: =IF(OR(Q36="YES", Q36="Not Applicable"), BA$1, "0") -> 4 | BB36: =IF(OR(R36="YES", R36="Not Applicable"), BB$1, "0") -> 4 | BC36: =IF(OR(S36="YES", S36="Not Applicable"), BC$1, "0") -> 4 | BD36: =IF(OR(T36="YES", T36="Not Applicable"), BD$1, "0") -> 2 | ... BY36: =IF(OR(AO36="YES", AO36="Not Applicable"), BY$1, "0") -> 0 | BZ36: =SUM(AW36:BY36) -> 100 | CA36: =VLOOKUP(J:J,'Agent wise'!A:C,3,0) -> Adharsh | CB36: =INT(E36) -> 45932 | CC36: =IF(BZ36>=94.5, "Excellent", IF(BZ36>89.5, "Good", IF(BZ36>84.5, "Average", "FC"))) -> Excellent | CJ36: =DAY(E36) -> 2 | CK36: =MONTH(E36) -> 10 | CL36: =YEAR(E36) -> 2025
A37: 45698.504 | B37: priyankajino2013@gmail.com | C37: 0 / 40 | D37: Priyanka | E37: 45932 | F37: Wireless | G37: 45667 | H37: 8330047076 | I37: 188 | J37: VPS251 | K37: Malayalam | L37: Kerala | M37: Yes | N37: Yes | O37: Yes | P37: Yes | Q37: Yes | R37: No | S37: No | T37: Yes | U37: Yes | V37: Yes | W37: Yes | X37: Yes | Y37: Yes | Z37: Yes | AA37: No | AB37: Yes | AC37: No | AD37: Yes | AE37: Yes | AF37: Yes | AG37: Yes | AH37: Yes | AI37: Not Applicable | AJ37: Yes | AK37: Yes | AL37: Yes | AM37: Yes | AN37: Yes | AO37: No | AP37: AOI-empathy missing,dead air, | AQ37: Opening & Introduction â€“ Done Customer details captured â€“Done Customer concern -Customer ask data issue Resolution shared - Advisor complete probing to customers as per call setting provide Closing as per standard - Done. AOI-empathy missing,dead air, | AR37: Prepaid | AS37: DATA SERVICES | AT37: UNABLE TO BROWSE DATA | AW37: =IF(OR(M37="YES", M37="Not Applicable"), AW$1, "0") -> 6 | AX37: =IF(OR(N37="YES", N37="Not Applicable"), AX$1, "0") -> 4 | AY37: =IF(OR(O37="YES", O37="Not Applicable"), AY$1, "0") -> 4 | AZ37: =IF(OR(P37="YES", P37="Not Applicable"), AZ$1, "0") -> 2 | BA37: =IF(OR(Q37="YES", Q37="Not Applicable"), BA$1, "0") -> 4 | BB37: =IF(OR(R37="YES", R37="Not Applicable"), BB$1, "0") -> 0 | BC37: =IF(OR(S37="YES", S37="Not Applicable"), BC$1, "0") -> 0 | BD37: =IF(OR(T37="YES", T37="Not Applicable"), BD$1, "0") -> 2 | ... BY37: =IF(OR(AO37="YES", AO37="Not Applicable"), BY$1, "0") -> 0 | BZ37: =SUM(AW37:BY37) -> 84 | CA37: =VLOOKUP(J:J,'Agent wise'!A:C,3,0) -> Shakeer | CB37: =INT(E37) -> 45932 | CC37: =IF(BZ37>=94.5, "Excellent", IF(BZ37>89.5, "Good", IF(BZ37>84.5, "Average", "FC"))) -> FC | CJ37: =DAY(E37) -> 2 | CK37: =MONTH(E37) -> 10 | CL37: =YEAR(E37) -> 2025
A38: 45698.519 | B38: priyankajino2013@gmail.com | C38: 0 / 50 | D38: Priyanka | E38: 45932 | F38: Wireless | G38: 45667 | H38: 8281797484 | I38: 141 | J38: VPS249 | K38: Malayalam | L38: Kerala | M38: Yes | N38: Yes | O38: Yes | P38: Yes | Q38: Yes | R38: No | S38: Yes | T38: Yes | U38: Yes | V38: Yes | W38: Yes | X38: Yes | Y38: Yes | Z38: Yes | AA38: No | AB38: Yes | AC38: Yes | AD38: Yes | AE38: Yes | AF38: Yes | AG38: Yes | AH38: Yes | AI38: Not Applicable | AJ38: Yes | AK38: Yes | AL38: Yes | AM38: Yes | AN38: Yes | AO38: Yes | AP38: AOI-empathy missing,probing not done | AQ38: Opening & Introduction â€“ Done Customer details captured â€“Done Customer concern -Customer ask network issue Resolution shared - Advisor complete probing to customers as per call setting provide Closing as per standard - Done. AOI-empathy missing,probing not done | AR38: Prepaid | AS38: SIM | AT38: REPLACED SIM NOT ACTIVATED | AU38: Good Call | AW38: =IF(OR(M38="YES", M38="Not Applicable"), AW$1, "0") -> 6 | AX38: =IF(OR(N38="YES", N38="Not Applicable"), AX$1, "0") -> 4 | AY38: =IF(OR(O38="YES", O38="Not Applicable"), AY$1, "0") -> 4 | AZ38: =IF(OR(P38="YES", P38="Not Applicable"), AZ$1, "0") -> 2 | BA38: =IF(OR(Q38="YES", Q38="Not Applicable"), BA$1, "0") -> 4 | BB38: =IF(OR(R38="YES", R38="Not Applicable"), BB$1, "0") -> 0 | BC38: =IF(OR(S38="YES", S38="Not Applicable"), BC$1, "0") -> 4 | BD38: =IF(OR(T38="YES", T38="Not Applicable"), BD$1, "0") -> 2 | ... BY38: =IF(OR(AO38="YES", AO38="Not Applicable"), BY$1, "0") -> 0 | BZ38: =SUM(AW38:BY38) -> 92 | CA38: =VLOOKUP(J:J,'Agent wise'!A:C,3,0) -> Adharsh | CB38: =INT(E38) -> 45932 | CC38: =IF(BZ38>=94.5, "Excellent", IF(BZ38>89.5, "Good", IF(BZ38>84.5, "Average", "FC"))) -> Good | CJ38: =DAY(E38) -> 2 | CK38: =MONTH(E38) -> 10 | CL38: =YEAR(E38) -> 2025
A39: 45698.523 | B39: amalbabu142@gmail.com | C39: 0 / 50 | D39: Amal | E39: 45932 | F39: Wireline | G39: 45698 | H39: 8807707635 | I39: 181 | J39: SBM653 | K39: Tamil | L39: Tamil Nadu | M39: Yes | N39: Yes | O39: No | P39: Yes | Q39: Yes | R39: Yes | S39: Yes | T39: Yes | U39: Yes | V39: Yes | W39: Yes | X39: Yes | Y39: Yes | Z39: Yes | AA39: Yes | AB39: Yes | AC39: Yes | AD39: Yes | AE39: Yes | AF39: Yes | AG39: Yes | AH39: Not Applicable | AI39: Not Applicable | AJ39: Yes | AK39: Yes | AL39: No | AM39: Yes | AN39: No | AO39: Yes | AP39: Failed to ask Asked Caller Name and Script adherence | AQ39: The customer called and Inquiry about skypro iptv details agent checked and Information given Properly | AR39: Postpaid | AS39: skypro iptv | AT39: skypro iptv | AU39: Good Call | AW39: =IF(OR(M39="YES", M39="Not Applicable"), AW$1, "0") -> 6 | AX39: =IF(OR(N39="YES", N39="Not Applicable"), AX$1, "0") -> 4 | AY39: =IF(OR(O39="YES", O39="Not Applicable"), AY$1, "0") -> 0 | AZ39: =IF(OR(P39="YES", P39="Not Applicable"), AZ$1, "0") -> 2 | BA39: =IF(OR(Q39="YES", Q39="Not Applicable"), BA$1, "0") -> 4 | BB39: =IF(OR(R39="YES", R39="Not Applicable"), BB$1, "0") -> 4 | BC39: =IF(OR(S39="YES", S39="Not Applicable"), BC$1, "0") -> 4 | BD39: =IF(OR(T39="YES", T39="Not Applicable"), BD$1, "0") -> 2 | ... BY39: =IF(OR(AO39="YES", AO39="Not Applicable"), BY$1, "0") -> 0 | BZ39: =SUM(AW39:BY39) -> 96 | CA39: =VLOOKUP(J:J,'Agent wise'!A:C,3,0) -> Amal | CB39: =INT(E39) -> 45932 | CC39: =IF(BZ39>=94.5, "Excellent", IF(BZ39>89.5, "Good", IF(BZ39>84.5, "Average", "FC"))) -> Excellent | CJ39: =DAY(E39) -> 2 | CK39: =MONTH(E39) -> 10 | CL39: =YEAR(E39) -> 2025
A40: 45698.529 | B40: amalbabu142@gmail.com | C40: 0 / 50 | D40: Amal | E40: 45932 | F40: Wireline | G40: 45698 | H40: 7306503357 | I40: 163 | J40: SBM963 | K40: Malayalam | L40: Kerala | M40: Yes | N40: Yes | O40: Yes | P40: Yes | Q40: Yes | R40: Yes | S40: Yes | T40: Yes | U40: Yes | V40: Yes | W40: Yes | X40: Yes | Y40: Yes | Z40: Yes | AA40: Yes | AB40: Yes | AC40: Not Applicable | AD40: Yes | AE40: Yes | AF40: Yes | AG40: Yes | AH40: Yes | AI40: Not Applicable | AJ40: Yes | AK40: Yes | AL40: Yes | AM40: Yes | AN40: Yes | AO40: Yes | AP40: Good Call | AQ40: The customer called and Inquiry About Old connection Reactivation related Issue, agent checked and Information given Properly | AR40: Postpaid | AS40: SERVICE -OTHER(REMARK) | AT40: SERVICE -OTHER(REMARK) | AU40: Good Call | AW40: =IF(OR(M40="YES", M40="Not Applicable"), AW$1, "0") -> 6 | AX40: =IF(OR(N40="YES", N40="Not Applicable"), AX$1, "0") -> 4 | AY40: =IF(OR(O40="YES", O40="Not Applicable"), AY$1, "0") -> 4 | AZ40: =IF(OR(P40="YES", P40="Not Applicable"), AZ$1, "0") -> 2 | BA40: =IF(OR(Q40="YES", Q40="Not Applicable"), BA$1, "0") -> 4 | BB40: =IF(OR(R40="YES", R40="Not Applicable"), BB$1, "0") -> 4 | BC40: =IF(OR(S40="YES", S40="Not Applicable"), BC$1, "0") -> 4 | BD40: =IF(OR(T40="YES", T40="Not Applicable"), BD$1, "0") -> 2 | ... BY40: =IF(OR(AO40="YES", AO40="Not Applicable"), BY$1, "0") -> 0 | BZ40: =SUM(AW40:BY40) -> 100 | CA40: =VLOOKUP(J:J,'Agent wise'!A:C,3,0) -> Shakeer | CB40: =INT(E40) -> 45932 | CC40: =IF(BZ40>=94.5, "Excellent", IF(BZ40>89.5, "Good", IF(BZ40>84.5, "Average", "FC"))) -> Excellent | CJ40: =DAY(E40) -> 2 | CK40: =MONTH(E40) -> 10 | CL40: =YEAR(E40) -> 2025
A41: 45698.53 | B41: priyankajino2013@gmail.com | C41: 0 / 50 | D41: Priyanka | E41: 45932 | F41: Wireless | G41: 45667 | H41: 9400651030 | I41: 148 | J41: VPS248 | K41: Malayalam | L41: Kerala | M41: Yes | N41: Yes | O41: Yes | P41: Yes | Q41: Yes | R41: Yes | S41: Yes | T41: Yes | U41: Yes | V41: Yes | W41: Yes | X41: Yes | Y41: Yes | Z41: Yes | AA41: No | AB41: Yes | AC41: No | AD41: Not Applicable | AE41: Yes | AF41: Yes | AG41: Yes | AH41: Yes | AI41: Not Applicable | AJ41: Yes | AK41: Yes | AL41: Yes | AM41: Yes | AN41: Yes | AO41: No | AP41: AOI-empathy missing,probing not donev | AQ41: Opening & Introduction â€“ Done Customer details captured â€“Done Customer concern -Customer ask sim comvert Resolution shared - Advisor complete probing to customers as per call 4g sim details provide Closing as per standard - Done. AOI-empathy missing,probing not done | AR41: Prepaid | AS41: DATA SERVICES | AT41: DATA SERVICES | AU41: Good Call | AW41: =IF(OR(M41="YES", M41="Not Applicable"), AW$1, "0") -> 6 | AX41: =IF(OR(N41="YES", N41="Not Applicable"), AX$1, "0") -> 4 | AY41: =IF(OR(O41="YES", O41="Not Applicable"), AY$1, "0") -> 4 | AZ41: =IF(OR(P41="YES", P41="Not Applicable"), AZ$1, "0") -> 2 | BA41: =IF(OR(Q41="YES", Q41="Not Applicable"), BA$1, "0") -> 4 | BB41: =IF(OR(R41="YES", R41="Not Applicable"), BB$1, "0") -> 4 | BC41: =IF(OR(S41="YES", S41="Not Applicable"), BC$1, "0") -> 4 | BD41: =IF(OR(T41="YES", T41="Not Applicable"), BD$1, "0") -> 2 | ... BY41: =IF(OR(AO41="YES", AO41="Not Applicable"), BY$1, "0") -> 0 | BZ41: =SUM(AW41:BY41) -> 92 | CA41: =VLOOKUP(J:J,'Agent wise'!A:C,3,0) -> Shakeer | CB41: =INT(E41) -> 45932 | CC41: =IF(BZ41>=94.5, "Excellent", IF(BZ41>89.5, "Good", IF(BZ41>84.5, "Average", "FC"))) -> Good | CJ41: =DAY(E41) -> 2 | CK41: =MONTH(E41) -> 10 | CL41: =YEAR(E41) -> 2025
A42: 45698.535 | B42: amalbabu142@gmail.com | C42: 0 / 50 | D42: Amal | E42: 45932 | F42: Wireline | G42: 45698 | H42: 9633508987 | I42: 174 | J42: VPS181 | K42: Malayalam | L42: Kerala | M42: Yes | N42: Yes | O42: Yes | P42: Yes | Q42: Yes | R42: Yes | S42: Yes | T42: Yes | U42: Yes | V42: Yes | W42: Yes | X42: Yes | Y42: Yes | Z42: Yes | AA42: Yes | AB42: Yes | AC42: Not Applicable | AD42: Yes | AE42: Yes | AF42: Yes | AG42: Yes | AH42: Yes | AI42: No | AJ42: Yes | AK42: Yes | AL42: No | AM42: Yes | AN42: Yes | AO42: Yes | AP42: Failed to Provide the complaint number and Script adherence | AQ42: The customer called and Inquiry About data not getting related Issue agent checked and Booked a complaint | AR42: Postpaid | AS42: NO INTERNET CONNECTIVITY | AT42: NO INTERNET CONNECTIVITY | AU42: Good Call | AW42: =IF(OR(M42="YES", M42="Not Applicable"), AW$1, "0") -> 6 | AX42: =IF(OR(N42="YES", N42="Not Applicable"), AX$1, "0") -> 4 | AY42: =IF(OR(O42="YES", O42="Not Applicable"), AY$1, "0") -> 4 | AZ42: =IF(OR(P42="YES", P42="Not Applicable"), AZ$1, "0") -> 2 | BA42: =IF(OR(Q42="YES", Q42="Not Applicable"), BA$1, "0") -> 4 | BB42: =IF(OR(R42="YES", R42="Not Applicable"), BB$1, "0") -> 4 | BC42: =IF(OR(S42="YES", S42="Not Applicable"), BC$1, "0") -> 4 | BD42: =IF(OR(T42="YES", T42="Not Applicable"), BD$1, "0") -> 2 | ... BY42: =IF(OR(AO42="YES", AO42="Not Applicable"), BY$1, "0") -> 0 | BZ42: =SUM(AW42:BY42) -> 96 | CA42: =VLOOKUP(J:J,'Agent wise'!A:C,3,0) -> Amal | CB42: =INT(E42) -> 45932 | CC42: =IF(BZ42>=94.5, "Excellent", IF(BZ42>89.5, "Good", IF(BZ42>84.5, "Average", "FC"))) -> Excellent | CJ42: =DAY(E42) -> 2 | CK42: =MONTH(E42) -> 10 | CL42: =YEAR(E42) -> 2025
A43: 45698.537 | B43: priyankajino2013@gmail.com | C43: 0 / 50 | D43: Priyanka | E43: 45932 | F43: Wireless | G43: 45667 | H43: 9497774987 | I43: 154 | J43: VPS247 | K43: Malayalam | L43: Kerala | M43: Yes | N43: Yes | O43: Yes | P43: Yes | Q43: Yes | R43: Yes | S43: Yes | T43: Yes | U43: Yes | V43: Yes | W43: Yes | X43: Yes | Y43: Yes | Z43: Yes | AA43: No | AB43: Yes | AC43: No | AD43: Yes | AE43: Yes | AF43: Yes | AG43: Yes | AH43: Yes | AI43: Not Applicable | AJ43: Yes | AK43: Yes | AL43: Yes | AM43: Yes | AN43: Yes | AO43: Yes | AP43: AOI-empathy missing,dead air | AQ43: Opening & Introduction â€“ Done Customer details captured â€“Done Customer concern -Customer ask recharge issue Resolution shared - Advisor complete probing to customers as per call main account blance maintance then call back Closing as per standard - Done. AOI-empathy missing,dead air | AR43: Prepaid | AS43: RECHARGE ISSUE | AT43: WRONG RECHARGE | AU43: Good Call | AW43: =IF(OR(M43="YES", M43="Not Applicable"), AW$1, "0") -> 6 | AX43: =IF(OR(N43="YES", N43="Not Applicable"), AX$1, "0") -> 4 | AY43: =IF(OR(O43="YES", O43="Not Applicable"), AY$1, "0") -> 4 | AZ43: =IF(OR(P43="YES", P43="Not Applicable"), AZ$1, "0") -> 2 | BA43: =IF(OR(Q43="YES", Q43="Not Applicable"), BA$1, "0") -> 4 | BB43: =IF(OR(R43="YES", R43="Not Applicable"), BB$1, "0") -> 4 | BC43: =IF(OR(S43="YES", S43="Not Applicable"), BC$1, "0") -> 4 | BD43: =IF(OR(T43="YES", T43="Not Applicable"), BD$1, "0") -> 2 | ... BY43: =IF(OR(AO43="YES", AO43="Not Applicable"), BY$1, "0") -> 0 | BZ43: =SUM(AW43:BY43) -> 92 | CA43: =VLOOKUP(J:J,'Agent wise'!A:C,3,0) -> Shiny | CB43: =INT(E43) -> 45932 | CC43: =IF(BZ43>=94.5, "Excellent", IF(BZ43>89.5, "Good", IF(BZ43>84.5, "Average", "FC"))) -> Good | CJ43: =DAY(E43) -> 2 | CK43: =MONTH(E43) -> 10 | CL43: =YEAR(E43) -> 2025
A44: 45698.557 | B44: amalbabu142@gmail.com | C44: 0 / 50 | D44: Amal | E44: 45932 | F44: Wireline | G44: 45698 | H44: 7339583437 | I44: 165 | J44: SBM618 | K44: Tamil | L44: Tamil Nadu | M44: Yes | N44: Yes | O44: Yes | P44: Yes | Q44: Yes | R44: Yes | S44: Yes | T44: Yes | U44: Yes | V44: Yes | W44: Yes | X44: Yes | Y44: Yes | Z44: Yes | AA44: Yes | AB44: Yes | AC44: Not Applicable | AD44: Yes | AE44: Yes | AF44: Yes | AG44: Yes | AH44: Not Applicable | AI44: Not Applicable | AJ44: Yes | AK44: Yes | AL44: No | AM44: Yes | AN44: Yes | AO44: Yes | AP44: Script not Providing properly | AQ44: The customer called and Inquiry about Bill Payment related Issue, Agent checked and Information given properly | AR44: Postpaid | AS44: INVOICE - REQUEST A DETAILED BILL REPORT | AT44: INVOICE - REQUEST A DETAILED BILL REPORT | AU44: Good Call | AW44: =IF(OR(M44="YES", M44="Not Applicable"), AW$1, "0") -> 6 | AX44: =IF(OR(N44="YES", N44="Not Applicable"), AX$1, "0") -> 4 | AY44: =IF(OR(O44="YES", O44="Not Applicable"), AY$1, "0") -> 4 | AZ44: =IF(OR(P44="YES", P44="Not Applicable"), AZ$1, "0") -> 2 | BA44: =IF(OR(Q44="YES", Q44="Not Applicable"), BA$1, "0") -> 4 | BB44: =IF(OR(R44="YES", R44="Not Applicable"), BB$1, "0") -> 4 | BC44: =IF(OR(S44="YES", S44="Not Applicable"), BC$1, "0") -> 4 | BD44: =IF(OR(T44="YES", T44="Not Applicable"), BD$1, "0") -> 2 | ... BY44: =IF(OR(AO44="YES", AO44="Not Applicable"), BY$1, "0") -> 0 | BZ44: =SUM(AW44:BY44) -> 100 | CA44: =VLOOKUP(J:J,'Agent wise'!A:C,3,0) -> Amal | CB44: =INT(E44) -> 45932 | CC44: =IF(BZ44>=94.5, "Excellent", IF(BZ44>89.5, "Good", IF(BZ44>84.5, "Average", "FC"))) -> Excellent | CJ44: =DAY(E44) -> 2 | CK44: =MONTH(E44) -> 10 | CL44: =YEAR(E44) -> 2025
A45: 45698.562 | B45: amalbabu142@gmail.com | C45: 0 / 50 | D45: Amal | E45: 45932 | F45: Wireline | G45: 45698 | H45: 9840390388 | I45: 247 | J45: SBM794 | K45: Tamil | L45: Tamil Nadu | M45: Yes | N45: Yes | O45: Yes | P45: Yes | Q45: Yes | R45: Yes | S45: Yes | T45: Yes | U45: Yes | V45: Yes | W45: Yes | X45: Yes | Y45: Yes | Z45: Yes | AA45: Yes | AB45: Yes | AC45: Not Applicable | AD45: Yes | AE45: Yes | AF45: Yes | AG45: Yes | AH45: Not Applicable | AI45: Yes | AJ45: Yes | AK45: Yes | AL45: Yes | AM45: Yes | AN45: Yes | AO45: Yes | AP45: Good call | AQ45: The customer called and Inquiry about Internet not getting related Issue ,Agent checked and booked a complaint | AR45: Postpaid | AS45: FAULT - NO INTERNET CONNECTIVITY | AT45: FAULT - NO INTERNET CONNECTIVITY | AU45: Good Call | AW45: =IF(OR(M45="YES", M45="Not Applicable"), AW$1, "0") -> 6 | AX45: =IF(OR(N45="YES", N45="Not Applicable"), AX$1, "0") -> 4 | AY45: =IF(OR(O45="YES", O45="Not Applicable"), AY$1, "0") -> 4 | AZ45: =IF(OR(P45="YES", P45="Not Applicable"), AZ$1, "0") -> 2 | BA45: =IF(OR(Q45="YES", Q45="Not Applicable"), BA$1, "0") -> 4 | BB45: =IF(OR(R45="YES", R45="Not Applicable"), BB$1, "0") -> 4 | BC45: =IF(OR(S45="YES", S45="Not Applicable"), BC$1, "0") -> 4 | BD45: =IF(OR(T45="YES", T45="Not Applicable"), BD$1, "0") -> 2 | ... BY45: =IF(OR(AO45="YES", AO45="Not Applicable"), BY$1, "0") -> 0 | BZ45: =SUM(AW45:BY45) -> 100 | CA45: =VLOOKUP(J:J,'Agent wise'!A:C,3,0) -> Amal | CB45: =INT(E45) -> 45932 | CC45: =IF(BZ45>=94.5, "Excellent", IF(BZ45>89.5, "Good", IF(BZ45>84.5, "Average", "FC"))) -> Excellent | CJ45: =DAY(E45) -> 2 | CK45: =MONTH(E45) -> 10 | CL45: =YEAR(E45) -> 2025
A46: 45698.585 | B46: nehafire4444@gmail.com | C46: 0 / 50 | D46: Sneha | E46: 45932 | F46: Wireless | G46: 45666 | H46: 8943482329 | I46: 222 | J46: SBM703 | K46: Malayalam | L46: Kerala | M46: Yes | N46: Yes | O46: Yes | P46: Yes | Q46: Yes | R46: Yes | S46: Yes | T46: Yes | U46: No | V46: Yes | W46: Yes | X46: Yes | Y46: Yes | Z46: No | AA46: Yes | AB46: No | AC46: Yes | AD46: Yes | AE46: Yes | AF46: Not Applicable | AG46: Yes | AH46: Not Applicable | AI46: Not Applicable | AJ46: Yes | AK46: Yes | AL46: No | AM46: Yes | AN46: Yes | AO46: Yes | AP46: No active listening skills, No apology used | AQ46: The customer facing call connectivity related issue , The advisor suggest to set the network settings,The advisor did not used complete parameter properly. | AR46: Prepaid | AS46: CALL SERVICES | AT46: UNABLE TO MAKE O/G CALLS | AU46: Good Call, Fillings | AW46: =IF(OR(M46="YES", M46="Not Applicable"), AW$1, "0") -> 6 | AX46: =IF(OR(N46="YES", N46="Not Applicable"), AX$1, "0") -> 4 | AY46: =IF(OR(O46="YES", O46="Not Applicable"), AY$1, "0") -> 4 | AZ46: =IF(OR(P46="YES", P46="Not Applicable"), AZ$1, "0") -> 2 | BA46: =IF(OR(Q46="YES", Q46="Not Applicable"), BA$1, "0") -> 4 | BB46: =IF(OR(R46="YES", R46="Not Applicable"), BB$1, "0") -> 4 | BC46: =IF(OR(S46="YES", S46="Not Applicable"), BC$1, "0") -> 4 | BD46: =IF(OR(T46="YES", T46="Not Applicable"), BD$1, "0") -> 2 | ... BY46: =IF(OR(AO46="YES", AO46="Not Applicable"), BY$1, "0") -> 0 | BZ46: =SUM(AW46:BY46) -> 92 | CA46: =VLOOKUP(J:J,'Agent wise'!A:C,3,0) -> Shiny | CB46: =INT(E46) -> 45932 | CC46: =IF(BZ46>=94.5, "Excellent", IF(BZ46>89.5, "Good", IF(BZ46>84.5, "Average", "FC"))) -> Good | CJ46: =DAY(E46) -> 2 | CK46: =MONTH(E46) -> 10 | CL46: =YEAR(E46) -> 2025
A47: 45698.625 | B47: priyankajino2013@gmail.com | C47: 0 / 50 | D47: Priyanka | E47: 45932 | F47: Wireless | G47: 45667 | H47: 9443741038 | I47: 138 | J47: VPS160 | K47: Tamil | L47: Tamil Nadu | M47: Yes | N47: Yes | O47: Yes | P47: Yes | Q47: Yes | R47: Yes | S47: Yes | T47: Yes | U47: Yes | V47: Yes | W47: Yes | X47: Yes | Y47: Yes | Z47: Yes | AA47: No | AB47: Yes | AC47: Yes | AD47: Yes | AE47: Yes | AF47: Yes | AG47: Yes | AH47: Yes | AI47: Not Applicable | AJ47: Yes | AK47: Yes | AL47: Yes | AM47: Yes | AN47: Yes | AO47: Yes | AP47: AOI-empathy missing,dead air | AQ47: Opening & Introduction â€“ Done Customer details captured â€“Done Customer concern -Customer ask plan details Resolution shared - Advisor complete probing to customers as per call plan147 Closing as per standard - Done. AOI-empathy missing,dead air | AR47: Prepaid | AS47: PLANS AND VALIDITY DETAILS | AT47: ENQUIRY ON BALANCE AND VALIDITY | AU47: Good Call | AW47: =IF(OR(M47="YES", M47="Not Applicable"), AW$1, "0") -> 6 | AX47: =IF(OR(N47="YES", N47="Not Applicable"), AX$1, "0") -> 4 | AY47: =IF(OR(O47="YES", O47="Not Applicable"), AY$1, "0") -> 4 | AZ47: =IF(OR(P47="YES", P47="Not Applicable"), AZ$1, "0") -> 2 | BA47: =IF(OR(Q47="YES", Q47="Not Applicable"), BA$1, "0") -> 4 | BB47: =IF(OR(R47="YES", R47="Not Applicable"), BB$1, "0") -> 4 | BC47: =IF(OR(S47="YES", S47="Not Applicable"), BC$1, "0") -> 4 | BD47: =IF(OR(T47="YES", T47="Not Applicable"), BD$1, "0") -> 2 | ... BY47: =IF(OR(AO47="YES", AO47="Not Applicable"), BY$1, "0") -> 0 | BZ47: =SUM(AW47:BY47) -> 96 | CA47: =VLOOKUP(J:J,'Agent wise'!A:C,3,0) -> Shiny | CB47: =INT(E47) -> 45932 | CC47: =IF(BZ47>=94.5, "Excellent", IF(BZ47>89.5, "Good", IF(BZ47>84.5, "Average", "FC"))) -> Excellent | CJ47: =DAY(E47) -> 2 | CK47: =MONTH(E47) -> 10 | CL47: =YEAR(E47) -> 2025
A48: 45698.629 | B48: nehafire4444@gmail.com | C48: 0 / 50 | D48: Sneha | E48: 45932 | F48: Wireless | G48: 45667 | H48: 9043787697 | I48: 141 | J48: VPS111 | K48: Tamil | L48: Tamil Nadu | M48: No | N48: Yes | O48: Yes | P48: Yes | Q48: Yes | R48: Yes | S48: Yes | T48: Yes | U48: No | V48: Yes | W48: Yes | X48: Yes | Y48: Yes | Z48: Yes | AA48: Yes | AB48: No | AC48: Yes | AD48: Yes | AE48: Yes | AF48: Yes | AG48: Yes | AH48: Yes | AI48: Not Applicable | AJ48: Yes | AK48: Yes | AL48: No | AM48: Yes | AN48: Yes | AO48: Yes | AP48: Not used apology, Delay opening | AQ48: The customer called for sim lost regarding issue , the advisor suggest to contact nearby csc for post paid sim block , not used follow parameter properly . | AR48: Prepaid | AS48: SIM | AT48: REPLACED SIM NOT ACTIVATED | AU48: Good Call | AW48: =IF(OR(M48="YES", M48="Not Applicable"), AW$1, "0") -> 0 | AX48: =IF(OR(N48="YES", N48="Not Applicable"), AX$1, "0") -> 4 | AY48: =IF(OR(O48="YES", O48="Not Applicable"), AY$1, "0") -> 4 | AZ48: =IF(OR(P48="YES", P48="Not Applicable"), AZ$1, "0") -> 2 | BA48: =IF(OR(Q48="YES", Q48="Not Applicable"), BA$1, "0") -> 4 | BB48: =IF(OR(R48="YES", R48="Not Applicable"), BB$1, "0") -> 4 | BC48: =IF(OR(S48="YES", S48="Not Applicable"), BC$1, "0") -> 4 | BD48: =IF(OR(T48="YES", T48="Not Applicable"), BD$1, "0") -> 2 | ... BY48: =IF(OR(AO48="YES", AO48="Not Applicable"), BY$1, "0") -> 0 | BZ48: =SUM(AW48:BY48) -> 88 | CA48: =VLOOKUP(J:J,'Agent wise'!A:C,3,0) -> Shiny | CB48: =INT(E48) -> 45932 | CC48: =IF(BZ48>=94.5, "Excellent", IF(BZ48>89.5, "Good", IF(BZ48>84.5, "Average", "FC"))) -> Average | CJ48: =DAY(E48) -> 2 | CK48: =MONTH(E48) -> 10 | CL48: =YEAR(E48) -> 2025
A49: 45698.639 | B49: nehafire4444@gmail.com | C49: 0 / 50 | D49: Sneha | E49: 45932 | F49: Wireless | G49: 45667 | H49: 9487882275 | I49: 160 | J49: VPS120 | K49: Tamil | L49: Tamil Nadu | M49: Yes | N49: Yes | O49: Yes | P49: Yes | Q49: Yes | R49: Yes | S49: Yes | T49: No | U49: No | V49: Yes | W49: Yes | X49: Yes | Y49: Yes | Z49: No | AA49: Yes | AB49: No | AC49: Yes | AD49: Yes | AE49: Yes | AF49: No | AG49: No | AH49: Not Applicable | AI49: Not Applicable | AJ49: Yes | AK49: Yes | AL49: No | AM49: Yes | AN49: Yes | AO49: Yes | AP49: Wrong information ,irruption ,lack of active listings ,Not used apology words | AQ49: The customer called for wrong recharge regarding issue for his both connection.The advisor not give proper information, The advisor informed the customer that a conversation has already taken place regarding this number and that further assistance would require contacting the wrongly recharged number. A new conversation request should be initiated only after contact the concerned number. | AR49: Prepaid | AS49: RECHARGE ISSUE | AT49: ANY OTHER RECHARGE ISSUE | AU49: Good Call, Interuption | AW49: =IF(OR(M49="YES", M49="Not Applicable"), AW$1, "0") -> 6 | AX49: =IF(OR(N49="YES", N49="Not Applicable"), AX$1, "0") -> 4 | AY49: =IF(OR(O49="YES", O49="Not Applicable"), AY$1, "0") -> 4 | AZ49: =IF(OR(P49="YES", P49="Not Applicable"), AZ$1, "0") -> 2 | BA49: =IF(OR(Q49="YES", Q49="Not Applicable"), BA$1, "0") -> 4 | BB49: =IF(OR(R49="YES", R49="Not Applicable"), BB$1, "0") -> 4 | BC49: =IF(OR(S49="YES", S49="Not Applicable"), BC$1, "0") -> 4 | BD49: =IF(OR(T49="YES", T49="Not Applicable"), BD$1, "0") -> 0 | ... BY49: =IF(OR(AO49="YES", AO49="Not Applicable"), BY$1, "0") -> 0 | BZ49: =SUM(AW49:BY49) -> 80 | CA49: =VLOOKUP(J:J,'Agent wise'!A:C,3,0) -> Adharsh | CB49: =INT(E49) -> 45932 | CC49: =IF(BZ49>=94.5, "Excellent", IF(BZ49>89.5, "Good", IF(BZ49>84.5, "Average", "FC"))) -> FC | CJ49: =DAY(E49) -> 2 | CK49: =MONTH(E49) -> 10 | CL49: =YEAR(E49) -> 2025
... A107: 45726.568 | B107: priyankajino2013@gmail.com | C107: 0 / 50 | D107: Priyanka | E107: 45933 | F107: Wireline | G107: 45698 | H107: 9498406001 | I107: 131 | J107: SBM653 | K107: Tamil | L107: Tamil Nadu | M107: Yes | N107: Yes | O107: Yes | P107: Yes | Q107: Yes | R107: Yes | S107: Yes | T107: Yes | U107: Yes | V107: Yes | W107: Yes | X107: Yes | Y107: Yes | Z107: Yes | AA107: Yes | AB107: Yes | AC107: Yes | AD107: Yes | AE107: No | AF107: Yes | AG107: Yes | AH107: Yes | AI107: Not Applicable | AJ107: Yes | AK107: Yes | AL107: Yes | AM107: Yes | AN107: Yes | AO107: Yes | AP107: customer call did not focuse | AQ107: Opening & Introduction â€“ Done Customer details captured â€“Done Customer concern -Customer ask landline issue Resolution shared - Advisor complete probing to customers as per call wait for 24hr Closing as per standard - Done. AOI-customer call did not focuse | AR107: Postpaid | AS107: na | AT107: na | AU107: Good Call | AW107: =IF(OR(M107="YES", M107="Not Applicable"), AW$1, "0") -> 6 | AX107: =IF(OR(N107="YES", N107="Not Applicable"), AX$1, "0") -> 4 | AY107: =IF(OR(O107="YES", O107="Not Applicable"), AY$1, "0") -> 4 | AZ107: =IF(OR(P107="YES", P107="Not Applicable"), AZ$1, "0") -> 2 | BA107: =IF(OR(Q107="YES", Q107="Not Applicable"), BA$1, "0") -> 4 | BB107: =IF(OR(R107="YES", R107="Not Applicable"), BB$1, "0") -> 4 | BC107: =IF(OR(S107="YES", S107="Not Applicable"), BC$1, "0") -> 4 | BD107: =IF(OR(T107="YES", T107="Not Applicable"), BD$1, "0") -> 2 | ... BY107: =IF(OR(AO107="YES", AO107="Not Applicable"), BY$1, "0") -> 0 | BZ107: =SUM(AW107:BY107) -> 96 | CA107: =VLOOKUP(J:J,'Agent wise'!A:C,3,0) -> Amal | CB107: =INT(E107) -> 45933 | CC107: =IF(BZ107>=94.5, "Excellent", IF(BZ107>89.5, "Good", IF(BZ107>84.5, "Average", "FC"))) -> Excellent | CJ107: =DAY(E107) -> 3 | CK107: =MONTH(E107) -> 10 | CL107: =YEAR(E107) -> 2025
A108: 45726.572 | B108: adharshleewvan003@gmail.com | C108: 0 / 50 | D108: Adharsh | E108: 45931 | F108: Wireless | G108: 9/30/2025 | H108: 9843502046 | I108: 141 | J108: SBM962 | K108: Tamil | L108: Tamil Nadu | M108: Yes | N108: Yes | O108: Yes | P108: Yes | Q108: Yes | R108: Yes | S108: Yes | T108: Yes | U108: Yes | V108: Yes | W108: Yes | X108: Yes | Y108: Yes | Z108: Yes | AA108: Yes | AB108: Yes | AC108: Yes | AD108: Yes | AE108: Yes | AF108: Yes | AG108: Yes | AH108: Yes | AI108: Not Applicable | AJ108: Yes | AK108: Yes | AL108: No | AM108: Yes | AN108: Yes | AO108: Yes | AP108: Script adherence | AQ108: Customer called and informed us that he is facing IC and OG SMS issues. The agent checked and said that the customer has taken a duplicate SIM; that's the reason for the SMS service being barred, and he requested the customer to wait for 24 to 48 hours. | AR108: Prepaid | AS108: SMS SERVICES | AT108: I/C AND O/G SMS BARRED | AU108: Interuption, Fillings | AW108: =IF(OR(M108="YES", M108="Not Applicable"), AW$1, "0") -> 6 | AX108: =IF(OR(N108="YES", N108="Not Applicable"), AX$1, "0") -> 4 | AY108: =IF(OR(O108="YES", O108="Not Applicable"), AY$1, "0") -> 4 | AZ108: =IF(OR(P108="YES", P108="Not Applicable"), AZ$1, "0") -> 2 | BA108: =IF(OR(Q108="YES", Q108="Not Applicable"), BA$1, "0") -> 4 | BB108: =IF(OR(R108="YES", R108="Not Applicable"), BB$1, "0") -> 4 | BC108: =IF(OR(S108="YES", S108="Not Applicable"), BC$1, "0") -> 4 | BD108: =IF(OR(T108="YES", T108="Not Applicable"), BD$1, "0") -> 2 | ... BY108: =IF(OR(AO108="YES", AO108="Not Applicable"), BY$1, "0") -> 0 | BZ108: =SUM(AW108:BY108) -> 100 | CA108: =VLOOKUP(J:J,'Agent wise'!A:C,3,0) -> #N/A | CB108: =INT(E108) -> 45931 | CC108: =IF(BZ108>=94.5, "Excellent", IF(BZ108>89.5, "Good", IF(BZ108>84.5, "Average", "FC"))) -> Excellent | CJ108: =DAY(E108) -> 1 | CK108: =MONTH(E108) -> 10 | CL108: =YEAR(E108) -> 2025
A109: 45726.573 | B109: priyankajino2013@gmail.com | C109: 0 / 50 | D109: Priyanka | E109: 45933 | F109: Wireline | G109: 45698 | H109: 9567646698 | I109: 157 | J109: SBM734 | K109: Malayalam | L109: Kerala | M109: Yes | N109: Yes | O109: Yes | P109: Yes | Q109: Yes | R109: No | S109: Yes | T109: Yes | U109: Yes | V109: Yes | W109: Yes | X109: Yes | Y109: Yes | Z109: Yes | AA109: No | AB109: No | AC109: No | AD109: Yes | AE109: Yes | AF109: Yes | AG109: Yes | AH109: Yes | AI109: No | AJ109: Yes | AK109: Yes | AL109: Yes | AM109: Yes | AN109: Yes | AO109: Yes | AP109: AOI-empathy missing,sr number not provide | AQ109: Opening & Introduction â€“ Done Customer details captured â€“Done Customer concern -Customer ask landline issue Resolution shared - Advisor complete probing to customers as per call complaint booking Closing as per standard - Done. AOI-empathy missing,sr number not provide | AR109: Postpaid | AS109: na | AT109: na | AU109: Good Call | AW109: =IF(OR(M109="YES", M109="Not Applicable"), AW$1, "0") -> 6 | AX109: =IF(OR(N109="YES", N109="Not Applicable"), AX$1, "0") -> 4 | AY109: =IF(OR(O109="YES", O109="Not Applicable"), AY$1, "0") -> 4 | AZ109: =IF(OR(P109="YES", P109="Not Applicable"), AZ$1, "0") -> 2 | BA109: =IF(OR(Q109="YES", Q109="Not Applicable"), BA$1, "0") -> 4 | BB109: =IF(OR(R109="YES", R109="Not Applicable"), BB$1, "0") -> 0 | BC109: =IF(OR(S109="YES", S109="Not Applicable"), BC$1, "0") -> 4 | BD109: =IF(OR(T109="YES", T109="Not Applicable"), BD$1, "0") -> 2 | ... BY109: =IF(OR(AO109="YES", AO109="Not Applicable"), BY$1, "0") -> 0 | BZ109: =SUM(AW109:BY109) -> 82 | CA109: =VLOOKUP(J:J,'Agent wise'!A:C,3,0) -> Amal | CB109: =INT(E109) -> 45933 | CC109: =IF(BZ109>=94.5, "Excellent", IF(BZ109>89.5, "Good", IF(BZ109>84.5, "Average", "FC"))) -> FC | CJ109: =DAY(E109) -> 3 | CK109: =MONTH(E109) -> 10 | CL109: =YEAR(E109) -> 2025
A110: 45726.575 | B110: adharshleewvan003@gmail.com | C110: 0 / 50 | D110: Adharsh | E110: 45932 | F110: Wireless | G110: 45667 | H110: 9487005324 | I110: 110 | J110: SBM718 | K110: Tamil | L110: Tamil Nadu | M110: Yes | N110: Yes | O110: Yes | P110: Yes | Q110: Yes | R110: Yes | S110: Yes | T110: Yes | U110: Yes | V110: Yes | W110: Yes | X110: Yes | Y110: Yes | Z110: Yes | AA110: Yes | AB110: Yes | AC110: Yes | AD110: Yes | AE110: Yes | AF110: Yes | AG110: No | AH110: Not Applicable | AI110: Not Applicable | AJ110: Yes | AK110: Yes | AL110: Yes | AM110: Yes | AN110: Yes | AO110: Yes | AP110: Give accurate information/ Next steps on each issue | AQ110: Customer called and said he had been facing a hotspot issue. The agent checked and said the APN setting was for the customer. | AR110: Prepaid | AS110: DATA SERVICES | AT110: UNABLE TO BROWSE DATA | AU110: Interuption | AW110: =IF(OR(M110="YES", M110="Not Applicable"), AW$1, "0") -> 6 | AX110: =IF(OR(N110="YES", N110="Not Applicable"), AX$1, "0") -> 4 | AY110: =IF(OR(O110="YES", O110="Not Applicable"), AY$1, "0") -> 4 | AZ110: =IF(OR(P110="YES", P110="Not Applicable"), AZ$1, "0") -> 2 | BA110: =IF(OR(Q110="YES", Q110="Not Applicable"), BA$1, "0") -> 4 | BB110: =IF(OR(R110="YES", R110="Not Applicable"), BB$1, "0") -> 4 | BC110: =IF(OR(S110="YES", S110="Not Applicable"), BC$1, "0") -> 4 | BD110: =IF(OR(T110="YES", T110="Not Applicable"), BD$1, "0") -> 2 | ... BY110: =IF(OR(AO110="YES", AO110="Not Applicable"), BY$1, "0") -> 0 | BZ110: =SUM(AW110:BY110) -> 94 | CA110: =VLOOKUP(J:J,'Agent wise'!A:C,3,0) -> Shiny | CB110: =INT(E110) -> 45932 | CC110: =IF(BZ110>=94.5, "Excellent", IF(BZ110>89.5, "Good", IF(BZ110>84.5, "Average", "FC"))) -> Good | CJ110: =DAY(E110) -> 2 | CK110: =MONTH(E110) -> 10 | CL110: =YEAR(E110) -> 2025
A111: 45726.575 | B111: nehafire4444@gmail.com | C111: 0 / 50 | D111: Sneha | E111: 45933 | F111: Wireless | G111: 45698 | H111: 9447603601 | I111: 154 | J111: SBM150 | K111: Malayalam | L111: Kerala | M111: Yes | N111: Yes | O111: Yes | P111: Yes | Q111: Yes | R111: Yes | S111: Yes | T111: Yes | U111: No | V111: Yes | W111: Yes | X111: Yes | Y111: Yes | Z111: No | AA111: Yes | AB111: Yes | AC111: Yes | AD111: Yes | AE111: Yes | AF111: Yes | AG111: Yes | AH111: Not Applicable | AI111: Not Applicable | AJ111: Yes | AK111: Yes | AL111: Yes | AM111: Yes | AN111: Yes | AO111: Yes | AP111: interruption Lack of active listening | AQ111: The customer called for called and data connectivity related issue , the Advisor check the details and informed sim side there is no issues so try another handset continuedly no response on the other end so the advisor disconnect the call with proper script. | AR111: Prepaid | AS111: WEAK SIGNAL | AT111: VOICE SERVICES | AU111: Interuption | AW111: =IF(OR(M111="YES", M111="Not Applicable"), AW$1, "0") -> 6 | AX111: =IF(OR(N111="YES", N111="Not Applicable"), AX$1, "0") -> 4 | AY111: =IF(OR(O111="YES", O111="Not Applicable"), AY$1, "0") -> 4 | AZ111: =IF(OR(P111="YES", P111="Not Applicable"), AZ$1, "0") -> 2 | BA111: =IF(OR(Q111="YES", Q111="Not Applicable"), BA$1, "0") -> 4 | BB111: =IF(OR(R111="YES", R111="Not Applicable"), BB$1, "0") -> 4 | BC111: =IF(OR(S111="YES", S111="Not Applicable"), BC$1, "0") -> 4 | BD111: =IF(OR(T111="YES", T111="Not Applicable"), BD$1, "0") -> 2 | ... BY111: =IF(OR(AO111="YES", AO111="Not Applicable"), BY$1, "0") -> 0 | BZ111: =SUM(AW111:BY111) -> 94 | CA111: =VLOOKUP(J:J,'Agent wise'!A:C,3,0) -> Saran S | CB111: =INT(E111) -> 45933 | CC111: =IF(BZ111>=94.5, "Excellent", IF(BZ111>89.5, "Good", IF(BZ111>84.5, "Average", "FC"))) -> Good | CJ111: =DAY(E111) -> 3 | CK111: =MONTH(E111) -> 10 | CL111: =YEAR(E111) -> 2025
A112: 45726.575 | B112: priyankajino2013@gmail.com | C112: 0 / 50 | D112: Priyanka | E112: 45933 | F112: Wireline | G112: 45698 | H112: 7034171849 | I112: 143 | J112: SBM734 | K112: Malayalam | L112: Kerala | M112: Yes | N112: Yes | O112: Yes | P112: Yes | Q112: Yes | R112: Yes | S112: Yes | T112: Yes | U112: Yes | V112: Yes | W112: Yes | X112: Yes | Y112: Yes | Z112: Yes | AA112: No | AB112: No | AC112: No | AD112: Yes | AE112: Yes | AF112: Yes | AG112: Yes | AH112: Yes | AI112: Not Applicable | AJ112: Yes | AK112: Yes | AL112: Yes | AM112: Yes | AN112: Yes | AO112: Yes | AP112: AOI-empathy missing,sr number not provide | AQ112: Opening & Introduction â€“ Done Customer details captured â€“Done Customer concern -Customer ask landline issue Resolution shared - Advisor complete probing to customers as per call bill details Closing as per standard - Done. AOI-empathy missing,sr number not provide | AR112: Postpaid | AS112: na | AT112: na | AU112: Good Call | AW112: =IF(OR(M112="YES", M112="Not Applicable"), AW$1, "0") -> 6 | AX112: =IF(OR(N112="YES", N112="Not Applicable"), AX$1, "0") -> 4 | AY112: =IF(OR(O112="YES", O112="Not Applicable"), AY$1, "0") -> 4 | AZ112: =IF(OR(P112="YES", P112="Not Applicable"), AZ$1, "0") -> 2 | BA112: =IF(OR(Q112="YES", Q112="Not Applicable"), BA$1, "0") -> 4 | BB112: =IF(OR(R112="YES", R112="Not Applicable"), BB$1, "0") -> 4 | BC112: =IF(OR(S112="YES", S112="Not Applicable"), BC$1, "0") -> 4 | BD112: =IF(OR(T112="YES", T112="Not Applicable"), BD$1, "0") -> 2 | ... BY112: =IF(OR(AO112="YES", AO112="Not Applicable"), BY$1, "0") -> 0 | BZ112: =SUM(AW112:BY112) -> 90 | CA112: =VLOOKUP(J:J,'Agent wise'!A:C,3,0) -> Amal | CB112: =INT(E112) -> 45933 | CC112: =IF(BZ112>=94.5, "Excellent", IF(BZ112>89.5, "Good", IF(BZ112>84.5, "Average", "FC"))) -> Good | CJ112: =DAY(E112) -> 3 | CK112: =MONTH(E112) -> 10 | CL112: =YEAR(E112) -> 2025
A113: 45726.577 | B113: nehafire4444@gmail.com | C113: 0 / 50 | D113: Sneha | E113: 45933 | F113: Wireless | G113: 45698 | H113: 6238628489 | I113: 145 | J113: SBM157 | K113: Malayalam | L113: Kerala | M113: Yes | N113: Yes | O113: Yes | P113: Yes | Q113: Yes | R113: Yes | S113: Yes | T113: Yes | U113: Yes | V113: Yes | W113: Yes | X113: Yes | Y113: Yes | Z113: Yes | AA113: Yes | AB113: Yes | AC113: Yes | AD113: Yes | AE113: Yes | AF113: Yes | AG113: Yes | AH113: Not Applicable | AI113: Not Applicable | AJ113: Yes | AK113: Yes | AL113: Yes | AM113: Yes | AN113: Yes | AO113: Yes | AP113: good call | AQ113: The customer called for sim signal not show in Germany regarding issue , The advisor check the details sim already IR sim side no issue , try to set the network operator. | AR113: Prepaid | AS113: ISD ROAMING | AT113: ENQUIRY ON ISD ROAMING | AU113: Good Call | AW113: =IF(OR(M113="YES", M113="Not Applicable"), AW$1, "0") -> 6 | AX113: =IF(OR(N113="YES", N113="Not Applicable"), AX$1, "0") -> 4 | AY113: =IF(OR(O113="YES", O113="Not Applicable"), AY$1, "0") -> 4 | AZ113: =IF(OR(P113="YES", P113="Not Applicable"), AZ$1, "0") -> 2 | BA113: =IF(OR(Q113="YES", Q113="Not Applicable"), BA$1, "0") -> 4 | BB113: =IF(OR(R113="YES", R113="Not Applicable"), BB$1, "0") -> 4 | BC113: =IF(OR(S113="YES", S113="Not Applicable"), BC$1, "0") -> 4 | BD113: =IF(OR(T113="YES", T113="Not Applicable"), BD$1, "0") -> 2 | ... BY113: =IF(OR(AO113="YES", AO113="Not Applicable"), BY$1, "0") -> 0 | BZ113: =SUM(AW113:BY113) -> 100 | CA113: =VLOOKUP(J:J,'Agent wise'!A:C,3,0) -> Saran S | CB113: =INT(E113) -> 45933 | CC113: =IF(BZ113>=94.5, "Excellent", IF(BZ113>89.5, "Good", IF(BZ113>84.5, "Average", "FC"))) -> Excellent | CJ113: =DAY(E113) -> 3 | CK113: =MONTH(E113) -> 10 | CL113: =YEAR(E113) -> 2025
A114: 45726.578 | B114: adharshleewvan003@gmail.com | C114: 0 / 50 | D114: Adharsh | E114: 45931 | F114: Wireless | G114: 9/30/2025 | H114: 9446650630 | I114: 136 | J114: SBM773 | K114: Malayalam | L114: Kerala | M114: Yes | N114: Yes | O114: Yes | P114: Yes | Q114: Yes | R114: Yes | S114: Yes | T114: Yes | U114: Yes | V114: Yes | W114: Yes | X114: Yes | Y114: Yes | Z114: Yes | AA114: Yes | AB114: Yes | AC114: Yes | AD114: Not Applicable | AE114: Yes | AF114: Yes | AG114: Yes | AH114: Not Applicable | AI114: Not Applicable | AJ114: Yes | AK114: Yes | AL114: Yes | AM114: Yes | AN114: Yes | AO114: Yes | AP114: Good call | AQ114: Customer reported that she is facing a data connectivity issue; the agent said to update her SIM to 4G for better data speed. | AR114: Prepaid | AS114: DATA SERVICES | AT114: UNABLE TO BROWSE DATA | AU114: Good Call | AW114: =IF(OR(M114="YES", M114="Not Applicable"), AW$1, "0") -> 6 | AX114: =IF(OR(N114="YES", N114="Not Applicable"), AX$1, "0") -> 4 | AY114: =IF(OR(O114="YES", O114="Not Applicable"), AY$1, "0") -> 4 | AZ114: =IF(OR(P114="YES", P114="Not Applicable"), AZ$1, "0") -> 2 | BA114: =IF(OR(Q114="YES", Q114="Not Applicable"), BA$1, "0") -> 4 | BB114: =IF(OR(R114="YES", R114="Not Applicable"), BB$1, "0") -> 4 | BC114: =IF(OR(S114="YES", S114="Not Applicable"), BC$1, "0") -> 4 | BD114: =IF(OR(T114="YES", T114="Not Applicable"), BD$1, "0") -> 2 | ... BY114: =IF(OR(AO114="YES", AO114="Not Applicable"), BY$1, "0") -> 0 | BZ114: =SUM(AW114:BY114) -> 100 | CA114: =VLOOKUP(J:J,'Agent wise'!A:C,3,0) -> Adharsh | CB114: =INT(E114) -> 45931 | CC114: =IF(BZ114>=94.5, "Excellent", IF(BZ114>89.5, "Good", IF(BZ114>84.5, "Average", "FC"))) -> Excellent | CJ114: =DAY(E114) -> 1 | CK114: =MONTH(E114) -> 10 | CL114: =YEAR(E114) -> 2025
A115: 45726.579 | B115: nehafire4444@gmail.com | C115: 0 / 50 | D115: Sneha | E115: 45933 | F115: Wireless | G115: 45698 | H115: 8300825737 | I115: 173 | J115: SBM202 | K115: Tamil | L115: Tamil Nadu | M115: Yes | N115: Yes | O115: Yes | P115: Yes | Q115: Yes | R115: Yes | S115: Yes | T115: Yes | U115: No | V115: Yes | W115: Yes | X115: Yes | Y115: Yes | Z115: Yes | AA115: Yes | AB115: No | AC115: Yes | AD115: Yes | AE115: Yes | AF115: Yes | AG115: Yes | AH115: Not Applicable | AI115: Not Applicable | AJ115: Yes | AK115: Yes | AL115: No | AM115: Yes | AN115: Yes | AO115: Yes | AP115: Not used apology words | AQ115: The customer called for data connectivity related issue .The advisor inform check the adress and call back for registering acomplaint . | AR115: Prepaid | AS115: DATA SERVICES | AT115: UNABLE TO BROWSE DATA | AU115: Good Call | AW115: =IF(OR(M115="YES", M115="Not Applicable"), AW$1, "0") -> 6 | AX115: =IF(OR(N115="YES", N115="Not Applicable"), AX$1, "0") -> 4 | AY115: =IF(OR(O115="YES", O115="Not Applicable"), AY$1, "0") -> 4 | AZ115: =IF(OR(P115="YES", P115="Not Applicable"), AZ$1, "0") -> 2 | BA115: =IF(OR(Q115="YES", Q115="Not Applicable"), BA$1, "0") -> 4 | BB115: =IF(OR(R115="YES", R115="Not Applicable"), BB$1, "0") -> 4 | BC115: =IF(OR(S115="YES", S115="Not Applicable"), BC$1, "0") -> 4 | BD115: =IF(OR(T115="YES", T115="Not Applicable"), BD$1, "0") -> 2 | ... BY115: =IF(OR(AO115="YES", AO115="Not Applicable"), BY$1, "0") -> 0 | BZ115: =SUM(AW115:BY115) -> 94 | CA115: =VLOOKUP(J:J,'Agent wise'!A:C,3,0) -> Adharsh | CB115: =INT(E115) -> 45933 | CC115: =IF(BZ115>=94.5, "Excellent", IF(BZ115>89.5, "Good", IF(BZ115>84.5, "Average", "FC"))) -> Good | CJ115: =DAY(E115) -> 3 | CK115: =MONTH(E115) -> 10 | CL115: =YEAR(E115) -> 2025
A116: 45726.581 | B116: nehafire4444@gmail.com | C116: 0 / 50 | D116: Sneha | E116: 45933 | F116: Wireless | G116: 45698 | H116: 6369961346 | I116: 204 | J116: SBM267 | K116: Tamil | L116: Tamil Nadu | M116: Yes | N116: Yes | O116: Yes | P116: Yes | Q116: Yes | R116: Yes | S116: Yes | T116: Yes | U116: No | V116: Yes | W116: Yes | X116: Yes | Y116: Yes | Z116: Yes | AA116: Yes | AB116: No | AC116: Yes | AD116: Yes | AE116: Yes | AF116: Yes | AG116: Yes | AH116: Not Applicable | AI116: Not Applicable | AJ116: Yes | AK116: Yes | AL116: No | AM116: Yes | AN116: Yes | AO116: Yes | AP116: No apology words used. | AQ116: The customer called for network signal regarding issue ,the Advisor inform check the full address and call back for registering a complaint . | AR116: Prepaid | AS116: WEAK SIGNAL | AT116: VOICE SERVICES | AU116: Good Call | AW116: =IF(OR(M116="YES", M116="Not Applicable"), AW$1, "0") -> 6 | AX116: =IF(OR(N116="YES", N116="Not Applicable"), AX$1, "0") -> 4 | AY116: =IF(OR(O116="YES", O116="Not Applicable"), AY$1, "0") -> 4 | AZ116: =IF(OR(P116="YES", P116="Not Applicable"), AZ$1, "0") -> 2 | BA116: =IF(OR(Q116="YES", Q116="Not Applicable"), BA$1, "0") -> 4 | BB116: =IF(OR(R116="YES", R116="Not Applicable"), BB$1, "0") -> 4 | BC116: =IF(OR(S116="YES", S116="Not Applicable"), BC$1, "0") -> 4 | BD116: =IF(OR(T116="YES", T116="Not Applicable"), BD$1, "0") -> 2 | ... BY116: =IF(OR(AO116="YES", AO116="Not Applicable"), BY$1, "0") -> 0 | BZ116: =SUM(AW116:BY116) -> 94 | CA116: =VLOOKUP(J:J,'Agent wise'!A:C,3,0) -> Saran S | CB116: =INT(E116) -> 45933 | CC116: =IF(BZ116>=94.5, "Excellent", IF(BZ116>89.5, "Good", IF(BZ116>84.5, "Average", "FC"))) -> Good | CJ116: =DAY(E116) -> 3 | CK116: =MONTH(E116) -> 10 | CL116: =YEAR(E116) -> 2025
A117: 45726.581 | B117: adharshleewvan003@gmail.com | C117: 0 / 50 | D117: Adharsh | E117: 45932 | F117: Wireless | G117: 45667 | H117: 7871152565 | I117: 125 | J117: SBM625 | K117: Tamil | L117: Tamil Nadu | M117: Yes | N117: Yes | O117: Yes | P117: Yes | Q117: Yes | R117: Yes | S117: Yes | T117: Yes | U117: Yes | V117: Yes | W117: Yes | X117: Yes | Y117: No | Z117: Yes | AA117: Yes | AB117: Yes | AC117: Not Applicable | AD117: Yes | AE117: Yes | AF117: Yes | AG117: Yes | AH117: Not Applicable | AI117: Not Applicable | AJ117: Yes | AK117: Yes | AL117: Yes | AM117: Yes | AN117: Yes | AO117: Yes | AP117: Used Approved Question/Polite language | AQ117: Customer called and said she need PUK code, agent verified customer details and provided PUK code | AR117: Prepaid | AS117: PLANS AND VALIDITY DETAILS | AT117: ENQUIRY ON PREPAID PLANS | AU117: Interuption | AW117: =IF(OR(M117="YES", M117="Not Applicable"), AW$1, "0") -> 6 | AX117: =IF(OR(N117="YES", N117="Not Applicable"), AX$1, "0") -> 4 | AY117: =IF(OR(O117="YES", O117="Not Applicable"), AY$1, "0") -> 4 | AZ117: =IF(OR(P117="YES", P117="Not Applicable"), AZ$1, "0") -> 2 | BA117: =IF(OR(Q117="YES", Q117="Not Applicable"), BA$1, "0") -> 4 | BB117: =IF(OR(R117="YES", R117="Not Applicable"), BB$1, "0") -> 4 | BC117: =IF(OR(S117="YES", S117="Not Applicable"), BC$1, "0") -> 4 | BD117: =IF(OR(T117="YES", T117="Not Applicable"), BD$1, "0") -> 2 | ... BY117: =IF(OR(AO117="YES", AO117="Not Applicable"), BY$1, "0") -> 0 | BZ117: =SUM(AW117:BY117) -> 96 | CA117: =VLOOKUP(J:J,'Agent wise'!A:C,3,0) -> Saran S | CB117: =INT(E117) -> 45932 | CC117: =IF(BZ117>=94.5, "Excellent", IF(BZ117>89.5, "Good", IF(BZ117>84.5, "Average", "FC"))) -> Excellent | CJ117: =DAY(E117) -> 2 | CK117: =MONTH(E117) -> 10 | CL117: =YEAR(E117) -> 2025
A118: 45726.582 | B118: nehafire4444@gmail.com | C118: 0 / 50 | D118: Sneha | E118: 45933 | F118: Wireless | G118: 45698 | H118: 8891884648 | I118: 173 | J118: SBM314 | K118: Malayalam | L118: Kerala | M118: Yes | N118: Yes | O118: Yes | P118: Yes | Q118: Yes | R118: Yes | S118: Yes | T118: Yes | U118: Yes | V118: Yes | W118: Yes | X118: Yes | Y118: Yes | Z118: Yes | AA118: Yes | AB118: Yes | AC118: Yes | AD118: Yes | AE118: Yes | AF118: Yes | AG118: Yes | AH118: Not Applicable | AI118: Yes | AJ118: Yes | AK118: Yes | AL118: Yes | AM118: Yes | AN118: Yes | AO118: Yes | AP118: Good Call | AQ118: The customer called for network signal regarding issue , call and data not connected properly signal disconnected issue , The advisor taken a complaint and given proper information. | AR118: Prepaid | AS118: NETWORK | AT118: POOR NETWORK COVERAGE | AU118: Good Call | AW118: =IF(OR(M118="YES", M118="Not Applicable"), AW$1, "0") -> 6 | AX118: =IF(OR(N118="YES", N118="Not Applicable"), AX$1, "0") -> 4 | AY118: =IF(OR(O118="YES", O118="Not Applicable"), AY$1, "0") -> 4 | AZ118: =IF(OR(P118="YES", P118="Not Applicable"), AZ$1, "0") -> 2 | BA118: =IF(OR(Q118="YES", Q118="Not Applicable"), BA$1, "0") -> 4 | BB118: =IF(OR(R118="YES", R118="Not Applicable"), BB$1, "0") -> 4 | BC118: =IF(OR(S118="YES", S118="Not Applicable"), BC$1, "0") -> 4 | BD118: =IF(OR(T118="YES", T118="Not Applicable"), BD$1, "0") -> 2 | ... BY118: =IF(OR(AO118="YES", AO118="Not Applicable"), BY$1, "0") -> 0 | BZ118: =SUM(AW118:BY118) -> 100 | CA118: =VLOOKUP(J:J,'Agent wise'!A:C,3,0) -> Shakeer | CB118: =INT(E118) -> 45933 | CC118: =IF(BZ118>=94.5, "Excellent", IF(BZ118>89.5, "Good", IF(BZ118>84.5, "Average", "FC"))) -> Excellent | CJ118: =DAY(E118) -> 3 | CK118: =MONTH(E118) -> 10 | CL118: =YEAR(E118) -> 2025
A119: 45726.584 | B119: nehafire4444@gmail.com | C119: 0 / 50 | D119: Sneha | E119: 45933 | F119: Wireless | G119: 45698 | H119: 7598341582 | I119: 137 | J119: SBM373 | K119: Tamil | L119: Tamil Nadu | M119: Yes | N119: Yes | O119: Yes | P119: Yes | Q119: Yes | R119: Yes | S119: Yes | T119: Yes | U119: No | V119: Yes | W119: Yes | X119: Yes | Y119: Yes | Z119: No | AA119: Yes | AB119: Yes | AC119: Yes | AD119: Yes | AE119: Yes | AF119: Yes | AG119: Yes | AH119: Not Applicable | AI119: Not Applicable | AJ119: Yes | AK119: Yes | AL119: No | AM119: No | AN119: No | AO119: No | AP119: Tagging not accurate, lack of activeness on call | AQ119: The customer called for new port sim not activated regarding issue , The advisors informed wait for some time the sim will be activated. | AR119: Prepaid | AS119: SIM | AT119: NEW SIM ACTIVATION PROCESS | AU119: Good Call | AW119: =IF(OR(M119="YES", M119="Not Applicable"), AW$1, "0") -> 6 | AX119: =IF(OR(N119="YES", N119="Not Applicable"), AX$1, "0") -> 4 | AY119: =IF(OR(O119="YES", O119="Not Applicable"), AY$1, "0") -> 4 | AZ119: =IF(OR(P119="YES", P119="Not Applicable"), AZ$1, "0") -> 2 | BA119: =IF(OR(Q119="YES", Q119="Not Applicable"), BA$1, "0") -> 4 | BB119: =IF(OR(R119="YES", R119="Not Applicable"), BB$1, "0") -> 4 | BC119: =IF(OR(S119="YES", S119="Not Applicable"), BC$1, "0") -> 4 | BD119: =IF(OR(T119="YES", T119="Not Applicable"), BD$1, "0") -> 2 | ... BY119: =IF(OR(AO119="YES", AO119="Not Applicable"), BY$1, "0") -> 0 | BZ119: =SUM(AW119:BY119) -> 88 | CA119: =VLOOKUP(J:J,'Agent wise'!A:C,3,0) -> Saran S | CB119: =INT(E119) -> 45933 | CC119: =IF(BZ119>=94.5, "Excellent", IF(BZ119>89.5, "Good", IF(BZ119>84.5, "Average", "FC"))) -> Average | CJ119: =DAY(E119) -> 3 | CK119: =MONTH(E119) -> 10 | CL119: =YEAR(E119) -> 2025
A120: 45726.585 | B120: adharshleewvan003@gmail.com | C120: 0 / 50 | D120: Adharsh | E120: 45932 | F120: Wireless | G120: 45667 | H120: 9444585445 | I120: 132 | J120: VPS214 | K120: Tamil | L120: Tamil Nadu | M120: Yes | N120: Yes | O120: Yes | P120: Yes | Q120: Yes | R120: Yes | S120: Yes | T120: Yes | U120: Yes | V120: Yes | W120: Yes | X120: Yes | Y120: No | Z120: Yes | AA120: Yes | AB120: Yes | AC120: Yes | AD120: Yes | AE120: Yes | AF120: Yes | AG120: Yes | AH120: Not Applicable | AI120: Not Applicable | AJ120: Yes | AK120: Yes | AL120: Yes | AM120: Yes | AN120: Yes | AO120: Yes | AP120: Used Approved Question/Polite language | AQ120: Customer reported that customer SIM was lost and needed to block his SIM | AR120: Prepaid | AS120: SIM BLOCK | AT120: SIM BLOCKDUE TO SIM LOST | AU120: Interuption | AW120: =IF(OR(M120="YES", M120="Not Applicable"), AW$1, "0") -> 6 | AX120: =IF(OR(N120="YES", N120="Not Applicable"), AX$1, "0") -> 4 | AY120: =IF(OR(O120="YES", O120="Not Applicable"), AY$1, "0") -> 4 | AZ120: =IF(OR(P120="YES", P120="Not Applicable"), AZ$1, "0") -> 2 | BA120: =IF(OR(Q120="YES", Q120="Not Applicable"), BA$1, "0") -> 4 | BB120: =IF(OR(R120="YES", R120="Not Applicable"), BB$1, "0") -> 4 | BC120: =IF(OR(S120="YES", S120="Not Applicable"), BC$1, "0") -> 4 | BD120: =IF(OR(T120="YES", T120="Not Applicable"), BD$1, "0") -> 2 | ... BY120: =IF(OR(AO120="YES", AO120="Not Applicable"), BY$1, "0") -> 0 | BZ120: =SUM(AW120:BY120) -> 96 | CA120: =VLOOKUP(J:J,'Agent wise'!A:C,3,0) -> Shakeer | CB120: =INT(E120) -> 45932 | CC120: =IF(BZ120>=94.5, "Excellent", IF(BZ120>89.5, "Good", IF(BZ120>84.5, "Average", "FC"))) -> Excellent | CJ120: =DAY(E120) -> 2 | CK120: =MONTH(E120) -> 10 | CL120: =YEAR(E120) -> 2025
A121: 45726.586 | B121: nehafire4444@gmail.com | C121: 0 / 50 | D121: Sneha | E121: 45933 | F121: Wireless | G121: 45698 | H121: 9495952850 | I121: 159 | J121: VPS239 | K121: Malayalam | L121: Kerala | M121: Yes | N121: Yes | O121: Yes | P121: Yes | Q121: Yes | R121: Yes | S121: Yes | T121: Yes | U121: No | V121: Yes | W121: Yes | X121: Yes | Y121: Yes | Z121: Yes | AA121: Yes | AB121: Yes | AC121: Yes | AD121: Yes | AE121: Yes | AF121: Yes | AG121: Yes | AH121: Yes | AI121: Not Applicable | AJ121: Yes | AK121: Yes | AL121: No | AM121: Yes | AN121: Yes | AO121: Yes | AP121: No script adherence , tagging not accurate | AQ121: The customer called for call not connected and recharge plan regarding details, The advisor given proper information sim not active state need to recharge plan details | AR121: Prepaid | AS121: VOICE SERVICES | AT121: WEAK SIGNAL | AU121: Good Call | AW121: =IF(OR(M121="YES", M121="Not Applicable"), AW$1, "0") -> 6 | AX121: =IF(OR(N121="YES", N121="Not Applicable"), AX$1, "0") -> 4 | AY121: =IF(OR(O121="YES", O121="Not Applicable"), AY$1, "0") -> 4 | AZ121: =IF(OR(P121="YES", P121="Not Applicable"), AZ$1, "0") -> 2 | BA121: =IF(OR(Q121="YES", Q121="Not Applicable"), BA$1, "0") -> 4 | BB121: =IF(OR(R121="YES", R121="Not Applicable"), BB$1, "0") -> 4 | BC121: =IF(OR(S121="YES", S121="Not Applicable"), BC$1, "0") -> 4 | BD121: =IF(OR(T121="YES", T121="Not Applicable"), BD$1, "0") -> 2 | ... BY121: =IF(OR(AO121="YES", AO121="Not Applicable"), BY$1, "0") -> 0 | BZ121: =SUM(AW121:BY121) -> 96 | CA121: =VLOOKUP(J:J,'Agent wise'!A:C,3,0) -> Adharsh | CB121: =INT(E121) -> 45933 | CC121: =IF(BZ121>=94.5, "Excellent", IF(BZ121>89.5, "Good", IF(BZ121>84.5, "Average", "FC"))) -> Excellent | CJ121: =DAY(E121) -> 3 | CK121: =MONTH(E121) -> 10 | CL121: =YEAR(E121) -> 2025
A122: 45726.588 | B122: nehafire4444@gmail.com | C122: 0 / 50 | D122: Sneha | E122: 45933 | F122: Wireless | G122: 45698 | H122: 8289812141 | I122: 179 | J122: SBM485 | K122: Malayalam | L122: Kerala | M122: Yes | N122: Yes | O122: Yes | P122: Yes | Q122: Yes | R122: Yes | S122: Yes | T122: Yes | U122: No | V122: Yes | W122: Yes | X122: Yes | Y122: Yes | Z122: No | AA122: No | AB122: Yes | AC122: Yes | AD122: Yes | AE122: Yes | AF122: Yes | AG122: Yes | AH122: Yes | AI122: Not Applicable | AJ122: Yes | AK122: Yes | AL122: No | AM122: Yes | AN122: Yes | AO122: Yes | AP122: Not used script adherence, Lack of energy ,empathy missing | AQ122: The customer called for data connectivity regarding issue .The advisor given proper information to set the network settings | AR122: Prepaid | AS122: DATA SERVICES | AT122: DATA BALANCE NOT AVAILABLE | AU122: Good Call | AW122: =IF(OR(M122="YES", M122="Not Applicable"), AW$1, "0") -> 6 | AX122: =IF(OR(N122="YES", N122="Not Applicable"), AX$1, "0") -> 4 | AY122: =IF(OR(O122="YES", O122="Not Applicable"), AY$1, "0") -> 4 | AZ122: =IF(OR(P122="YES", P122="Not Applicable"), AZ$1, "0") -> 2 | BA122: =IF(OR(Q122="YES", Q122="Not Applicable"), BA$1, "0") -> 4 | BB122: =IF(OR(R122="YES", R122="Not Applicable"), BB$1, "0") -> 4 | BC122: =IF(OR(S122="YES", S122="Not Applicable"), BC$1, "0") -> 4 | BD122: =IF(OR(T122="YES", T122="Not Applicable"), BD$1, "0") -> 2 | ... BY122: =IF(OR(AO122="YES", AO122="Not Applicable"), BY$1, "0") -> 0 | BZ122: =SUM(AW122:BY122) -> 90 | CA122: =VLOOKUP(J:J,'Agent wise'!A:C,3,0) -> Saran S | CB122: =INT(E122) -> 45933 | CC122: =IF(BZ122>=94.5, "Excellent", IF(BZ122>89.5, "Good", IF(BZ122>84.5, "Average", "FC"))) -> Good | CJ122: =DAY(E122) -> 3 | CK122: =MONTH(E122) -> 10 | CL122: =YEAR(E122) -> 2025
A123: 45726.59 | B123: nehafire4444@gmail.com | C123: 0 / 50 | D123: Sneha | E123: 45933 | F123: Wireless | G123: 45698 | H123: 9488423340 | I123: 170 | J123: SBM524 | K123: Tamil | L123: Tamil Nadu | M123: Yes | N123: Yes | O123: Yes | P123: Yes | Q123: Yes | R123: Yes | S123: Yes | T123: Yes | U123: No | V123: Yes | W123: Yes | X123: Yes | Y123: Yes | Z123: Yes | AA123: Yes | AB123: No | AC123: Yes | AD123: Yes | AE123: Yes | AF123: Yes | AG123: Yes | AH123: Not Applicable | AI123: Not Applicable | AJ123: Yes | AK123: Yes | AL123: No | AM123: Yes | AN123: Yes | AO123: Yes | AP123: Not used apology words, No further assistance | AQ123: The customer called for network signal regarding issue , The advisor probing properly and taken complaint and given proper information. | AR123: Prepaid | AS123: NETWORK | AT123: POOR NETWORK COVERAGE | AU123: Good Call | AW123: =IF(OR(M123="YES", M123="Not Applicable"), AW$1, "0") -> 6 | AX123: =IF(OR(N123="YES", N123="Not Applicable"), AX$1, "0") -> 4 | AY123: =IF(OR(O123="YES", O123="Not Applicable"), AY$1, "0") -> 4 | AZ123: =IF(OR(P123="YES", P123="Not Applicable"), AZ$1, "0") -> 2 | BA123: =IF(OR(Q123="YES", Q123="Not Applicable"), BA$1, "0") -> 4 | BB123: =IF(OR(R123="YES", R123="Not Applicable"), BB$1, "0") -> 4 | BC123: =IF(OR(S123="YES", S123="Not Applicable"), BC$1, "0") -> 4 | BD123: =IF(OR(T123="YES", T123="Not Applicable"), BD$1, "0") -> 2 | ... BY123: =IF(OR(AO123="YES", AO123="Not Applicable"), BY$1, "0") -> 0 | BZ123: =SUM(AW123:BY123) -> 94 | CA123: =VLOOKUP(J:J,'Agent wise'!A:C,3,0) -> Saran S | CB123: =INT(E123) -> 45933 | CC123: =IF(BZ123>=94.5, "Excellent", IF(BZ123>89.5, "Good", IF(BZ123>84.5, "Average", "FC"))) -> Good | CJ123: =DAY(E123) -> 3 | CK123: =MONTH(E123) -> 10 | CL123: =YEAR(E123) -> 2025
A124: 45726.591 | B124: adharshleewvan003@gmail.com | C124: 0 / 50 | D124: Adharsh | E124: 45933 | F124: Wireless | G124: 45698 | H124: 9629631328 | I124: 137 | J124: VPS213 | K124: Tamil | L124: Tamil Nadu | M124: Yes | N124: Yes | O124: Yes | P124: Yes | Q124: Yes | R124: Yes | S124: Yes | T124: Yes | U124: Yes | V124: Yes | W124: Yes | X124: Yes | Y124: Yes | Z124: Yes | AA124: Yes | AB124: No | AC124: No | AD124: Yes | AE124: Yes | AF124: Yes | AG124: Yes | AH124: Not Applicable | AI124: Not Applicable | AJ124: Yes | AK124: Yes | AL124: Yes | AM124: Yes | AN124: Yes | AO124: Yes | AP124: Gave apology/reassurance/appropriate response, Explained hold time or Dead air | AQ124: Customer called and said he had been facing a VoLTE issue. The agent said she would be activating the VoLTE service, and it would be activated within24 hours. | AR124: Prepaid | AS124: SIM | AT124: SIM REPLACEMENT PROCESS | AU124: Good Call | AW124: =IF(OR(M124="YES", M124="Not Applicable"), AW$1, "0") -> 6 | AX124: =IF(OR(N124="YES", N124="Not Applicable"), AX$1, "0") -> 4 | AY124: =IF(OR(O124="YES", O124="Not Applicable"), AY$1, "0") -> 4 | AZ124: =IF(OR(P124="YES", P124="Not Applicable"), AZ$1, "0") -> 2 | BA124: =IF(OR(Q124="YES", Q124="Not Applicable"), BA$1, "0") -> 4 | BB124: =IF(OR(R124="YES", R124="Not Applicable"), BB$1, "0") -> 4 | BC124: =IF(OR(S124="YES", S124="Not Applicable"), BC$1, "0") -> 4 | BD124: =IF(OR(T124="YES", T124="Not Applicable"), BD$1, "0") -> 2 | ... BY124: =IF(OR(AO124="YES", AO124="Not Applicable"), BY$1, "0") -> 0 | BZ124: =SUM(AW124:BY124) -> 94 | CA124: =VLOOKUP(J:J,'Agent wise'!A:C,3,0) -> Saran S | CB124: =INT(E124) -> 45933 | CC124: =IF(BZ124>=94.5, "Excellent", IF(BZ124>89.5, "Good", IF(BZ124>84.5, "Average", "FC"))) -> Good | CJ124: =DAY(E124) -> 3 | CK124: =MONTH(E124) -> 10 | CL124: =YEAR(E124) -> 2025
A125: 45726.591 | B125: nehafire4444@gmail.com | C125: 0 / 50 | D125: Sneha | E125: 45933 | F125: Wireless | G125: 45698 | H125: 9500309333 | I125: 152 | J125: SBM550 | K125: Tamil | L125: Tamil Nadu | M125: Yes | N125: Yes | O125: Yes | P125: Yes | Q125: Yes | R125: Yes | S125: Yes | T125: Yes | U125: Yes | V125: Yes | W125: Yes | X125: Yes | Y125: Yes | Z125: Yes | AA125: Yes | AB125: Yes | AC125: Yes | AD125: Yes | AE125: Yes | AF125: Yes | AG125: Yes | AH125: Yes | AI125: Not Applicable | AJ125: Yes | AK125: Yes | AL125: Yes | AM125: Yes | AN125: Yes | AO125: Yes | AP125: GOOD CALL | AQ125: The customer called for new sim not activated regarding issue .The advisor check and given proper information recharge not updated need to update the recharge the sim will be activated. | AR125: Prepaid | AS125: UNIFIED SIM | AT125: VOICE SERVICES | AU125: Good Call | AW125: =IF(OR(M125="YES", M125="Not Applicable"), AW$1, "0") -> 6 | AX125: =IF(OR(N125="YES", N125="Not Applicable"), AX$1, "0") -> 4 | AY125: =IF(OR(O125="YES", O125="Not Applicable"), AY$1, "0") -> 4 | AZ125: =IF(OR(P125="YES", P125="Not Applicable"), AZ$1, "0") -> 2 | BA125: =IF(OR(Q125="YES", Q125="Not Applicable"), BA$1, "0") -> 4 | BB125: =IF(OR(R125="YES", R125="Not Applicable"), BB$1, "0") -> 4 | BC125: =IF(OR(S125="YES", S125="Not Applicable"), BC$1, "0") -> 4 | BD125: =IF(OR(T125="YES", T125="Not Applicable"), BD$1, "0") -> 2 | ... BY125: =IF(OR(AO125="YES", AO125="Not Applicable"), BY$1, "0") -> 0 | BZ125: =SUM(AW125:BY125) -> 100 | CA125: =VLOOKUP(J:J,'Agent wise'!A:C,3,0) -> Shakeer | CB125: =INT(E125) -> 45933 | CC125: =IF(BZ125>=94.5, "Excellent", IF(BZ125>89.5, "Good", IF(BZ125>84.5, "Average", "FC"))) -> Excellent | CJ125: =DAY(E125) -> 3 | CK125: =MONTH(E125) -> 10 | CL125: =YEAR(E125) -> 2025
A126: 45726.598 | B126: adharshleewvan003@gmail.com | C126: 0 / 50 | D126: Adharsh | E126: 45933 | F126: Wireless | G126: 45698 | H126: 9965443787 | I126: 122 | J126: VPS244 | K126: Tamil | L126: Tamil Nadu | M126: Yes | N126: Yes | O126: Yes | P126: Yes | Q126: Yes | R126: Yes | S126: Yes | T126: Yes | U126: Yes | V126: Yes | W126: Yes | X126: Yes | Y126: Yes | Z126: Yes | AA126: Yes | AB126: Yes | AC126: No | AD126: Yes | AE126: Yes | AF126: Yes | AG126: Yes | AH126: Not Applicable | AI126: Not Applicable | AJ126: Yes | AK126: Yes | AL126: Yes | AM126: Yes | AN126: Yes | AO126: Yes | AP126: Explained hold time or Dead air | AQ126: Customer called and inquired about recharge plan details related | AR126: Prepaid | AS126: PLANS AND VALIDITY DETAILS | AT126: ENQUIRY ON PREPAID PLANS | AU126: Fillings | AW126: =IF(OR(M126="YES", M126="Not Applicable"), AW$1, "0") -> 6 | AX126: =IF(OR(N126="YES", N126="Not Applicable"), AX$1, "0") -> 4 | AY126: =IF(OR(O126="YES", O126="Not Applicable"), AY$1, "0") -> 4 | AZ126: =IF(OR(P126="YES", P126="Not Applicable"), AZ$1, "0") -> 2 | BA126: =IF(OR(Q126="YES", Q126="Not Applicable"), BA$1, "0") -> 4 | BB126: =IF(OR(R126="YES", R126="Not Applicable"), BB$1, "0") -> 4 | BC126: =IF(OR(S126="YES", S126="Not Applicable"), BC$1, "0") -> 4 | BD126: =IF(OR(T126="YES", T126="Not Applicable"), BD$1, "0") -> 2 | ... BY126: =IF(OR(AO126="YES", AO126="Not Applicable"), BY$1, "0") -> 0 | BZ126: =SUM(AW126:BY126) -> 96 | CA126: =VLOOKUP(J:J,'Agent wise'!A:C,3,0) -> Shakeer | CB126: =INT(E126) -> 45933 | CC126: =IF(BZ126>=94.5, "Excellent", IF(BZ126>89.5, "Good", IF(BZ126>84.5, "Average", "FC"))) -> Excellent | CJ126: =DAY(E126) -> 3 | CK126: =MONTH(E126) -> 10 | CL126: =YEAR(E126) -> 2025
... A269: 45787.772 | B269: priyankajino2013@gmail.com | C269: 0 / 50 | D269: Priyanka | E269: 45935 | F269: Wireline | G269: 45757 | H269: 8072124503 | I269: 142 | J269: SBM264 | K269: Tamil | L269: Tamil Nadu | M269: No | N269: Yes | O269: Yes | P269: Yes | Q269: Yes | R269: Yes | S269: Yes | T269: Yes | U269: Yes | V269: Yes | W269: Yes | X269: Yes | Y269: Yes | Z269: Yes | AA269: No | AB269: No | AC269: Yes | AD269: Yes | AE269: Yes | AF269: Yes | AG269: Yes | AH269: Yes | AI269: Not Applicable | AJ269: Yes | AK269: Yes | AL269: Yes | AM269: Yes | AN269: Yes | AO269: Yes | AP269: AOI-greeting not done | AQ269: Opening & Introduction â€“ Done Customer details captured â€“Done Customer concern -Customer landline issue Resolution shared - Advisor complete probing to customers as per call application down Closing as per standard - Done. AOI-greeting not done | AR269: Postpaid | AS269: na | AT269: na | AU269: Good Call | AW269: =IF(OR(M269="YES", M269="Not Applicable"), AW$1, "0") -> 0 | AX269: =IF(OR(N269="YES", N269="Not Applicable"), AX$1, "0") -> 4 | AY269: =IF(OR(O269="YES", O269="Not Applicable"), AY$1, "0") -> 4 | AZ269: =IF(OR(P269="YES", P269="Not Applicable"), AZ$1, "0") -> 2 | BA269: =IF(OR(Q269="YES", Q269="Not Applicable"), BA$1, "0") -> 4 | BB269: =IF(OR(R269="YES", R269="Not Applicable"), BB$1, "0") -> 4 | BC269: =IF(OR(S269="YES", S269="Not Applicable"), BC$1, "0") -> 4 | BD269: =IF(OR(T269="YES", T269="Not Applicable"), BD$1, "0") -> 2 | ... BY269: =IF(OR(AO269="YES", AO269="Not Applicable"), BY$1, "0") -> 0 | BZ269: =SUM(AW269:BY269) -> 88 | CA269: =VLOOKUP(J:J,'Agent wise'!A:C,3,0) -> Shakeer | CB269: =INT(E269) -> 45935 | CC269: =IF(BZ269>=94.5, "Excellent", IF(BZ269>89.5, "Good", IF(BZ269>84.5, "Average", "FC"))) -> Average | CJ269: =DAY(E269) -> 5 | CK269: =MONTH(E269) -> 10 | CL269: =YEAR(E269) -> 2025
A270: 45787.776 | B270: nehafire4444@gmail.com | C270: 0 / 50 | D270: Sneha | E270: 45935 | F270: Wireline OBD | G270: 45726 | H270: 9976222010 | I270: 134 | J270: VPS171 | K270: Tamil | L270: Tamil Nadu | M270: Yes | N270: Yes | O270: Yes | P270: Yes | Q270: Yes | R270: Yes | S270: Yes | T270: Yes | U270: Yes | V270: Yes | W270: Yes | X270: Yes | Y270: Yes | Z270: Yes | AA270: Yes | AB270: Yes | AC270: Yes | AD270: Yes | AE270: Yes | AF270: Yes | AG270: Yes | AH270: Not Applicable | AI270: Not Applicable | AJ270: Yes | AK270: Yes | AL270: Yes | AM270: Yes | AN270: Yes | AO270: Yes | AQ270: The Advisor contact the customer for prelead details updation ,but customer need to know thw offer details so the advisor provide the cc helpdisk number . | AR270: Postpaid | AS270: PRELEAD | AT270: PRELEAD | AU270: Good Call | AW270: =IF(OR(M270="YES", M270="Not Applicable"), AW$1, "0") -> 6 | AX270: =IF(OR(N270="YES", N270="Not Applicable"), AX$1, "0") -> 4 | AY270: =IF(OR(O270="YES", O270="Not Applicable"), AY$1, "0") -> 4 | AZ270: =IF(OR(P270="YES", P270="Not Applicable"), AZ$1, "0") -> 2 | BA270: =IF(OR(Q270="YES", Q270="Not Applicable"), BA$1, "0") -> 4 | BB270: =IF(OR(R270="YES", R270="Not Applicable"), BB$1, "0") -> 4 | BC270: =IF(OR(S270="YES", S270="Not Applicable"), BC$1, "0") -> 4 | BD270: =IF(OR(T270="YES", T270="Not Applicable"), BD$1, "0") -> 2 | ... BY270: =IF(OR(AO270="YES", AO270="Not Applicable"), BY$1, "0") -> 0 | BZ270: =SUM(AW270:BY270) -> 100 | CA270: =VLOOKUP(J:J,'Agent wise'!A:C,3,0) -> Amal | CB270: =INT(E270) -> 45935 | CC270: =IF(BZ270>=94.5, "Excellent", IF(BZ270>89.5, "Good", IF(BZ270>84.5, "Average", "FC"))) -> Excellent | CJ270: =DAY(E270) -> 5 | CK270: =MONTH(E270) -> 10 | CL270: =YEAR(E270) -> 2025
A271: 45787.779 | B271: nehafire4444@gmail.com | C271: 0 / 50 | D271: Sneha | E271: 45935 | F271: Wireline OBD | G271: 45757 | H271: 9442906783 | I271: 166 | J271: VPS171 | K271: Tamil | L271: Tamil Nadu | M271: Yes | N271: Yes | O271: Yes | P271: Yes | Q271: Yes | R271: Yes | S271: Yes | T271: Yes | U271: Yes | V271: Yes | W271: Yes | X271: Yes | Y271: Yes | Z271: Yes | AA271: Yes | AB271: Yes | AC271: Yes | AD271: Yes | AE271: Yes | AF271: Yes | AG271: Yes | AH271: Not Applicable | AI271: Not Applicable | AJ271: Yes | AK271: Yes | AL271: Yes | AM271: Yes | AN271: Yes | AO271: Yes | AP271: GOOD CALL | AQ271: The advisor contacted the client and collect the address details, the customer who has given the address details | AR271: Postpaid | AS271: prelead | AT271: prelead | AU271: Good Call | AW271: =IF(OR(M271="YES", M271="Not Applicable"), AW$1, "0") -> 6 | AX271: =IF(OR(N271="YES", N271="Not Applicable"), AX$1, "0") -> 4 | AY271: =IF(OR(O271="YES", O271="Not Applicable"), AY$1, "0") -> 4 | AZ271: =IF(OR(P271="YES", P271="Not Applicable"), AZ$1, "0") -> 2 | BA271: =IF(OR(Q271="YES", Q271="Not Applicable"), BA$1, "0") -> 4 | BB271: =IF(OR(R271="YES", R271="Not Applicable"), BB$1, "0") -> 4 | BC271: =IF(OR(S271="YES", S271="Not Applicable"), BC$1, "0") -> 4 | BD271: =IF(OR(T271="YES", T271="Not Applicable"), BD$1, "0") -> 2 | ... BY271: =IF(OR(AO271="YES", AO271="Not Applicable"), BY$1, "0") -> 0 | BZ271: =SUM(AW271:BY271) -> 100 | CA271: =VLOOKUP(J:J,'Agent wise'!A:C,3,0) -> Amal | CB271: =INT(E271) -> 45935 | CC271: =IF(BZ271>=94.5, "Excellent", IF(BZ271>89.5, "Good", IF(BZ271>84.5, "Average", "FC"))) -> Excellent | CJ271: =DAY(E271) -> 5 | CK271: =MONTH(E271) -> 10 | CL271: =YEAR(E271) -> 2025
A272: 45787.779 | B272: priyankajino2013@gmail.com | C272: 0 / 50 | D272: Priyanka | E272: 45935 | F272: Wireline | G272: 45726 | H272: 7736749529 | I272: 138 | J272: SBM613 | K272: Malayalam | L272: Kerala | M272: Yes | N272: Yes | O272: Yes | P272: Yes | Q272: Yes | R272: Yes | S272: Yes | T272: Yes | U272: Yes | V272: Yes | W272: Yes | X272: Yes | Y272: Yes | Z272: Yes | AA272: No | AB272: Yes | AC272: Yes | AD272: Not Applicable | AE272: Yes | AF272: Yes | AG272: Yes | AH272: Yes | AI272: Not Applicable | AJ272: Yes | AK272: Yes | AL272: No | AM272: Yes | AN272: Yes | AO272: Yes | AP272: AOI-empathy missing | AQ272: Opening & Introduction â€“ Done Customer details captured â€“Done Customer concern -Customer landline issue Resolution shared - Advisor complete probing to customers as per call inactive Closing as per standard - Done. AOI-empathy missing | AR272: Postpaid | AS272: na | AT272: na | AU272: Good Call | AW272: =IF(OR(M272="YES", M272="Not Applicable"), AW$1, "0") -> 6 | AX272: =IF(OR(N272="YES", N272="Not Applicable"), AX$1, "0") -> 4 | AY272: =IF(OR(O272="YES", O272="Not Applicable"), AY$1, "0") -> 4 | AZ272: =IF(OR(P272="YES", P272="Not Applicable"), AZ$1, "0") -> 2 | BA272: =IF(OR(Q272="YES", Q272="Not Applicable"), BA$1, "0") -> 4 | BB272: =IF(OR(R272="YES", R272="Not Applicable"), BB$1, "0") -> 4 | BC272: =IF(OR(S272="YES", S272="Not Applicable"), BC$1, "0") -> 4 | BD272: =IF(OR(T272="YES", T272="Not Applicable"), BD$1, "0") -> 2 | ... BY272: =IF(OR(AO272="YES", AO272="Not Applicable"), BY$1, "0") -> 0 | BZ272: =SUM(AW272:BY272) -> 96 | CA272: =VLOOKUP(J:J,'Agent wise'!A:C,3,0) -> Amal | CB272: =INT(E272) -> 45935 | CC272: =IF(BZ272>=94.5, "Excellent", IF(BZ272>89.5, "Good", IF(BZ272>84.5, "Average", "FC"))) -> Excellent | CJ272: =DAY(E272) -> 5 | CK272: =MONTH(E272) -> 10 | CL272: =YEAR(E272) -> 2025
A273: 45787.781 | B273: nehafire4444@gmail.com | C273: 0 / 50 | D273: Sneha | E273: 45935 | F273: Wireline OBD | G273: 45757 | H273: 9445941540 | I273: 196 | J273: SBM963 | K273: Tamil | L273: Tamil Nadu | M273: Yes | N273: Yes | O273: Yes | P273: Yes | Q273: Yes | R273: Yes | S273: Yes | T273: Yes | U273: No | V273: Yes | W273: Yes | X273: Yes | Y273: Yes | Z273: No | AA273: Yes | AB273: Yes | AC273: Yes | AD273: Yes | AE273: Yes | AF273: Yes | AG273: Yes | AH273: Not Applicable | AI273: Not Applicable | AJ273: Yes | AK273: Yes | AL273: No | AM273: Yes | AN273: Yes | AO273: Yes | AP273: low active listening | AQ273: The advisor contacted the client and collect the address details, the customer who has given the address details | AR273: Postpaid | AS273: PRELEAD | AT273: PRELEAD | AU273: Good Call | AW273: =IF(OR(M273="YES", M273="Not Applicable"), AW$1, "0") -> 6 | AX273: =IF(OR(N273="YES", N273="Not Applicable"), AX$1, "0") -> 4 | AY273: =IF(OR(O273="YES", O273="Not Applicable"), AY$1, "0") -> 4 | AZ273: =IF(OR(P273="YES", P273="Not Applicable"), AZ$1, "0") -> 2 | BA273: =IF(OR(Q273="YES", Q273="Not Applicable"), BA$1, "0") -> 4 | BB273: =IF(OR(R273="YES", R273="Not Applicable"), BB$1, "0") -> 4 | BC273: =IF(OR(S273="YES", S273="Not Applicable"), BC$1, "0") -> 4 | BD273: =IF(OR(T273="YES", T273="Not Applicable"), BD$1, "0") -> 2 | ... BY273: =IF(OR(AO273="YES", AO273="Not Applicable"), BY$1, "0") -> 0 | BZ273: =SUM(AW273:BY273) -> 94 | CA273: =VLOOKUP(J:J,'Agent wise'!A:C,3,0) -> Shakeer | CB273: =INT(E273) -> 45935 | CC273: =IF(BZ273>=94.5, "Excellent", IF(BZ273>89.5, "Good", IF(BZ273>84.5, "Average", "FC"))) -> Good | CJ273: =DAY(E273) -> 5 | CK273: =MONTH(E273) -> 10 | CL273: =YEAR(E273) -> 2025
A274: 45787.783 | B274: priyankajino2013@gmail.com | C274: 0 / 50 | D274: Priyanka | E274: 45935 | F274: Wireline | G274: 45726 | H274: 8547517703 | I274: 134 | J274: SBM554 | K274: Malayalam | L274: Kerala | M274: Yes | N274: Yes | O274: Yes | P274: Yes | Q274: Yes | R274: Yes | S274: Yes | T274: Yes | U274: Yes | V274: Yes | W274: Yes | X274: Yes | Y274: Yes | Z274: Yes | AA274: No | AB274: No | AC274: Yes | AD274: Yes | AE274: Yes | AF274: Yes | AG274: Yes | AH274: Yes | AI274: No | AJ274: Yes | AK274: Yes | AL274: Yes | AM274: Yes | AN274: Yes | AO274: Yes | AP274: AOI-empathy missing,sr number not provide | AQ274: Opening & Introduction â€“ Done Customer details captured â€“Done Customer concern -Customer landline issue Resolution shared - Advisor complete probing to customers as per call complaint booking Closing as per standard - Done. AOI-empathy missing,sr number not provide | AR274: Postpaid | AS274: na | AT274: na | AU274: Good Call | AW274: =IF(OR(M274="YES", M274="Not Applicable"), AW$1, "0") -> 6 | AX274: =IF(OR(N274="YES", N274="Not Applicable"), AX$1, "0") -> 4 | AY274: =IF(OR(O274="YES", O274="Not Applicable"), AY$1, "0") -> 4 | AZ274: =IF(OR(P274="YES", P274="Not Applicable"), AZ$1, "0") -> 2 | BA274: =IF(OR(Q274="YES", Q274="Not Applicable"), BA$1, "0") -> 4 | BB274: =IF(OR(R274="YES", R274="Not Applicable"), BB$1, "0") -> 4 | BC274: =IF(OR(S274="YES", S274="Not Applicable"), BC$1, "0") -> 4 | BD274: =IF(OR(T274="YES", T274="Not Applicable"), BD$1, "0") -> 2 | ... BY274: =IF(OR(AO274="YES", AO274="Not Applicable"), BY$1, "0") -> 0 | BZ274: =SUM(AW274:BY274) -> 90 | CA274: =VLOOKUP(J:J,'Agent wise'!A:C,3,0) -> Adharsh | CB274: =INT(E274) -> 45935 | CC274: =IF(BZ274>=94.5, "Excellent", IF(BZ274>89.5, "Good", IF(BZ274>84.5, "Average", "FC"))) -> Good | CJ274: =DAY(E274) -> 5 | CK274: =MONTH(E274) -> 10 | CL274: =YEAR(E274) -> 2025
A275: 45787.787 | B275: priyankajino2013@gmail.com | C275: 0 / 50 | D275: Priyanka | E275: 45935 | F275: Wireline | G275: 45726 | H275: 8667864193 | I275: 133 | J275: SBM618 | K275: Tamil | L275: Tamil Nadu | M275: Yes | N275: Yes | O275: Yes | P275: Yes | Q275: Yes | R275: Yes | S275: Yes | T275: Yes | U275: Yes | V275: Yes | W275: Yes | X275: Yes | Y275: Yes | Z275: Yes | AA275: Yes | AB275: No | AC275: Yes | AD275: Yes | AE275: Yes | AF275: Yes | AG275: Yes | AH275: Yes | AI275: Yes | AJ275: Yes | AK275: Yes | AL275: Yes | AM275: Yes | AN275: Yes | AO275: Yes | AP275: AOI-apology missing, | AQ275: Opening & Introduction â€“ Done Customer details captured â€“Done Customer concern -Customer landline issue Resolution shared - Advisor complete probing to customers as per call complaint booking Closing as per standard - Done. AOI-apology missing, | AR275: Postpaid | AS275: na | AT275: na | AU275: Good Call | AW275: =IF(OR(M275="YES", M275="Not Applicable"), AW$1, "0") -> 6 | AX275: =IF(OR(N275="YES", N275="Not Applicable"), AX$1, "0") -> 4 | AY275: =IF(OR(O275="YES", O275="Not Applicable"), AY$1, "0") -> 4 | AZ275: =IF(OR(P275="YES", P275="Not Applicable"), AZ$1, "0") -> 2 | BA275: =IF(OR(Q275="YES", Q275="Not Applicable"), BA$1, "0") -> 4 | BB275: =IF(OR(R275="YES", R275="Not Applicable"), BB$1, "0") -> 4 | BC275: =IF(OR(S275="YES", S275="Not Applicable"), BC$1, "0") -> 4 | BD275: =IF(OR(T275="YES", T275="Not Applicable"), BD$1, "0") -> 2 | ... BY275: =IF(OR(AO275="YES", AO275="Not Applicable"), BY$1, "0") -> 0 | BZ275: =SUM(AW275:BY275) -> 98 | CA275: =VLOOKUP(J:J,'Agent wise'!A:C,3,0) -> Amal | CB275: =INT(E275) -> 45935 | CC275: =IF(BZ275>=94.5, "Excellent", IF(BZ275>89.5, "Good", IF(BZ275>84.5, "Average", "FC"))) -> Excellent | CJ275: =DAY(E275) -> 5 | CK275: =MONTH(E275) -> 10 | CL275: =YEAR(E275) -> 2025
A276: 45787.788 | B276: nehafire4444@gmail.com | C276: 0 / 50 | D276: Sneha | E276: 45935 | F276: MNP OBD | G276: 45757 | H276: 7598701190 | I276: 110 | J276: SBM267 | K276: Tamil | L276: Tamil Nadu | M276: Yes | N276: Yes | O276: Yes | P276: Yes | Q276: Yes | R276: Yes | S276: Yes | T276: Yes | U276: No | V276: Yes | W276: Yes | X276: Yes | Y276: Yes | Z276: Yes | AA276: Yes | AB276: No | AC276: Yes | AD276: Yes | AE276: Yes | AF276: Yes | AG276: Yes | AH276: Not Applicable | AI276: Not Applicable | AJ276: Yes | AK276: Yes | AL276: Yes | AM276: Yes | AN276: Yes | AO276: Yes | AP276: voice modulation not much to retain the customer | AQ276: The agent contact the MNP customer for retain the customer , The customer facing network regarding issue , not will to continue(voice modulation not much to retain the customer ) | AR276: Prepaid | AS276: COMPLETE CALL | AT276: NOT AGREED | AU276: Good Call | AW276: =IF(OR(M276="YES", M276="Not Applicable"), AW$1, "0") -> 6 | AX276: =IF(OR(N276="YES", N276="Not Applicable"), AX$1, "0") -> 4 | AY276: =IF(OR(O276="YES", O276="Not Applicable"), AY$1, "0") -> 4 | AZ276: =IF(OR(P276="YES", P276="Not Applicable"), AZ$1, "0") -> 2 | BA276: =IF(OR(Q276="YES", Q276="Not Applicable"), BA$1, "0") -> 4 | BB276: =IF(OR(R276="YES", R276="Not Applicable"), BB$1, "0") -> 4 | BC276: =IF(OR(S276="YES", S276="Not Applicable"), BC$1, "0") -> 4 | BD276: =IF(OR(T276="YES", T276="Not Applicable"), BD$1, "0") -> 2 | ... BY276: =IF(OR(AO276="YES", AO276="Not Applicable"), BY$1, "0") -> 0 | BZ276: =SUM(AW276:BY276) -> 94 | CA276: =VLOOKUP(J:J,'Agent wise'!A:C,3,0) -> Saran S | CB276: =INT(E276) -> 45935 | CC276: =IF(BZ276>=94.5, "Excellent", IF(BZ276>89.5, "Good", IF(BZ276>84.5, "Average", "FC"))) -> Good | CJ276: =DAY(E276) -> 5 | CK276: =MONTH(E276) -> 10 | CL276: =YEAR(E276) -> 2025
A277: 45787.792 | B277: priyankajino2013@gmail.com | C277: 0 / 50 | D277: Priyanka | E277: 45935 | F277: Wireline | G277: 45726 | H277: 9447632365 | I277: 130 | J277: SBM653 | K277: Malayalam | L277: Kerala | M277: Yes | N277: Yes | O277: Yes | P277: Yes | Q277: Yes | R277: Yes | S277: Yes | T277: Yes | U277: Yes | V277: Yes | W277: Yes | X277: Yes | Y277: Yes | Z277: Yes | AA277: Yes | AB277: No | AC277: Yes | AD277: Yes | AE277: Yes | AF277: Yes | AG277: Yes | AH277: Yes | AI277: Not Applicable | AJ277: Yes | AK277: Yes | AL277: Yes | AM277: Yes | AN277: Yes | AO277: Yes | AP277: AOI-apology missing, | AQ277: Opening & Introduction â€“ Done Customer details captured â€“Done Customer concern -Customer fiber issue Resolution shared - Advisor complete probing to customers as per call complaint booking Closing as per standard - Done. AOI-apology missing, | AR277: Postpaid | AS277: na | AT277: na | AU277: Good Call | AW277: =IF(OR(M277="YES", M277="Not Applicable"), AW$1, "0") -> 6 | AX277: =IF(OR(N277="YES", N277="Not Applicable"), AX$1, "0") -> 4 | AY277: =IF(OR(O277="YES", O277="Not Applicable"), AY$1, "0") -> 4 | AZ277: =IF(OR(P277="YES", P277="Not Applicable"), AZ$1, "0") -> 2 | BA277: =IF(OR(Q277="YES", Q277="Not Applicable"), BA$1, "0") -> 4 | BB277: =IF(OR(R277="YES", R277="Not Applicable"), BB$1, "0") -> 4 | BC277: =IF(OR(S277="YES", S277="Not Applicable"), BC$1, "0") -> 4 | BD277: =IF(OR(T277="YES", T277="Not Applicable"), BD$1, "0") -> 2 | ... BY277: =IF(OR(AO277="YES", AO277="Not Applicable"), BY$1, "0") -> 0 | BZ277: =SUM(AW277:BY277) -> 98 | CA277: =VLOOKUP(J:J,'Agent wise'!A:C,3,0) -> Amal | CB277: =INT(E277) -> 45935 | CC277: =IF(BZ277>=94.5, "Excellent", IF(BZ277>89.5, "Good", IF(BZ277>84.5, "Average", "FC"))) -> Excellent | CJ277: =DAY(E277) -> 5 | CK277: =MONTH(E277) -> 10 | CL277: =YEAR(E277) -> 2025
A278: 45787.793 | B278: nehafire4444@gmail.com | C278: 0 / 50 | D278: Sneha | E278: 45935 | F278: MNP OBD | G278: 45757 | H278: 9487114489 | I278: 234 | J278: SBM625 | K278: Tamil | L278: Tamil Nadu | M278: Yes | N278: Yes | O278: Yes | P278: Yes | Q278: Yes | R278: Yes | S278: Yes | T278: Yes | U278: No | V278: Yes | W278: Yes | X278: Yes | Y278: Yes | Z278: Yes | AA278: Yes | AB278: Yes | AC278: Yes | AD278: Yes | AE278: Yes | AF278: Yes | AG278: Yes | AH278: Not Applicable | AI278: Not Applicable | AJ278: Yes | AK278: Yes | AL278: Yes | AM278: Yes | AN278: Yes | AO278: Yes | AP278: GOOD CALL | AQ278: Agent contacts MNP customer for customer retention, regarding network issue facing customer, does not want to proceed because the issue on the other states | AR278: Postpaid | AS278: COMPLETE CALL | AT278: NOT AGREED | AU278: Good Call | AW278: =IF(OR(M278="YES", M278="Not Applicable"), AW$1, "0") -> 6 | AX278: =IF(OR(N278="YES", N278="Not Applicable"), AX$1, "0") -> 4 | AY278: =IF(OR(O278="YES", O278="Not Applicable"), AY$1, "0") -> 4 | AZ278: =IF(OR(P278="YES", P278="Not Applicable"), AZ$1, "0") -> 2 | BA278: =IF(OR(Q278="YES", Q278="Not Applicable"), BA$1, "0") -> 4 | BB278: =IF(OR(R278="YES", R278="Not Applicable"), BB$1, "0") -> 4 | BC278: =IF(OR(S278="YES", S278="Not Applicable"), BC$1, "0") -> 4 | BD278: =IF(OR(T278="YES", T278="Not Applicable"), BD$1, "0") -> 2 | ... BY278: =IF(OR(AO278="YES", AO278="Not Applicable"), BY$1, "0") -> 0 | BZ278: =SUM(AW278:BY278) -> 96 | CA278: =VLOOKUP(J:J,'Agent wise'!A:C,3,0) -> Saran S | CB278: =INT(E278) -> 45935 | CC278: =IF(BZ278>=94.5, "Excellent", IF(BZ278>89.5, "Good", IF(BZ278>84.5, "Average", "FC"))) -> Excellent | CJ278: =DAY(E278) -> 5 | CK278: =MONTH(E278) -> 10 | CL278: =YEAR(E278) -> 2025
A279: 45787.793 | B279: priyankajino2013@gmail.com | C279: 0 / 50 | D279: Priyanka | E279: 45935 | F279: Wireline | G279: 45726 | H279: 9488759020 | I279: 143 | J279: SBM758 | K279: Tamil | L279: Tamil Nadu | M279: Yes | N279: Yes | O279: Yes | P279: Yes | Q279: Yes | R279: Yes | S279: Yes | T279: Yes | U279: Yes | V279: Yes | W279: Yes | X279: Yes | Y279: Yes | Z279: Yes | AA279: No | AB279: Yes | AC279: Yes | AD279: Yes | AE279: Yes | AF279: Yes | AG279: Yes | AH279: Yes | AI279: Not Applicable | AJ279: Yes | AK279: Yes | AL279: Yes | AM279: Yes | AN279: Yes | AO279: Yes | AP279: AOI-empathy missing, | AQ279: Opening & Introduction â€“ Done Customer details captured â€“Done Customer concern -Customer sim details Resolution shared - Advisor complete probing to customers as per call 18001801503 Closing as per standard - Done. AOI-empathy missing, | AR279: Postpaid | AS279: na | AT279: na | AU279: Good Call | AW279: =IF(OR(M279="YES", M279="Not Applicable"), AW$1, "0") -> 6 | AX279: =IF(OR(N279="YES", N279="Not Applicable"), AX$1, "0") -> 4 | AY279: =IF(OR(O279="YES", O279="Not Applicable"), AY$1, "0") -> 4 | AZ279: =IF(OR(P279="YES", P279="Not Applicable"), AZ$1, "0") -> 2 | BA279: =IF(OR(Q279="YES", Q279="Not Applicable"), BA$1, "0") -> 4 | BB279: =IF(OR(R279="YES", R279="Not Applicable"), BB$1, "0") -> 4 | BC279: =IF(OR(S279="YES", S279="Not Applicable"), BC$1, "0") -> 4 | BD279: =IF(OR(T279="YES", T279="Not Applicable"), BD$1, "0") -> 2 | ... BY279: =IF(OR(AO279="YES", AO279="Not Applicable"), BY$1, "0") -> 0 | BZ279: =SUM(AW279:BY279) -> 96 | CA279: =VLOOKUP(J:J,'Agent wise'!A:C,3,0) -> Amal | CB279: =INT(E279) -> 45935 | CC279: =IF(BZ279>=94.5, "Excellent", IF(BZ279>89.5, "Good", IF(BZ279>84.5, "Average", "FC"))) -> Excellent | CJ279: =DAY(E279) -> 5 | CK279: =MONTH(E279) -> 10 | CL279: =YEAR(E279) -> 2025
A280: 45787.799 | B280: nehafire4444@gmail.com | C280: 0 / 50 | D280: Sneha | E280: 45935 | F280: MNP OBD | G280: 45757 | H280: 9344759520 | I280: 185 | J280: SBM711 | K280: Tamil | L280: Tamil Nadu | M280: Yes | N280: Yes | O280: Yes | P280: Yes | Q280: Yes | R280: Yes | S280: Yes | T280: Yes | U280: Yes | V280: Yes | W280: Yes | X280: Yes | Y280: Yes | Z280: No | AA280: Yes | AB280: Yes | AC280: Yes | AD280: Yes | AE280: Yes | AF280: Yes | AG280: Yes | AH280: Yes | AI280: Not Applicable | AJ280: Yes | AK280: Yes | AL280: Yes | AM280: Yes | AN280: Yes | AO280: Yes | AP280: lack of energy on the call | AQ280: Agent contacts MNP customer for customer retention, regarding network issue facing customer, does not want to proceed | AR280: Prepaid | AS280: COMPLETE CALL | AT280: NOT AGREED | AU280: Good Call | AW280: =IF(OR(M280="YES", M280="Not Applicable"), AW$1, "0") -> 6 | AX280: =IF(OR(N280="YES", N280="Not Applicable"), AX$1, "0") -> 4 | AY280: =IF(OR(O280="YES", O280="Not Applicable"), AY$1, "0") -> 4 | AZ280: =IF(OR(P280="YES", P280="Not Applicable"), AZ$1, "0") -> 2 | BA280: =IF(OR(Q280="YES", Q280="Not Applicable"), BA$1, "0") -> 4 | BB280: =IF(OR(R280="YES", R280="Not Applicable"), BB$1, "0") -> 4 | BC280: =IF(OR(S280="YES", S280="Not Applicable"), BC$1, "0") -> 4 | BD280: =IF(OR(T280="YES", T280="Not Applicable"), BD$1, "0") -> 2 | ... BY280: =IF(OR(AO280="YES", AO280="Not Applicable"), BY$1, "0") -> 0 | BZ280: =SUM(AW280:BY280) -> 98 | CA280: =VLOOKUP(J:J,'Agent wise'!A:C,3,0) -> Shiny | CB280: =INT(E280) -> 45935 | CC280: =IF(BZ280>=94.5, "Excellent", IF(BZ280>89.5, "Good", IF(BZ280>84.5, "Average", "FC"))) -> Excellent | CJ280: =DAY(E280) -> 5 | CK280: =MONTH(E280) -> 10 | CL280: =YEAR(E280) -> 2025
A281: 45787.914 | B281: shakeerfazal11@gmail.com | C281: 0 / 50 | D281: Shakeer | E281: 45935 | F281: Wireless | G281: 45787 | H281: 9400152954 | I281: 135 | J281: SBM422 | K281: Malayalam | L281: Kerala | M281: Yes | N281: Yes | O281: Yes | P281: Yes | Q281: Yes | R281: Yes | S281: Yes | T281: Yes | U281: No | V281: Yes | W281: Yes | X281: Not Applicable | Y281: Yes | Z281: No | AA281: No | AB281: Yes | AC281: Not Applicable | AD281: Not Applicable | AE281: Yes | AF281: Not Applicable | AG281: Yes | AH281: Not Applicable | AI281: Not Applicable | AJ281: Yes | AK281: Yes | AL281: No | AM281: Yes | AN281: Yes | AO281: Yes | AP281: Not used empathy, No active listening skill, No further assistance | AQ281: Customer called and inquired about Weak signal related issue, Agent checked and given proper information but not followed required quality parameter properly. | AR281: Prepaid | AS281: VOICE SERVICES | AT281: WEAK SIGNAL | AU281: Interuption | AW281: =IF(OR(M281="YES", M281="Not Applicable"), AW$1, "0") -> 6 | AX281: =IF(OR(N281="YES", N281="Not Applicable"), AX$1, "0") -> 4 | AY281: =IF(OR(O281="YES", O281="Not Applicable"), AY$1, "0") -> 4 | AZ281: =IF(OR(P281="YES", P281="Not Applicable"), AZ$1, "0") -> 2 | BA281: =IF(OR(Q281="YES", Q281="Not Applicable"), BA$1, "0") -> 4 | BB281: =IF(OR(R281="YES", R281="Not Applicable"), BB$1, "0") -> 4 | BC281: =IF(OR(S281="YES", S281="Not Applicable"), BC$1, "0") -> 4 | BD281: =IF(OR(T281="YES", T281="Not Applicable"), BD$1, "0") -> 2 | ... BY281: =IF(OR(AO281="YES", AO281="Not Applicable"), BY$1, "0") -> 0 | BZ281: =SUM(AW281:BY281) -> 90 | CA281: =VLOOKUP(J:J,'Agent wise'!A:C,3,0) -> Shakeer | CB281: =INT(E281) -> 45935 | CC281: =IF(BZ281>=94.5, "Excellent", IF(BZ281>89.5, "Good", IF(BZ281>84.5, "Average", "FC"))) -> Good | CJ281: =DAY(E281) -> 5 | CK281: =MONTH(E281) -> 10 | CL281: =YEAR(E281) -> 2025
A282: 45787.918 | B282: shakeerfazal11@gmail.com | C282: 0 / 50 | D282: Shakeer | E282: 45935 | F282: Wireless | G282: 45787 | H282: 9497124500 | I282: 160 | J282: SBM422 | K282: Malayalam | L282: Kerala | M282: Yes | N282: Yes | O282: Yes | P282: Yes | Q282: Yes | R282: Yes | S282: Yes | T282: Yes | U282: No | V282: Yes | W282: Yes | X282: Not Applicable | Y282: Yes | Z282: Yes | AA282: No | AB282: Yes | AC282: No | AD282: Not Applicable | AE282: Yes | AF282: Not Applicable | AG282: Yes | AH282: Not Applicable | AI282: Yes | AJ282: Yes | AK282: Yes | AL282: No | AM282: Yes | AN282: Yes | AO282: Yes | AP282: Not used empathy words, Dead air, No further assistance | AQ282: Customer called and inquired about Weak signal related issue, Agent checked and taken poor coverage related complaint but not followed required quality parameter properly. | AR282: Prepaid | AS282: COMPLAINT | AT282: POOR NETWORK COVERAGE | AU282: Good Call | AW282: =IF(OR(M282="YES", M282="Not Applicable"), AW$1, "0") -> 6 | AX282: =IF(OR(N282="YES", N282="Not Applicable"), AX$1, "0") -> 4 | AY282: =IF(OR(O282="YES", O282="Not Applicable"), AY$1, "0") -> 4 | AZ282: =IF(OR(P282="YES", P282="Not Applicable"), AZ$1, "0") -> 2 | BA282: =IF(OR(Q282="YES", Q282="Not Applicable"), BA$1, "0") -> 4 | BB282: =IF(OR(R282="YES", R282="Not Applicable"), BB$1, "0") -> 4 | BC282: =IF(OR(S282="YES", S282="Not Applicable"), BC$1, "0") -> 4 | BD282: =IF(OR(T282="YES", T282="Not Applicable"), BD$1, "0") -> 2 | ... BY282: =IF(OR(AO282="YES", AO282="Not Applicable"), BY$1, "0") -> 0 | BZ282: =SUM(AW282:BY282) -> 88 | CA282: =VLOOKUP(J:J,'Agent wise'!A:C,3,0) -> Shakeer | CB282: =INT(E282) -> 45935 | CC282: =IF(BZ282>=94.5, "Excellent", IF(BZ282>89.5, "Good", IF(BZ282>84.5, "Average", "FC"))) -> Average | CJ282: =DAY(E282) -> 5 | CK282: =MONTH(E282) -> 10 | CL282: =YEAR(E282) -> 2025
... A359: 45818.924 | B359: amal.babu@visionplusindia.in | C359: 0 / 50 | D359: Amal | E359: 45935 | F359: Wireline | G359: 45787 | H359: 9943817971 | I359: 248 | J359: SBM157 | K359: Tamil | L359: Tamil Nadu | M359: Yes | N359: Yes | O359: Yes | P359: Yes | Q359: Yes | R359: Yes | S359: Yes | T359: Yes | U359: Yes | V359: Yes | W359: Yes | X359: Yes | Y359: Yes | Z359: Yes | AA359: Yes | AB359: Yes | AC359: No | AD359: Yes | AE359: Yes | AF359: Yes | AG359: Yes | AH359: Not Applicable | AI359: Yes | AJ359: Not Applicable | AK359: Yes | AL359: No | AM359: Yes | AN359: Yes | AO359: Yes | AP359: Script adherence and Dead air | AQ359: The customer called and Inquiry about OTT not working related Issue agent checked and Information given Properly | AR359: Postpaid | AS359: SERVICE - REQUEST OTT SERVICE ACTIVATION | AT359: SERVICE - REQUEST OTT SERVICE ACTIVATION | AU359: Good Call | AW359: =IF(OR(M359="YES", M359="Not Applicable"), AW$1, "0") -> 6 | AX359: =IF(OR(N359="YES", N359="Not Applicable"), AX$1, "0") -> 4 | AY359: =IF(OR(O359="YES", O359="Not Applicable"), AY$1, "0") -> 4 | AZ359: =IF(OR(P359="YES", P359="Not Applicable"), AZ$1, "0") -> 2 | BA359: =IF(OR(Q359="YES", Q359="Not Applicable"), BA$1, "0") -> 4 | BB359: =IF(OR(R359="YES", R359="Not Applicable"), BB$1, "0") -> 4 | BC359: =IF(OR(S359="YES", S359="Not Applicable"), BC$1, "0") -> 4 | BD359: =IF(OR(T359="YES", T359="Not Applicable"), BD$1, "0") -> 2 | ... BY359: =IF(OR(AO359="YES", AO359="Not Applicable"), BY$1, "0") -> 0 | BZ359: =SUM(AW359:BY359) -> 96 | CA359: =VLOOKUP(J:J,'Agent wise'!A:C,3,0) -> Saran S | CB359: =INT(E359) -> 45935 | CC359: =IF(BZ359>=94.5, "Excellent", IF(BZ359>89.5, "Good", IF(BZ359>84.5, "Average", "FC"))) -> Excellent | CJ359: =DAY(E359) -> 5 | CK359: =MONTH(E359) -> 10 | CL359: =YEAR(E359) -> 2025
A360: 45818.928 | B360: amal.babu@visionplusindia.in | C360: 0 / 50 | D360: Amal | E360: 45935 | F360: Wireline | G360: 45787 | H360: 9843616909 | I360: 284 | J360: 9843616909 | K360: English | L360: Tamil Nadu | M360: Yes | N360: Yes | O360: Yes | P360: Yes | Q360: Yes | R360: Yes | S360: Yes | T360: Yes | U360: Yes | V360: Yes | W360: Yes | X360: Yes | Y360: Yes | Z360: Yes | AA360: Yes | AB360: Yes | AC360: Yes | AD360: Yes | AE360: Yes | AF360: Yes | AG360: Yes | AH360: Not Applicable | AI360: Not Applicable | AJ360: Yes | AK360: Yes | AL360: Yes | AM360: Yes | AN360: Yes | AO360: Yes | AP360: Good call | AQ360: The customer called and Inquiry about plan details and Billing details agent checked and explained the Bill details Properly | AR360: Postpaid | AS360: SERVICE - CHANGE OR UPGRADE CURRENT PLAN | AT360: SERVICE - CHANGE OR UPGRADE CURRENT PLAN | AU360: Wow Call | AW360: =IF(OR(M360="YES", M360="Not Applicable"), AW$1, "0") -> 6 | AX360: =IF(OR(N360="YES", N360="Not Applicable"), AX$1, "0") -> 4 | AY360: =IF(OR(O360="YES", O360="Not Applicable"), AY$1, "0") -> 4 | AZ360: =IF(OR(P360="YES", P360="Not Applicable"), AZ$1, "0") -> 2 | BA360: =IF(OR(Q360="YES", Q360="Not Applicable"), BA$1, "0") -> 4 | BB360: =IF(OR(R360="YES", R360="Not Applicable"), BB$1, "0") -> 4 | BC360: =IF(OR(S360="YES", S360="Not Applicable"), BC$1, "0") -> 4 | BD360: =IF(OR(T360="YES", T360="Not Applicable"), BD$1, "0") -> 2 | ... BY360: =IF(OR(AO360="YES", AO360="Not Applicable"), BY$1, "0") -> 0 | BZ360: =SUM(AW360:BY360) -> 100 | CA360: =VLOOKUP(J:J,'Agent wise'!A:C,3,0) -> #N/A | CB360: =INT(E360) -> 45935 | CC360: =IF(BZ360>=94.5, "Excellent", IF(BZ360>89.5, "Good", IF(BZ360>84.5, "Average", "FC"))) -> Excellent | CJ360: =DAY(E360) -> 5 | CK360: =MONTH(E360) -> 10 | CL360: =YEAR(E360) -> 2025
A361: 45818.93 | B361: amal.babu@visionplusindia.in | C361: 0 / 50 | D361: Amal | E361: 45935 | F361: Wireline | G361: 45787 | H361: 9947178201 | I361: 186 | J361: SBM794 | K361: Malayalam | L361: Kerala | M361: Yes | N361: Yes | O361: Yes | P361: Yes | Q361: Yes | R361: Yes | S361: Yes | T361: Yes | U361: Yes | V361: Yes | W361: Yes | X361: Yes | Y361: Yes | Z361: Yes | AA361: Yes | AB361: Yes | AC361: Yes | AD361: Yes | AE361: Yes | AF361: Yes | AG361: Yes | AH361: Not Applicable | AI361: Yes | AJ361: Yes | AK361: Yes | AL361: Yes | AM361: Yes | AN361: Yes | AO361: Yes | AP361: Good Call | AQ361: The customer called and Inquiry about internet not getting related Issue Agent checked and Booked a complaint | AR361: Postpaid | AS361: FAULT - NO INTERNET CONNECTIVITY | AT361: FAULT - NO INTERNET CONNECTIVITY | AU361: Good Call | AW361: =IF(OR(M361="YES", M361="Not Applicable"), AW$1, "0") -> 6 | AX361: =IF(OR(N361="YES", N361="Not Applicable"), AX$1, "0") -> 4 | AY361: =IF(OR(O361="YES", O361="Not Applicable"), AY$1, "0") -> 4 | AZ361: =IF(OR(P361="YES", P361="Not Applicable"), AZ$1, "0") -> 2 | BA361: =IF(OR(Q361="YES", Q361="Not Applicable"), BA$1, "0") -> 4 | BB361: =IF(OR(R361="YES", R361="Not Applicable"), BB$1, "0") -> 4 | BC361: =IF(OR(S361="YES", S361="Not Applicable"), BC$1, "0") -> 4 | BD361: =IF(OR(T361="YES", T361="Not Applicable"), BD$1, "0") -> 2 | ... BY361: =IF(OR(AO361="YES", AO361="Not Applicable"), BY$1, "0") -> 0 | BZ361: =SUM(AW361:BY361) -> 100 | CA361: =VLOOKUP(J:J,'Agent wise'!A:C,3,0) -> Amal | CB361: =INT(E361) -> 45935 | CC361: =IF(BZ361>=94.5, "Excellent", IF(BZ361>89.5, "Good", IF(BZ361>84.5, "Average", "FC"))) -> Excellent | CJ361: =DAY(E361) -> 5 | CK361: =MONTH(E361) -> 10 | CL361: =YEAR(E361) -> 2025
A362: 45818.933 | B362: amal.babu@visionplusindia.in | C362: 0 / 50 | D362: Amal | E362: 45935 | F362: Wireline | G362: 45787 | H362: 9843616909 | I362: 248 | J362: SBM794 | K362: English | L362: Tamil Nadu | M362: Yes | N362: Yes | O362: Yes | P362: Yes | Q362: Yes | R362: Yes | S362: Yes | T362: Yes | U362: Yes | V362: Yes | W362: Yes | X362: Yes | Y362: Yes | Z362: Yes | AA362: Yes | AB362: Yes | AC362: Yes | AD362: Yes | AE362: Yes | AF362: Yes | AG362: Yes | AH362: Not Applicable | AI362: Not Applicable | AJ362: Yes | AK362: Yes | AL362: Yes | AM362: Yes | AN362: Yes | AO362: Yes | AP362: Good call | AQ362: The customer called and Inquiry about plan details Billing details and agent checked and explained the Bill details Properly | AR362: Postpaid | AS362: SERVICE - CHANGE OR UPGRADE CURRENT PLAN | AT362: SERVICE - CHANGE OR UPGRADE CURRENT PLAN | AU362: Wow Call | AW362: =IF(OR(M362="YES", M362="Not Applicable"), AW$1, "0") -> 6 | AX362: =IF(OR(N362="YES", N362="Not Applicable"), AX$1, "0") -> 4 | AY362: =IF(OR(O362="YES", O362="Not Applicable"), AY$1, "0") -> 4 | AZ362: =IF(OR(P362="YES", P362="Not Applicable"), AZ$1, "0") -> 2 | BA362: =IF(OR(Q362="YES", Q362="Not Applicable"), BA$1, "0") -> 4 | BB362: =IF(OR(R362="YES", R362="Not Applicable"), BB$1, "0") -> 4 | BC362: =IF(OR(S362="YES", S362="Not Applicable"), BC$1, "0") -> 4 | BD362: =IF(OR(T362="YES", T362="Not Applicable"), BD$1, "0") -> 2 | ... BY362: =IF(OR(AO362="YES", AO362="Not Applicable"), BY$1, "0") -> 0 | BZ362: =SUM(AW362:BY362) -> 100 | CA362: =VLOOKUP(J:J,'Agent wise'!A:C,3,0) -> Amal | CB362: =INT(E362) -> 45935 | CC362: =IF(BZ362>=94.5, "Excellent", IF(BZ362>89.5, "Good", IF(BZ362>84.5, "Average", "FC"))) -> Excellent | CJ362: =DAY(E362) -> 5 | CK362: =MONTH(E362) -> 10 | CL362: =YEAR(E362) -> 2025
A363: 45818.936 | B363: amal.babu@visionplusindia.in | C363: 0 / 50 | D363: Amal | E363: 45935 | F363: Wireline | G363: 45787 | H363: 7559809784 | I363: 148 | J363: SBM767 | K363: Malayalam | L363: Kerala | M363: Yes | N363: Yes | O363: Yes | P363: Yes | Q363: Yes | R363: Yes | S363: Yes | T363: Yes | U363: Yes | V363: Yes | W363: Yes | X363: Yes | Y363: Yes | Z363: Yes | AA363: Yes | AB363: No | AC363: Yes | AD363: Yes | AE363: Yes | AF363: Yes | AG363: Yes | AH363: Not Applicable | AI363: No | AJ363: Yes | AK363: Yes | AL363: No | AM363: Yes | AN363: Yes | AO363: Yes | AP363: Failed to ask apology and Complaint number not Provided | AQ363: The customer called and Inquiry about internet not getting related Issue Agent checked and Booked a complaint | AR363: Postpaid | AS363: FAULT - NO INTERNET CONNECTIVITY | AT363: FAULT - NO INTERNET CONNECTIVITY | AU363: Good Call | AW363: =IF(OR(M363="YES", M363="Not Applicable"), AW$1, "0") -> 6 | AX363: =IF(OR(N363="YES", N363="Not Applicable"), AX$1, "0") -> 4 | AY363: =IF(OR(O363="YES", O363="Not Applicable"), AY$1, "0") -> 4 | AZ363: =IF(OR(P363="YES", P363="Not Applicable"), AZ$1, "0") -> 2 | BA363: =IF(OR(Q363="YES", Q363="Not Applicable"), BA$1, "0") -> 4 | BB363: =IF(OR(R363="YES", R363="Not Applicable"), BB$1, "0") -> 4 | BC363: =IF(OR(S363="YES", S363="Not Applicable"), BC$1, "0") -> 4 | BD363: =IF(OR(T363="YES", T363="Not Applicable"), BD$1, "0") -> 2 | ... BY363: =IF(OR(AO363="YES", AO363="Not Applicable"), BY$1, "0") -> 0 | BZ363: =SUM(AW363:BY363) -> 94 | CA363: =VLOOKUP(J:J,'Agent wise'!A:C,3,0) -> Shakeer | CB363: =INT(E363) -> 45935 | CC363: =IF(BZ363>=94.5, "Excellent", IF(BZ363>89.5, "Good", IF(BZ363>84.5, "Average", "FC"))) -> Good | CJ363: =DAY(E363) -> 5 | CK363: =MONTH(E363) -> 10 | CL363: =YEAR(E363) -> 2025
A364: 45818.939 | B364: amal.babu@visionplusindia.in | C364: 0 / 50 | D364: Amal | E364: 45936 | F364: Wireline | G364: 45818 | H364: 9940640635 | I364: 156 | J364: SBM653 | K364: Tamil | L364: Tamil Nadu | M364: Yes | N364: Yes | O364: Yes | P364: Yes | Q364: Yes | R364: Yes | S364: Yes | T364: Yes | U364: Yes | V364: Yes | W364: Yes | X364: Yes | Y364: Yes | Z364: Yes | AA364: Yes | AB364: Yes | AC364: Yes | AD364: Yes | AE364: Yes | AF364: Yes | AG364: Yes | AH364: Not Applicable | AI364: Yes | AJ364: Yes | AK364: Yes | AL364: Yes | AM364: Yes | AN364: Yes | AO364: Yes | AP364: Wow Call | AQ364: The customer facing Landline - Voice not working related Issue, agent checked and Booked a complaint | AR364: Postpaid | AS364: FAULT - LANDLINE IS DEAD OR NOT WORKING | AT364: FAULT - LANDLINE IS DEAD OR NOT WORKING | AU364: Wow Call | AW364: =IF(OR(M364="YES", M364="Not Applicable"), AW$1, "0") -> 6 | AX364: =IF(OR(N364="YES", N364="Not Applicable"), AX$1, "0") -> 4 | AY364: =IF(OR(O364="YES", O364="Not Applicable"), AY$1, "0") -> 4 | AZ364: =IF(OR(P364="YES", P364="Not Applicable"), AZ$1, "0") -> 2 | BA364: =IF(OR(Q364="YES", Q364="Not Applicable"), BA$1, "0") -> 4 | BB364: =IF(OR(R364="YES", R364="Not Applicable"), BB$1, "0") -> 4 | BC364: =IF(OR(S364="YES", S364="Not Applicable"), BC$1, "0") -> 4 | BD364: =IF(OR(T364="YES", T364="Not Applicable"), BD$1, "0") -> 2 | ... BY364: =IF(OR(AO364="YES", AO364="Not Applicable"), BY$1, "0") -> 0 | BZ364: =SUM(AW364:BY364) -> 100 | CA364: =VLOOKUP(J:J,'Agent wise'!A:C,3,0) -> Amal | CB364: =INT(E364) -> 45936 | CC364: =IF(BZ364>=94.5, "Excellent", IF(BZ364>89.5, "Good", IF(BZ364>84.5, "Average", "FC"))) -> Excellent | CJ364: =DAY(E364) -> 6 | CK364: =MONTH(E364) -> 10 | CL364: =YEAR(E364) -> 2025
A365: 45818.941 | B365: amal.babu@visionplusindia.in | C365: 0 / 50 | D365: Amal | E365: 45936 | F365: Wireline | G365: 45818 | H365: 9025927792 | I365: 137 | J365: SBM653 | K365: Tamil | L365: Tamil Nadu | M365: Yes | N365: Yes | O365: Yes | P365: Yes | Q365: Yes | R365: Yes | S365: Yes | T365: Yes | U365: Yes | V365: Yes | W365: Yes | X365: Yes | Y365: Yes | Z365: Yes | AA365: Yes | AB365: Yes | AC365: Yes | AD365: Yes | AE365: Yes | AF365: Yes | AG365: Yes | AH365: Not Applicable | AI365: Yes | AJ365: Yes | AK365: Yes | AL365: Yes | AM365: Yes | AN365: Yes | AO365: Yes | AP365: Good Call | AQ365: The customer called and Inquiry about internet not getting related Issue Agent checked and Booked a complaint | AR365: Postpaid | AS365: FAULT - NO INTERNET CONNECTIVITY | AT365: FAULT - NO INTERNET CONNECTIVITY | AU365: Good Call | AW365: =IF(OR(M365="YES", M365="Not Applicable"), AW$1, "0") -> 6 | AX365: =IF(OR(N365="YES", N365="Not Applicable"), AX$1, "0") -> 4 | AY365: =IF(OR(O365="YES", O365="Not Applicable"), AY$1, "0") -> 4 | AZ365: =IF(OR(P365="YES", P365="Not Applicable"), AZ$1, "0") -> 2 | BA365: =IF(OR(Q365="YES", Q365="Not Applicable"), BA$1, "0") -> 4 | BB365: =IF(OR(R365="YES", R365="Not Applicable"), BB$1, "0") -> 4 | BC365: =IF(OR(S365="YES", S365="Not Applicable"), BC$1, "0") -> 4 | BD365: =IF(OR(T365="YES", T365="Not Applicable"), BD$1, "0") -> 2 | ... BY365: =IF(OR(AO365="YES", AO365="Not Applicable"), BY$1, "0") -> 0 | BZ365: =SUM(AW365:BY365) -> 100 | CA365: =VLOOKUP(J:J,'Agent wise'!A:C,3,0) -> Amal | CB365: =INT(E365) -> 45936 | CC365: =IF(BZ365>=94.5, "Excellent", IF(BZ365>89.5, "Good", IF(BZ365>84.5, "Average", "FC"))) -> Excellent | CJ365: =DAY(E365) -> 6 | CK365: =MONTH(E365) -> 10 | CL365: =YEAR(E365) -> 2025
A366: 45818.944 | B366: amal.babu@visionplusindia.in | C366: 0 / 50 | D366: Amal | E366: 45936 | F366: Wireline | G366: 45818 | H366: 8281890550 | I366: 169 | J366: SBM963 | K366: Malayalam | L366: Kerala | M366: Yes | N366: Yes | O366: Yes | P366: Yes | Q366: Yes | R366: Yes | S366: Yes | T366: Yes | U366: Yes | V366: Yes | W366: Yes | X366: Yes | Y366: Yes | Z366: Yes | AA366: Yes | AB366: Yes | AC366: Yes | AD366: Yes | AE366: Yes | AF366: Yes | AG366: Yes | AH366: Not Applicable | AI366: Not Applicable | AJ366: Yes | AK366: Yes | AL366: Yes | AM366: Yes | AN366: Yes | AO366: Yes | AP366: Good Call | AQ366: The customer called and Inquiry about New connection details and plan details, agent checked and Information given Properly | AR366: Postpaid | AS366: LEAD - ENQUIRY ABOUT NEW FTTH OR LANDLINE CONNECTION | AT366: LEAD - ENQUIRY ABOUT NEW FTTH OR LANDLINE CONNECTION | AU366: Good Call | AW366: =IF(OR(M366="YES", M366="Not Applicable"), AW$1, "0") -> 6 | AX366: =IF(OR(N366="YES", N366="Not Applicable"), AX$1, "0") -> 4 | AY366: =IF(OR(O366="YES", O366="Not Applicable"), AY$1, "0") -> 4 | AZ366: =IF(OR(P366="YES", P366="Not Applicable"), AZ$1, "0") -> 2 | BA366: =IF(OR(Q366="YES", Q366="Not Applicable"), BA$1, "0") -> 4 | BB366: =IF(OR(R366="YES", R366="Not Applicable"), BB$1, "0") -> 4 | BC366: =IF(OR(S366="YES", S366="Not Applicable"), BC$1, "0") -> 4 | BD366: =IF(OR(T366="YES", T366="Not Applicable"), BD$1, "0") -> 2 | ... BY366: =IF(OR(AO366="YES", AO366="Not Applicable"), BY$1, "0") -> 0 | BZ366: =SUM(AW366:BY366) -> 100 | CA366: =VLOOKUP(J:J,'Agent wise'!A:C,3,0) -> Shakeer | CB366: =INT(E366) -> 45936 | CC366: =IF(BZ366>=94.5, "Excellent", IF(BZ366>89.5, "Good", IF(BZ366>84.5, "Average", "FC"))) -> Excellent | CJ366: =DAY(E366) -> 6 | CK366: =MONTH(E366) -> 10 | CL366: =YEAR(E366) -> 2025
A367: 45818.944 | B367: saranchirayinkeezhu720@gmail.com | C367: 0 / 50 | D367: Saran | E367: 45936 | F367: Wireless | G367: 45818 | H367: 9444554266 | I367: 152 | J367: SBM720 | K367: Tamil | L367: Tamil Nadu | M367: Yes | N367: Yes | O367: Yes | P367: Yes | Q367: Yes | R367: Yes | S367: Yes | T367: Yes | U367: No | V367: Yes | W367: Yes | X367: Yes | Y367: Yes | Z367: Yes | AA367: Yes | AB367: Yes | AC367: No | AD367: Yes | AE367: Yes | AF367: Not Applicable | AG367: Yes | AH367: Not Applicable | AI367: Not Applicable | AJ367: Yes | AK367: Yes | AL367: No | AM367: Yes | AN367: Yes | AO367: Yes | AP367: Dead air, No further assistance | AQ367: Customer concern -Customer called for not getting incoming calls . Resolution shared - Advisor done complete probing to customer as per call. | AR367: Prepaid | AS367: CALL SERVICES | AT367: UNABLE TO MAKE O/G AND I/C CALLS | AU367: Good Call | AW367: =IF(OR(M367="YES", M367="Not Applicable"), AW$1, "0") -> 6 | AX367: =IF(OR(N367="YES", N367="Not Applicable"), AX$1, "0") -> 4 | AY367: =IF(OR(O367="YES", O367="Not Applicable"), AY$1, "0") -> 4 | AZ367: =IF(OR(P367="YES", P367="Not Applicable"), AZ$1, "0") -> 2 | BA367: =IF(OR(Q367="YES", Q367="Not Applicable"), BA$1, "0") -> 4 | BB367: =IF(OR(R367="YES", R367="Not Applicable"), BB$1, "0") -> 4 | BC367: =IF(OR(S367="YES", S367="Not Applicable"), BC$1, "0") -> 4 | BD367: =IF(OR(T367="YES", T367="Not Applicable"), BD$1, "0") -> 2 | ... BY367: =IF(OR(AO367="YES", AO367="Not Applicable"), BY$1, "0") -> 0 | BZ367: =SUM(AW367:BY367) -> 92 | CA367: =VLOOKUP(J:J,'Agent wise'!A:C,3,0) -> Shiny | CB367: =INT(E367) -> 45936 | CC367: =IF(BZ367>=94.5, "Excellent", IF(BZ367>89.5, "Good", IF(BZ367>84.5, "Average", "FC"))) -> Good | CJ367: =DAY(E367) -> 6 | CK367: =MONTH(E367) -> 10 | CL367: =YEAR(E367) -> 2025
A368: 45818.947 | B368: amal.babu@visionplusindia.in | C368: 0 / 50 | D368: Amal | E368: 45936 | F368: Wireline | G368: 45818 | H368: 9786621199 | I368: 169 | J368: SBM678 | K368: Tamil | L368: Tamil Nadu | M368: Yes | N368: Yes | O368: Yes | P368: Yes | Q368: Yes | R368: Yes | S368: Yes | T368: Yes | U368: Yes | V368: Yes | W368: Yes | X368: Yes | Y368: Yes | Z368: Yes | AA368: Yes | AB368: Yes | AC368: Yes | AD368: Yes | AE368: Yes | AF368: Yes | AG368: Yes | AH368: Not Applicable | AI368: No | AJ368: Yes | AK368: Yes | AL368: No | AM368: Yes | AN368: Yes | AO368: Yes | AP368: Failed to Gave SR Number and Script adherence | AQ368: The customer called and Inquiry about internet not getting related Issue Agent checked and Booked a complaint | AR368: Postpaid | AS368: FAULT - NO INTERNET CONNECTIVITY | AT368: FAULT - NO INTERNET CONNECTIVITY | AU368: Good Call | AW368: =IF(OR(M368="YES", M368="Not Applicable"), AW$1, "0") -> 6 | AX368: =IF(OR(N368="YES", N368="Not Applicable"), AX$1, "0") -> 4 | AY368: =IF(OR(O368="YES", O368="Not Applicable"), AY$1, "0") -> 4 | AZ368: =IF(OR(P368="YES", P368="Not Applicable"), AZ$1, "0") -> 2 | BA368: =IF(OR(Q368="YES", Q368="Not Applicable"), BA$1, "0") -> 4 | BB368: =IF(OR(R368="YES", R368="Not Applicable"), BB$1, "0") -> 4 | BC368: =IF(OR(S368="YES", S368="Not Applicable"), BC$1, "0") -> 4 | BD368: =IF(OR(T368="YES", T368="Not Applicable"), BD$1, "0") -> 2 | ... BY368: =IF(OR(AO368="YES", AO368="Not Applicable"), BY$1, "0") -> 0 | BZ368: =SUM(AW368:BY368) -> 96 | CA368: =VLOOKUP(J:J,'Agent wise'!A:C,3,0) -> Adharsh | CB368: =INT(E368) -> 45936 | CC368: =IF(BZ368>=94.5, "Excellent", IF(BZ368>89.5, "Good", IF(BZ368>84.5, "Average", "FC"))) -> Excellent | CJ368: =DAY(E368) -> 6 | CK368: =MONTH(E368) -> 10 | CL368: =YEAR(E368) -> 2025
A369: 45818.947 | B369: saranchirayinkeezhu720@gmail.com | C369: 0 / 50 | D369: Saran | E369: 45936 | F369: Wireless | G369: 45818 | H369: 9655956117 | I369: 126 | J369: SBM901 | K369: Tamil | L369: Tamil Nadu | M369: Yes | N369: Yes | O369: Yes | P369: Yes | Q369: Yes | R369: Yes | S369: Yes | T369: Yes | U369: No | V369: Yes | W369: Yes | X369: Yes | Y369: Yes | Z369: Yes | AA369: No | AB369: Yes | AC369: Yes | AD369: Yes | AE369: Yes | AF369: Not Applicable | AG369: Yes | AH369: Not Applicable | AI369: Not Applicable | AJ369: Yes | AK369: Yes | AL369: No | AM369: Yes | AN369: Yes | AO369: Yes | AP369: No empathy. | AQ369: Customer concern -Customer called for unable to recharge. Resolution shared - Advisor done complete probing to customer as per call. | AR369: Prepaid | AS369: PLANS AND VALIDITY DETAILS | AT369: UNABLE TO RECHARGE | AU369: Good Call | AW369: =IF(OR(M369="YES", M369="Not Applicable"), AW$1, "0") -> 6 | AX369: =IF(OR(N369="YES", N369="Not Applicable"), AX$1, "0") -> 4 | AY369: =IF(OR(O369="YES", O369="Not Applicable"), AY$1, "0") -> 4 | AZ369: =IF(OR(P369="YES", P369="Not Applicable"), AZ$1, "0") -> 2 | BA369: =IF(OR(Q369="YES", Q369="Not Applicable"), BA$1, "0") -> 4 | BB369: =IF(OR(R369="YES", R369="Not Applicable"), BB$1, "0") -> 4 | BC369: =IF(OR(S369="YES", S369="Not Applicable"), BC$1, "0") -> 4 | BD369: =IF(OR(T369="YES", T369="Not Applicable"), BD$1, "0") -> 2 | ... BY369: =IF(OR(AO369="YES", AO369="Not Applicable"), BY$1, "0") -> 0 | BZ369: =SUM(AW369:BY369) -> 92 | CA369: =VLOOKUP(J:J,'Agent wise'!A:C,3,0) -> Shiny | CB369: =INT(E369) -> 45936 | CC369: =IF(BZ369>=94.5, "Excellent", IF(BZ369>89.5, "Good", IF(BZ369>84.5, "Average", "FC"))) -> Good | CJ369: =DAY(E369) -> 6 | CK369: =MONTH(E369) -> 10 | CL369: =YEAR(E369) -> 2025
A370: 45818.951 | B370: amal.babu@visionplusindia.in | C370: 0 / 50 | D370: Amal | E370: 45936 | F370: Wireline | G370: 45818 | H370: 6300632226 | I370: 138 | J370: SBM678 | K370: English | L370: Tamil Nadu | M370: Yes | N370: Yes | O370: Yes | P370: Yes | Q370: Yes | R370: Yes | S370: Yes | T370: Yes | U370: Yes | V370: Yes | W370: No | X370: Yes | Y370: Yes | Z370: Yes | AA370: No | AB370: No | AC370: Yes | AD370: Not Applicable | AE370: Yes | AF370: Yes | AG370: Yes | AH370: Not Applicable | AI370: Not Applicable | AJ370: Yes | AK370: Yes | AL370: Yes | AM370: Yes | AN370: Yes | AO370: Yes | AP370: Failed to use empathy and apology Retention too | AQ370: The customer called and Inquiry about Connection closing details agent checked and Information given Properly but Failed to ask Retention for the customer | AR370: Postpaid | AS370: SERVICE - REQUEST FOR SERVICE TERMINATION OR CLOSURE | AT370: SERVICE - REQUEST FOR SERVICE TERMINATION OR CLOSURE | AU370: Good Call | AW370: =IF(OR(M370="YES", M370="Not Applicable"), AW$1, "0") -> 6 | AX370: =IF(OR(N370="YES", N370="Not Applicable"), AX$1, "0") -> 4 | AY370: =IF(OR(O370="YES", O370="Not Applicable"), AY$1, "0") -> 4 | AZ370: =IF(OR(P370="YES", P370="Not Applicable"), AZ$1, "0") -> 2 | BA370: =IF(OR(Q370="YES", Q370="Not Applicable"), BA$1, "0") -> 4 | BB370: =IF(OR(R370="YES", R370="Not Applicable"), BB$1, "0") -> 4 | BC370: =IF(OR(S370="YES", S370="Not Applicable"), BC$1, "0") -> 4 | BD370: =IF(OR(T370="YES", T370="Not Applicable"), BD$1, "0") -> 2 | ... BY370: =IF(OR(AO370="YES", AO370="Not Applicable"), BY$1, "0") -> 0 | BZ370: =SUM(AW370:BY370) -> 90 | CA370: =VLOOKUP(J:J,'Agent wise'!A:C,3,0) -> Adharsh | CB370: =INT(E370) -> 45936 | CC370: =IF(BZ370>=94.5, "Excellent", IF(BZ370>89.5, "Good", IF(BZ370>84.5, "Average", "FC"))) -> Good | CJ370: =DAY(E370) -> 6 | CK370: =MONTH(E370) -> 10 | CL370: =YEAR(E370) -> 2025
A371: 45818.952 | B371: saranchirayinkeezhu720@gmail.com | C371: 0 / 50 | D371: Saran | E371: 45936 | F371: Wireless | G371: 45818 | H371: 9486789044 | I371: 166 | J371: VPS143 | K371: Tamil | L371: Tamil Nadu | M371: Yes | N371: Yes | O371: Yes | P371: Yes | Q371: Yes | R371: Yes | S371: Yes | T371: Yes | U371: No | V371: Yes | W371: Yes | X371: Yes | Y371: Yes | Z371: Yes | AA371: Yes | AB371: No | AC371: No | AD371: Yes | AE371: Yes | AF371: Not Applicable | AG371: Yes | AH371: Not Applicable | AI371: Yes | AJ371: Yes | AK371: Yes | AL371: No | AM371: Yes | AN371: Yes | AO371: Yes | AP371: Dead air, No apology. | AQ371: Customer concern -Customer called for network complaints . Resolution shared - Advisor done complete probing to customer as per call. | AR371: Prepaid | AS371: NETWORK | AT371: POOR NETWORK COVERAGE | AU371: Good Call | AW371: =IF(OR(M371="YES", M371="Not Applicable"), AW$1, "0") -> 6 | AX371: =IF(OR(N371="YES", N371="Not Applicable"), AX$1, "0") -> 4 | AY371: =IF(OR(O371="YES", O371="Not Applicable"), AY$1, "0") -> 4 | AZ371: =IF(OR(P371="YES", P371="Not Applicable"), AZ$1, "0") -> 2 | BA371: =IF(OR(Q371="YES", Q371="Not Applicable"), BA$1, "0") -> 4 | BB371: =IF(OR(R371="YES", R371="Not Applicable"), BB$1, "0") -> 4 | BC371: =IF(OR(S371="YES", S371="Not Applicable"), BC$1, "0") -> 4 | BD371: =IF(OR(T371="YES", T371="Not Applicable"), BD$1, "0") -> 2 | ... BY371: =IF(OR(AO371="YES", AO371="Not Applicable"), BY$1, "0") -> 0 | BZ371: =SUM(AW371:BY371) -> 90 | CA371: =VLOOKUP(J:J,'Agent wise'!A:C,3,0) -> Shiny | CB371: =INT(E371) -> 45936 | CC371: =IF(BZ371>=94.5, "Excellent", IF(BZ371>89.5, "Good", IF(BZ371>84.5, "Average", "FC"))) -> Good | CJ371: =DAY(E371) -> 6 | CK371: =MONTH(E371) -> 10 | CL371: =YEAR(E371) -> 2025
A372: 45818.955 | B372: saranchirayinkeezhu720@gmail.com | C372: 0 / 50 | D372: Saran | E372: 45936 | F372: Wireless | G372: 45818 | H372: 9443432456 | I372: 130 | J372: VPS230 | K372: Tamil | L372: Tamil Nadu | M372: Yes | N372: Yes | O372: Yes | P372: Yes | Q372: Yes | R372: Yes | S372: Yes | T372: Yes | U372: No | V372: Yes | W372: Yes | X372: Yes | Y372: Yes | Z372: Yes | AA372: No | AB372: Not Applicable | AC372: No | AD372: Yes | AE372: Yes | AF372: Not Applicable | AG372: Yes | AH372: Not Applicable | AI372: Not Applicable | AJ372: Yes | AK372: Yes | AL372: No | AM372: Yes | AN372: Yes | AO372: Yes | AP372: No empathy, Dead air, No further assistance | AQ372: Customer concern -Customer called for unable to recharge 107 pack details . Resolution shared - Advisor done complete probing to customer as per call. | AR372: Prepaid | AS372: PLANS AND VALIDITY DETAILS | AT372: ENQUIRY ON BALANCE AND VALIDITY | AU372: Good Call | AW372: =IF(OR(M372="YES", M372="Not Applicable"), AW$1, "0") -> 6 | AX372: =IF(OR(N372="YES", N372="Not Applicable"), AX$1, "0") -> 4 | AY372: =IF(OR(O372="YES", O372="Not Applicable"), AY$1, "0") -> 4 | AZ372: =IF(OR(P372="YES", P372="Not Applicable"), AZ$1, "0") -> 2 | BA372: =IF(OR(Q372="YES", Q372="Not Applicable"), BA$1, "0") -> 4 | BB372: =IF(OR(R372="YES", R372="Not Applicable"), BB$1, "0") -> 4 | BC372: =IF(OR(S372="YES", S372="Not Applicable"), BC$1, "0") -> 4 | BD372: =IF(OR(T372="YES", T372="Not Applicable"), BD$1, "0") -> 2 | ... BY372: =IF(OR(AO372="YES", AO372="Not Applicable"), BY$1, "0") -> 0 | BZ372: =SUM(AW372:BY372) -> 88 | CA372: =VLOOKUP(J:J,'Agent wise'!A:C,3,0) -> Shiny | CB372: =INT(E372) -> 45936 | CC372: =IF(BZ372>=94.5, "Excellent", IF(BZ372>89.5, "Good", IF(BZ372>84.5, "Average", "FC"))) -> Average | CJ372: =DAY(E372) -> 6 | CK372: =MONTH(E372) -> 10 | CL372: =YEAR(E372) -> 2025
... A381: 45848.493 | B381: priyankajino2013@gmail.com | C381: 0 / 50 | D381: Priyanka | E381: 45937 | F381: MNP OBD | G381: 45818 | H381: 8903637972 | I381: 130 | J381: VPS111 | K381: Tamil | L381: Tamil Nadu | M381: Yes | N381: Yes | O381: Yes | P381: Yes | Q381: Yes | R381: No | S381: Yes | T381: Yes | U381: No | V381: Yes | W381: Yes | X381: Yes | Y381: Yes | Z381: Yes | AA381: No | AB381: No | AC381: Yes | AD381: Yes | AE381: Yes | AF381: Yes | AG381: Yes | AH381: Yes | AI381: Not Applicable | AJ381: Yes | AK381: Yes | AL381: No | AM381: Yes | AN381: Yes | AO381: Yes | AP381: AOI-empathy missing,probing not done | AQ381: AOI-empathy missing,probing not done | AR381: Prepaid | AS381: COMPLETE CALL | AT381: NOT AGREED | AU381: Good Call | AW381: =IF(OR(M381="YES", M381="Not Applicable"), AW$1, "0") -> 6 | AX381: =IF(OR(N381="YES", N381="Not Applicable"), AX$1, "0") -> 4 | AY381: =IF(OR(O381="YES", O381="Not Applicable"), AY$1, "0") -> 4 | AZ381: =IF(OR(P381="YES", P381="Not Applicable"), AZ$1, "0") -> 2 | BA381: =IF(OR(Q381="YES", Q381="Not Applicable"), BA$1, "0") -> 4 | BB381: =IF(OR(R381="YES", R381="Not Applicable"), BB$1, "0") -> 0 | BC381: =IF(OR(S381="YES", S381="Not Applicable"), BC$1, "0") -> 4 | BD381: =IF(OR(T381="YES", T381="Not Applicable"), BD$1, "0") -> 2 | ... BY381: =IF(OR(AO381="YES", AO381="Not Applicable"), BY$1, "0") -> 0 | BZ381: =SUM(AW381:BY381) -> 86 | CA381: =VLOOKUP(J:J,'Agent wise'!A:C,3,0) -> Shiny | CB381: =INT(E381) -> 45937 | CC381: =IF(BZ381>=94.5, "Excellent", IF(BZ381>89.5, "Good", IF(BZ381>84.5, "Average", "FC"))) -> Average | CJ381: =DAY(E381) -> 7 | CK381: =MONTH(E381) -> 10 | CL381: =YEAR(E381) -> 2025
A382: 45848.497 | B382: nehafire4444@gmail.com | C382: 0 / 50 | D382: Sneha | E382: 45937 | F382: Wireless | G382: 45818 | H382: 9488403397 | I382: 222 | J382: 7639942386 | K382: Tamil | L382: Tamil Nadu | M382: Yes | N382: Yes | O382: Yes | P382: Yes | Q382: Yes | R382: Yes | S382: Yes | T382: Yes | U382: No | V382: Yes | W382: Yes | X382: Yes | Y382: Yes | Z382: Yes | AA382: Yes | AB382: Yes | AC382: Not Applicable | AD382: Yes | AE382: Yes | AF382: Yes | AG382: Yes | AH382: Not Applicable | AI382: Not Applicable | AJ382: Yes | AK382: Yes | AL382: Yes | AM382: No | AN382: No | AO382: No | AP382: Tagging not done | AQ382: The customer called for data no connected regarding issue, The advisor check and given proper information . | AR382: Prepaid | AS382: DATA SERVICES | AT382: UNABLE TO BROWSE DATA | AU382: Good Call | AW382: =IF(OR(M382="YES", M382="Not Applicable"), AW$1, "0") -> 6 | AX382: =IF(OR(N382="YES", N382="Not Applicable"), AX$1, "0") -> 4 | AY382: =IF(OR(O382="YES", O382="Not Applicable"), AY$1, "0") -> 4 | AZ382: =IF(OR(P382="YES", P382="Not Applicable"), AZ$1, "0") -> 2 | BA382: =IF(OR(Q382="YES", Q382="Not Applicable"), BA$1, "0") -> 4 | BB382: =IF(OR(R382="YES", R382="Not Applicable"), BB$1, "0") -> 4 | BC382: =IF(OR(S382="YES", S382="Not Applicable"), BC$1, "0") -> 4 | BD382: =IF(OR(T382="YES", T382="Not Applicable"), BD$1, "0") -> 2 | ... BY382: =IF(OR(AO382="YES", AO382="Not Applicable"), BY$1, "0") -> 0 | BZ382: =SUM(AW382:BY382) -> 90 | CA382: =VLOOKUP(J:J,'Agent wise'!A:C,3,0) -> #N/A | CB382: =INT(E382) -> 45937 | CC382: =IF(BZ382>=94.5, "Excellent", IF(BZ382>89.5, "Good", IF(BZ382>84.5, "Average", "FC"))) -> Good | CJ382: =DAY(E382) -> 7 | CK382: =MONTH(E382) -> 10 | CL382: =YEAR(E382) -> 2025
A383: 45848.504 | B383: priyankajino2013@gmail.com | C383: 0 / 50 | D383: Priyanka | E383: 45937 | F383: MNP OBD | G383: 45818 | H383: 9787280957 | I383: 168 | J383: SBM958 | K383: Tamil | L383: Tamil Nadu | M383: Yes | N383: Yes | O383: No | P383: Yes | Q383: Yes | R383: No | S383: Yes | T383: Yes | U383: Yes | V383: Yes | W383: Yes | X383: Yes | Y383: Yes | Z383: Yes | AA383: No | AB383: No | AC383: Yes | AD383: Yes | AE383: No | AF383: Yes | AG383: Yes | AH383: Yes | AI383: Not Applicable | AJ383: Yes | AK383: Yes | AL383: No | AM383: Yes | AN383: Yes | AO383: No | AP383: AOI-empathy missing,probing not done,tagging not done | AQ383: AOI-empathy missing,probing not done,tagging not done | AR383: Prepaid | AS383: COMPLETE CALL | AT383: NOT AGREED | AU383: Good Call | AW383: =IF(OR(M383="YES", M383="Not Applicable"), AW$1, "0") -> 6 | AX383: =IF(OR(N383="YES", N383="Not Applicable"), AX$1, "0") -> 4 | AY383: =IF(OR(O383="YES", O383="Not Applicable"), AY$1, "0") -> 0 | AZ383: =IF(OR(P383="YES", P383="Not Applicable"), AZ$1, "0") -> 2 | BA383: =IF(OR(Q383="YES", Q383="Not Applicable"), BA$1, "0") -> 4 | BB383: =IF(OR(R383="YES", R383="Not Applicable"), BB$1, "0") -> 0 | BC383: =IF(OR(S383="YES", S383="Not Applicable"), BC$1, "0") -> 4 | BD383: =IF(OR(T383="YES", T383="Not Applicable"), BD$1, "0") -> 2 | ... BY383: =IF(OR(AO383="YES", AO383="Not Applicable"), BY$1, "0") -> 0 | BZ383: =SUM(AW383:BY383) -> 82 | CA383: =VLOOKUP(J:J,'Agent wise'!A:C,3,0) -> Saran S | CB383: =INT(E383) -> 45937 | CC383: =IF(BZ383>=94.5, "Excellent", IF(BZ383>89.5, "Good", IF(BZ383>84.5, "Average", "FC"))) -> FC | CJ383: =DAY(E383) -> 7 | CK383: =MONTH(E383) -> 10 | CL383: =YEAR(E383) -> 2025
A384: 45848.513 | B384: amal.babu@visionplusindia.in | C384: 0 / 50 | D384: Amal | E384: 45937 | F384: Wireline | G384: 45848 | H384: 9633724963 | I384: 140 | J384: VPS181 | K384: Malayalam | L384: Kerala | M384: Yes | N384: Yes | O384: No | P384: Yes | Q384: Yes | R384: Yes | S384: Yes | T384: Yes | U384: Yes | V384: Yes | W384: Yes | X384: Yes | Y384: Yes | Z384: Yes | AA384: Yes | AB384: Not Applicable | AC384: Yes | AD384: Not Applicable | AE384: Yes | AF384: Yes | AG384: Yes | AH384: Not Applicable | AI384: Not Applicable | AJ384: Yes | AK384: Yes | AL384: No | AM384: Yes | AN384: Yes | AO384: Yes | AP384: Failed to ask customer Name and Script adherence | AQ384: The customer called and Inquiry about New connection details, agent checked and Information given Properly | AR384: Postpaid | AS384: LEAD - ENQUIRY ABOUT NEW FTTH OR LANDLINE CONNECTION | AT384: LEAD - ENQUIRY ABOUT NEW FTTH OR LANDLINE CONNECTION | AU384: Good Call | AW384: =IF(OR(M384="YES", M384="Not Applicable"), AW$1, "0") -> 6 | AX384: =IF(OR(N384="YES", N384="Not Applicable"), AX$1, "0") -> 4 | AY384: =IF(OR(O384="YES", O384="Not Applicable"), AY$1, "0") -> 0 | AZ384: =IF(OR(P384="YES", P384="Not Applicable"), AZ$1, "0") -> 2 | BA384: =IF(OR(Q384="YES", Q384="Not Applicable"), BA$1, "0") -> 4 | BB384: =IF(OR(R384="YES", R384="Not Applicable"), BB$1, "0") -> 4 | BC384: =IF(OR(S384="YES", S384="Not Applicable"), BC$1, "0") -> 4 | BD384: =IF(OR(T384="YES", T384="Not Applicable"), BD$1, "0") -> 2 | ... BY384: =IF(OR(AO384="YES", AO384="Not Applicable"), BY$1, "0") -> 0 | BZ384: =SUM(AW384:BY384) -> 96 | CA384: =VLOOKUP(J:J,'Agent wise'!A:C,3,0) -> Amal | CB384: =INT(E384) -> 45937 | CC384: =IF(BZ384>=94.5, "Excellent", IF(BZ384>89.5, "Good", IF(BZ384>84.5, "Average", "FC"))) -> Excellent | CJ384: =DAY(E384) -> 7 | CK384: =MONTH(E384) -> 10 | CL384: =YEAR(E384) -> 2025
A385: 45848.516 | B385: nehafire4444@gmail.com | C385: 0 / 50 | D385: Sneha | E385: 45937 | F385: Wireless | G385: 45818 | H385: 8129243739 | I385: 251 | J385: VPS261 | K385: Malayalam | L385: Kerala | M385: Yes | N385: Yes | O385: Yes | P385: Yes | Q385: Yes | R385: Yes | S385: Yes | T385: Yes | U385: No | V385: Yes | W385: Yes | X385: Yes | Y385: Yes | Z385: Yes | AA385: No | AB385: Yes | AC385: Yes | AD385: Yes | AE385: Yes | AF385: Yes | AG385: No | AH385: Not Applicable | AI385: Not Applicable | AJ385: Yes | AK385: Yes | AL385: No | AM385: No | AN385: No | AO385: No | AP385: lack of listening skill, Complaint booked in wrongly | AQ385: The customer called for incoming call connectivity issue, The advisor wrongly taken complaint on the calling number (MSISDN:9400371621 ) | AR385: Prepaid | AS385: NETWORK | AT385: NO SIGNAL | AU385: Casual Talk | AW385: =IF(OR(M385="YES", M385="Not Applicable"), AW$1, "0") -> 6 | AX385: =IF(OR(N385="YES", N385="Not Applicable"), AX$1, "0") -> 4 | AY385: =IF(OR(O385="YES", O385="Not Applicable"), AY$1, "0") -> 4 | AZ385: =IF(OR(P385="YES", P385="Not Applicable"), AZ$1, "0") -> 2 | BA385: =IF(OR(Q385="YES", Q385="Not Applicable"), BA$1, "0") -> 4 | BB385: =IF(OR(R385="YES", R385="Not Applicable"), BB$1, "0") -> 4 | BC385: =IF(OR(S385="YES", S385="Not Applicable"), BC$1, "0") -> 4 | BD385: =IF(OR(T385="YES", T385="Not Applicable"), BD$1, "0") -> 2 | ... BY385: =IF(OR(AO385="YES", AO385="Not Applicable"), BY$1, "0") -> 0 | BZ385: =SUM(AW385:BY385) -> 80 | CA385: =VLOOKUP(J:J,'Agent wise'!A:C,3,0) -> Anusha | CB385: =INT(E385) -> 45937 | CC385: =IF(BZ385>=94.5, "Excellent", IF(BZ385>89.5, "Good", IF(BZ385>84.5, "Average", "FC"))) -> FC | CJ385: =DAY(E385) -> 7 | CK385: =MONTH(E385) -> 10 | CL385: =YEAR(E385) -> 2025
A386: 45848.518 | B386: amal.babu@visionplusindia.in | C386: 0 / 50 | D386: Amal | E386: 45937 | F386: Wireline | G386: 45848 | H386: 9567521388 | I386: 135 | J386: SBM554 | K386: Malayalam | L386: Kerala | M386: Yes | N386: Yes | O386: No | P386: Yes | Q386: Yes | R386: Yes | S386: Yes | T386: Yes | U386: Yes | V386: Yes | W386: Yes | X386: Yes | Y386: Yes | Z386: Yes | AA386: Yes | AB386: Yes | AC386: Yes | AD386: Yes | AE386: Yes | AF386: Yes | AG386: Yes | AH386: Not Applicable | AI386: Not Applicable | AJ386: Yes | AK386: Yes | AL386: No | AM386: Yes | AN386: Yes | AO386: Yes | AP386: Failed to ask caller name and Script adherence | AQ386: The customer called and Inquiry about Internet not getting related Issue,agent checked and Information given Properly | AR386: Postpaid | AS386: FAULT - NO INTERNET CONNECTIVITY | AT386: FAULT - NO INTERNET CONNECTIVITY | AU386: Good Call | AW386: =IF(OR(M386="YES", M386="Not Applicable"), AW$1, "0") -> 6 | AX386: =IF(OR(N386="YES", N386="Not Applicable"), AX$1, "0") -> 4 | AY386: =IF(OR(O386="YES", O386="Not Applicable"), AY$1, "0") -> 0 | AZ386: =IF(OR(P386="YES", P386="Not Applicable"), AZ$1, "0") -> 2 | BA386: =IF(OR(Q386="YES", Q386="Not Applicable"), BA$1, "0") -> 4 | BB386: =IF(OR(R386="YES", R386="Not Applicable"), BB$1, "0") -> 4 | BC386: =IF(OR(S386="YES", S386="Not Applicable"), BC$1, "0") -> 4 | BD386: =IF(OR(T386="YES", T386="Not Applicable"), BD$1, "0") -> 2 | ... BY386: =IF(OR(AO386="YES", AO386="Not Applicable"), BY$1, "0") -> 0 | BZ386: =SUM(AW386:BY386) -> 96 | CA386: =VLOOKUP(J:J,'Agent wise'!A:C,3,0) -> Adharsh | CB386: =INT(E386) -> 45937 | CC386: =IF(BZ386>=94.5, "Excellent", IF(BZ386>89.5, "Good", IF(BZ386>84.5, "Average", "FC"))) -> Excellent | CJ386: =DAY(E386) -> 7 | CK386: =MONTH(E386) -> 10 | CL386: =YEAR(E386) -> 2025
A387: 45848.522 | B387: nehafire4444@gmail.com | C387: 0 / 50 | D387: Sneha | E387: 45937 | F387: Wireless | G387: 45818 | H387: 9567786584 | I387: 186 | J387: VPS261 | K387: Malayalam | L387: Kerala | M387: Yes | N387: Yes | O387: Yes | P387: Yes | Q387: Yes | R387: Yes | S387: Yes | T387: Yes | U387: No | V387: Yes | W387: Yes | X387: Yes | Y387: Yes | Z387: Yes | AA387: No | AB387: Yes | AC387: Yes | AD387: Yes | AE387: Yes | AF387: Yes | AG387: Yes | AH387: Not Applicable | AI387: Not Applicable | AJ387: Yes | AK387: Yes | AL387: Yes | AM387: Yes | AN387: Yes | AO387: Yes | AP387: Fumbling observed, Lack of confidence | AQ387: The customer called for sim activating and need to know about the sim status regarding details, The advisor check and informed sim has blocked contact nearby csc. | AR387: Postpaid | AS387: PLANS AND VALIDITY DETAILS | AT387: ENQUIRY ON PREPAID PLANS | AU387: Good Call | AW387: =IF(OR(M387="YES", M387="Not Applicable"), AW$1, "0") -> 6 | AX387: =IF(OR(N387="YES", N387="Not Applicable"), AX$1, "0") -> 4 | AY387: =IF(OR(O387="YES", O387="Not Applicable"), AY$1, "0") -> 4 | AZ387: =IF(OR(P387="YES", P387="Not Applicable"), AZ$1, "0") -> 2 | BA387: =IF(OR(Q387="YES", Q387="Not Applicable"), BA$1, "0") -> 4 | BB387: =IF(OR(R387="YES", R387="Not Applicable"), BB$1, "0") -> 4 | BC387: =IF(OR(S387="YES", S387="Not Applicable"), BC$1, "0") -> 4 | BD387: =IF(OR(T387="YES", T387="Not Applicable"), BD$1, "0") -> 2 | ... BY387: =IF(OR(AO387="YES", AO387="Not Applicable"), BY$1, "0") -> 0 | BZ387: =SUM(AW387:BY387) -> 92 | CA387: =VLOOKUP(J:J,'Agent wise'!A:C,3,0) -> Anusha | CB387: =INT(E387) -> 45937 | CC387: =IF(BZ387>=94.5, "Excellent", IF(BZ387>89.5, "Good", IF(BZ387>84.5, "Average", "FC"))) -> Good | CJ387: =DAY(E387) -> 7 | CK387: =MONTH(E387) -> 10 | CL387: =YEAR(E387) -> 2025
...

Sheet Agent wise
A1: Login _ ID | B1: Agent Name | C1: TL | D1: Gender | E1: Process | F1: DOJ | G1: Call | H1: QA Score | I1: Tagging YES | J1: Tagging No | K1: Tagging Accuracy
A2: SBM107 | B2: Sudhi S R | C2: Shakeer | D2: Female | E2: Wire-line | F2: 44691 | G2: =COUNTIFS('Audit Raw data'!J:J,A:A) -> 10 | H2: =IFERROR(SUMIFS('Audit Raw data'!BZ:BZ,'Audit Raw data'!J:J,A:A)/G2,"") -> 96.4 | I2: =COUNTIFS('Audit Raw data'!AM:AM,"Yes",'Audit Raw data'!J:J,A:A) -> 10 | J2: =G2-I2 -> 0 | K2: =IFERROR(I2/G2," ") -> 1
A3: SBM150 | B3: Nikitha G | C3: Saran S | D3: Female | E3: Wireless | F3: 44707 | G3: =COUNTIFS('Audit Raw data'!J:J,A:A) -> 13 | H3: =IFERROR(SUMIFS('Audit Raw data'!BZ:BZ,'Audit Raw data'!J:J,A:A)/G3,"") -> 92.615385 | I3: =COUNTIFS('Audit Raw data'!AM:AM,"Yes",'Audit Raw data'!J:J,A:A) -> 12 | J3: =G3-I3 -> 1 | K3: =IFERROR(I3/G3," ") -> 0.92307692
A4: SBM155 | B4: Anuja J | C4: Sowmya | D4: Female | E4: RECL | F4: 44707 | G4: =COUNTIFS('Audit Raw data'!J:J,A:A) -> 0 | H4: =IFERROR(SUMIFS('Audit Raw data'!BZ:BZ,'Audit Raw data'!J:J,A:A)/G4,"") | I4: =COUNTIFS('Audit Raw data'!AM:AM,"Yes",'Audit Raw data'!J:J,A:A) -> 0 | J4: =G4-I4 -> 0 | K4: =IFERROR(I4/G4," ")
A5: SBM157 | B5: Abitha Sureshkumar | C5: Saran S | D5: Female | E5: Wireless | F5: 44713 | G5: =COUNTIFS('Audit Raw data'!J:J,A:A) -> 8 | H5: =IFERROR(SUMIFS('Audit Raw data'!BZ:BZ,'Audit Raw data'!J:J,A:A)/G5,"") -> 96 | I5: =COUNTIFS('Audit Raw data'!AM:AM,"Yes",'Audit Raw data'!J:J,A:A) -> 8 | J5: =G5-I5 -> 0 | K5: =IFERROR(I5/G5," ") -> 1
A6: SBM202 | B6: Selvaraj Nesamani | C6: Adharsh | D6: Male | E6: Wireless | F6: 44721 | G6: =COUNTIFS('Audit Raw data'!J:J,A:A) -> 15 | H6: =IFERROR(SUMIFS('Audit Raw data'!BZ:BZ,'Audit Raw data'!J:J,A:A)/G6,"") -> 92.933333 | I6: =COUNTIFS('Audit Raw data'!AM:AM,"Yes",'Audit Raw data'!J:J,A:A) -> 15 | J6: =G6-I6 -> 0 | K6: =IFERROR(I6/G6," ") -> 1
A7: SBM264 | B7: Vijin V | C7: Shakeer | D7: Male | E7: Wireless | F7: 44739 | G7: =COUNTIFS('Audit Raw data'!J:J,A:A) -> 16 | H7: =IFERROR(SUMIFS('Audit Raw data'!BZ:BZ,'Audit Raw data'!J:J,A:A)/G7,"") -> 91.375 | I7: =COUNTIFS('Audit Raw data'!AM:AM,"Yes",'Audit Raw data'!J:J,A:A) -> 16 | J7: =G7-I7 -> 0 | K7: =IFERROR(I7/G7," ") -> 1
A8: SBM267 | B8: Kumar Arul Raj | C8: Saran S | D8: Male | E8: Wireless | F8: 44768 | G8: =COUNTIFS('Audit Raw data'!J:J,A:A) -> 22 | H8: =IFERROR(SUMIFS('Audit Raw data'!BZ:BZ,'Audit Raw data'!J:J,A:A)/G8,"") -> 89.181818 | I8: =COUNTIFS('Audit Raw data'!AM:AM,"Yes",'Audit Raw data'!J:J,A:A) -> 22 | J8: =G8-I8 -> 0 | K8: =IFERROR(I8/G8," ") -> 1
A9: SBM314 | B9: Abisha J K | C9: Shakeer | D9: Female | E9: Wireless | F9: 44784 | G9: =COUNTIFS('Audit Raw data'!J:J,A:A) -> 13 | H9: =IFERROR(SUMIFS('Audit Raw data'!BZ:BZ,'Audit Raw data'!J:J,A:A)/G9,"") -> 96 | I9: =COUNTIFS('Audit Raw data'!AM:AM,"Yes",'Audit Raw data'!J:J,A:A) -> 13 | J9: =G9-I9 -> 0 | K9: =IFERROR(I9/G9," ") -> 1
A10: SBM363 | B10: Suresh Ayyappan | C10: Saran S | D10: Male | E10: Wireless | F10: 44786 | G10: =COUNTIFS('Audit Raw data'!J:J,A:A) -> 10 | H10: =IFERROR(SUMIFS('Audit Raw data'!BZ:BZ,'Audit Raw data'!J:J,A:A)/G10,"") -> 91.6 | I10: =COUNTIFS('Audit Raw data'!AM:AM,"Yes",'Audit Raw data'!J:J,A:A) -> 10 | J10: =G10-I10 -> 0 | K10: =IFERROR(I10/G10," ") -> 1
A11: SBM373 | B11: Rejisha Beautlin R | C11: Saran S | D11: Female | E11: Wireless | F11: 44786 | G11: =COUNTIFS('Audit Raw data'!J:J,A:A) -> 12 | H11: =IFERROR(SUMIFS('Audit Raw data'!BZ:BZ,'Audit Raw data'!J:J,A:A)/G11,"") -> 91 | I11: =COUNTIFS('Audit Raw data'!AM:AM,"Yes",'Audit Raw data'!J:J,A:A) -> 11 | J11: =G11-I11 -> 1 | K11: =IFERROR(I11/G11," ") -> 0.91666667
A12: SBM422 | B12: Abdulkalam Nisja Mudeen | C12: Shakeer | D12: Male | E12: Wireless | F12: 44882 | G12: =COUNTIFS('Audit Raw data'!J:J,A:A) -> 12 | H12: =IFERROR(SUMIFS('Audit Raw data'!BZ:BZ,'Audit Raw data'!J:J,A:A)/G12,"") -> 89.666667 | I12: =COUNTIFS('Audit Raw data'!AM:AM,"Yes",'Audit Raw data'!J:J,A:A) -> 12 | J12: =G12-I12 -> 0 | K12: =IFERROR(I12/G12," ") -> 1
A13: SBM481 | B13: Mary L | C13: Adharsh | D13: Female | E13: Wireless | F13: 44932 | G13: =COUNTIFS('Audit Raw data'!J:J,A:A) -> 12 | H13: =IFERROR(SUMIFS('Audit Raw data'!BZ:BZ,'Audit Raw data'!J:J,A:A)/G13,"") -> 92.5 | I13: =COUNTIFS('Audit Raw data'!AM:AM,"Yes",'Audit Raw data'!J:J,A:A) -> 12 | J13: =G13-I13 -> 0 | K13: =IFERROR(I13/G13," ") -> 1
... A111: VPS264 | B111: Akil K S | C111: Anusha | D111: Male | E111: Wireless | F111: 45938 | G111: =COUNTIFS('Audit Raw data'!J:J,A:A) -> 7 | H111: =IFERROR(SUMIFS('Audit Raw data'!BZ:BZ,'Audit Raw data'!J:J,A:A)/G111,"") -> 80.857143 | I111: =COUNTIFS('Audit Raw data'!AM:AM,"Yes",'Audit Raw data'!J:J,A:A) -> 6 | J111: =G111-I111 -> 1 | K111: =IFERROR(I111/G111," ") -> 0.85714286

Sheet Day wise agent
B1: EMP_ ID | C1: NAME | D1: DOJ | E1: TL | F1: Process | G1: Date | H1: Call | I1: QA Score | J1: Tagging YES | K1: Tagging No | L1: Tagging Accuracy
A2: =B2&G2 -> SBM10745931 | B2: SBM107 | C2: Sudhi S R | D2: 44691 | E2: Shakeer | F2: =VLOOKUP(B2,'Agent wise'!A:E,5,0) -> Wire-line | G2: 45931 | H2: =COUNTIFS('Audit Raw data'!J:J,B:B,'Audit Raw data'!E:E,G:G) -> 0 | I2: =IFERROR((SUMIFS('Audit Raw data'!BZ:BZ,'Audit Raw data'!J:J,B:B,'Audit Raw data'!E:E,G:G)/H2)/100,"-") -> - | J2: =COUNTIFS('Audit Raw data'!AM:AM,"Yes",'Audit Raw data'!J:J,B:B,'Audit Raw data'!E:E,'Day wise agent'!G:G) -> 0 | K2: =COUNTIFS('Audit Raw data'!AM:AM,"NO",'Audit Raw data'!J:J,B:B,'Audit Raw data'!E:E,'Day wise agent'!G:G) -> 0 | L2: =IFERROR(J2/H2," ")
A3: =B3&G3 -> SBM15045931 | B3: SBM150 | C3: Nikitha G | D3: 44707 | E3: Saran S | F3: =VLOOKUP(B3,'Agent wise'!A:E,5,0) -> Wireless | G3: 45931 | H3: =COUNTIFS('Audit Raw data'!J:J,B:B,'Audit Raw data'!E:E,G:G) -> 1 | I3: =IFERROR((SUMIFS('Audit Raw data'!BZ:BZ,'Audit Raw data'!J:J,B:B,'Audit Raw data'!E:E,G:G)/H3)/100,"-") -> 0.86 | J3: =COUNTIFS('Audit Raw data'!AM:AM,"Yes",'Audit Raw data'!J:J,B:B,'Audit Raw data'!E:E,'Day wise agent'!G:G) -> 0 | K3: =COUNTIFS('Audit Raw data'!AM:AM,"NO",'Audit Raw data'!J:J,B:B,'Audit Raw data'!E:E,'Day wise agent'!G:G) -> 1 | L3: =IFERROR(J3/H3," ") -> 0
A4: =B4&G4 -> SBM15545931 | B4: SBM155 | C4: Anuja J | D4: 44707 | E4: Sowmya | F4: =VLOOKUP(B4,'Agent wise'!A:E,5,0) -> RECL | G4: 45931 | H4: =COUNTIFS('Audit Raw data'!J:J,B:B,'Audit Raw data'!E:E,G:G) -> 0 | I4: =IFERROR((SUMIFS('Audit Raw data'!BZ:BZ,'Audit Raw data'!J:J,B:B,'Audit Raw data'!E:E,G:G)/H4)/100,"-") -> - | J4: =COUNTIFS('Audit Raw data'!AM:AM,"Yes",'Audit Raw data'!J:J,B:B,'Audit Raw data'!E:E,'Day wise agent'!G:G) -> 0 | K4: =COUNTIFS('Audit Raw data'!AM:AM,"NO",'Audit Raw data'!J:J,B:B,'Audit Raw data'!E:E,'Day wise agent'!G:G) -> 0 | L4: =IFERROR(J4/H4," ")
A5: =B5&G5 -> SBM15745931 | B5: SBM157 | C5: Abitha Sureshkumar | D5: 44713 | E5: Saran S | F5: =VLOOKUP(B5,'Agent wise'!A:E,5,0) -> Wireless | G5: 45931 | H5: =COUNTIFS('Audit Raw data'!J:J,B:B,'Audit Raw data'!E:E,G:G) -> 1 | I5: =IFERROR((SUMIFS('Audit Raw data'!BZ:BZ,'Audit Raw data'!J:J,B:B,'Audit Raw data'!E:E,G:G)/H5)/100,"-") -> 0.92 | J5: =COUNTIFS('Audit Raw data'!AM:AM,"Yes",'Audit Raw data'!J:J,B:B,'Audit Raw data'!E:E,'Day wise agent'!G:G) -> 1 | K5: =COUNTIFS('Audit Raw data'!AM:AM,"NO",'Audit Raw data'!J:J,B:B,'Audit Raw data'!E:E,'Day wise agent'!G:G) -> 0 | L5: =IFERROR(J5/H5," ") -> 1
A6: =B6&G6 -> SBM20245931 | B6: SBM202 | C6: Selvaraj Nesamani | D6: 44721 | E6: Adharsh | F6: =VLOOKUP(B6,'Agent wise'!A:E,5,0) -> Wireless | G6: 45931 | H6: =COUNTIFS('Audit Raw data'!J:J,B:B,'Audit Raw data'!E:E,G:G) -> 0 | I6: =IFERROR((SUMIFS('Audit Raw data'!BZ:BZ,'Audit Raw data'!J:J,B:B,'Audit Raw data'!E:E,G:G)/H6)/100,"-") -> - | J6: =COUNTIFS('Audit Raw data'!AM:AM,"Yes",'Audit Raw data'!J:J,B:B,'Audit Raw data'!E:E,'Day wise agent'!G:G) -> 0 | K6: =COUNTIFS('Audit Raw data'!AM:AM,"NO",'Audit Raw data'!J:J,B:B,'Audit Raw data'!E:E,'Day wise agent'!G:G) -> 0 | L6: =IFERROR(J6/H6," ")
A7: =B7&G7 -> SBM26445931 | B7: SBM264 | C7: Vijin V | D7: 44739 | E7: Shakeer | F7: =VLOOKUP(B7,'Agent wise'!A:E,5,0) -> Wireless | G7: 45931 | H7: =COUNTIFS('Audit Raw data'!J:J,B:B,'Audit Raw data'!E:E,G:G) -> 0 | I7: =IFERROR((SUMIFS('Audit Raw data'!BZ:BZ,'Audit Raw data'!J:J,B:B,'Audit Raw data'!E:E,G:G)/H7)/100,"-") -> - | J7: =COUNTIFS('Audit Raw data'!AM:AM,"Yes",'Audit Raw data'!J:J,B:B,'Audit Raw data'!E:E,'Day wise agent'!G:G) -> 0 | K7: =COUNTIFS('Audit Raw data'!AM:AM,"NO",'Audit Raw data'!J:J,B:B,'Audit Raw data'!E:E,'Day wise agent'!G:G) -> 0 | L7: =IFERROR(J7/H7," ")
A8: =B8&G8 -> SBM26745931 | B8: SBM267 | C8: Kumar Arul Raj | D8: 44768 | E8: Saran S | F8: =VLOOKUP(B8,'Agent wise'!A:E,5,0) -> Wireless | G8: 45931 | H8: =COUNTIFS('Audit Raw data'!J:J,B:B,'Audit Raw data'!E:E,G:G) -> 1 | I8: =IFERROR((SUMIFS('Audit Raw data'!BZ:BZ,'Audit Raw data'!J:J,B:B,'Audit Raw data'!E:E,G:G)/H8)/100,"-") -> 0.9 | J8: =COUNTIFS('Audit Raw data'!AM:AM,"Yes",'Audit Raw data'!J:J,B:B,'Audit Raw data'!E:E,'Day wise agent'!G:G) -> 1 | K8: =COUNTIFS('Audit Raw data'!AM:AM,"NO",'Audit Raw data'!J:J,B:B,'Audit Raw data'!E:E,'Day wise agent'!G:G) -> 0 | L8: =IFERROR(J8/H8," ") -> 1
A9: =B9&G9 -> SBM31445931 | B9: SBM314 | C9: Abisha J K | D9: 44784 | E9: Shakeer | F9: =VLOOKUP(B9,'Agent wise'!A:E,5,0) -> Wireless | G9: 45931 | H9: =COUNTIFS('Audit Raw data'!J:J,B:B,'Audit Raw data'!E:E,G:G) -> 1 | I9: =IFERROR((SUMIFS('Audit Raw data'!BZ:BZ,'Audit Raw data'!J:J,B:B,'Audit Raw data'!E:E,G:G)/H9)/100,"-") -> 0.84 | J9: =COUNTIFS('Audit Raw data'!AM:AM,"Yes",'Audit Raw data'!J:J,B:B,'Audit Raw data'!E:E,'Day wise agent'!G:G) -> 1 | K9: =COUNTIFS('Audit Raw data'!AM:AM,"NO",'Audit Raw data'!J:J,B:B,'Audit Raw data'!E:E,'Day wise agent'!G:G) -> 0 | L9: =IFERROR(J9/H9," ") -> 1
A10: =B10&G10 -> SBM36345931 | B10: SBM363 | C10: Suresh Ayyappan | D10: 44786 | E10: Saran S | F10: =VLOOKUP(B10,'Agent wise'!A:E,5,0) -> Wireless | G10: 45931 | H10: =COUNTIFS('Audit Raw data'!J:J,B:B,'Audit Raw data'!E:E,G:G) -> 1 | I10: =IFERROR((SUMIFS('Audit Raw data'!BZ:BZ,'Audit Raw data'!J:J,B:B,'Audit Raw data'!E:E,G:G)/H10)/100,"-") -> 0.8 | J10: =COUNTIFS('Audit Raw data'!AM:AM,"Yes",'Audit Raw data'!J:J,B:B,'Audit Raw data'!E:E,'Day wise agent'!G:G) -> 1 | K10: =COUNTIFS('Audit Raw data'!AM:AM,"NO",'Audit Raw data'!J:J,B:B,'Audit Raw data'!E:E,'Day wise agent'!G:G) -> 0 | L10: =IFERROR(J10/H10," ") -> 1
A11: =B11&G11 -> SBM37345931 | B11: SBM373 | C11: Rejisha Beautlin R | D11: 44786 | E11: Saran S | F11: =VLOOKUP(B11,'Agent wise'!A:E,5,0) -> Wireless | G11: 45931 | H11: =COUNTIFS('Audit Raw data'!J:J,B:B,'Audit Raw data'!E:E,G:G) -> 1 | I11: =IFERROR((SUMIFS('Audit Raw data'!BZ:BZ,'Audit Raw data'!J:J,B:B,'Audit Raw data'!E:E,G:G)/H11)/100,"-") -> 0.88 | J11: =COUNTIFS('Audit Raw data'!AM:AM,"Yes",'Audit Raw data'!J:J,B:B,'Audit Raw data'!E:E,'Day wise agent'!G:G) -> 1 | K11: =COUNTIFS('Audit Raw data'!AM:AM,"NO",'Audit Raw data'!J:J,B:B,'Audit Raw data'!E:E,'Day wise agent'!G:G) -> 0 | L11: =IFERROR(J11/H11," ") -> 1
A12: =B12&G12 -> SBM42245931 | B12: SBM422 | C12: Abdulkalam Nisja Mudeen | D12: 44882 | E12: Shakeer | F12: =VLOOKUP(B12,'Agent wise'!A:E,5,0) -> Wireless | G12: 45931 | H12: =COUNTIFS('Audit Raw data'!J:J,B:B,'Audit Raw data'!E:E,G:G) -> 0 | I12: =IFERROR((SUMIFS('Audit Raw data'!BZ:BZ,'Audit Raw data'!J:J,B:B,'Audit Raw data'!E:E,G:G)/H12)/100,"-") -> - | J12: =COUNTIFS('Audit Raw data'!AM:AM,"Yes",'Audit Raw data'!J:J,B:B,'Audit Raw data'!E:E,'Day wise agent'!G:G) -> 0 | K12: =COUNTIFS('Audit Raw data'!AM:AM,"NO",'Audit Raw data'!J:J,B:B,'Audit Raw data'!E:E,'Day wise agent'!G:G) -> 0 | L12: =IFERROR(J12/H12," ")
A13: =B13&G13 -> SBM47945931 | B13: SBM479 | C13: Divya V S Ram | D13: 44932 | E13: Sowmya | F13: =VLOOKUP(B13,'Agent wise'!A:E,5,0) -> RECL | G13: 45931 | H13: =COUNTIFS('Audit Raw data'!J:J,B:B,'Audit Raw data'!E:E,G:G) -> 0 | I13: =IFERROR((SUMIFS('Audit Raw data'!BZ:BZ,'Audit Raw data'!J:J,B:B,'Audit Raw data'!E:E,G:G)/H13)/100,"-") -> - | J13: =COUNTIFS('Audit Raw data'!AM:AM,"Yes",'Audit Raw data'!J:J,B:B,'Audit Raw data'!E:E,'Day wise agent'!G:G) -> 0 | K13: =COUNTIFS('Audit Raw data'!AM:AM,"NO",'Audit Raw data'!J:J,B:B,'Audit Raw data'!E:E,'Day wise agent'!G:G) -> 0 | L13: =IFERROR(J13/H13," ")
... A1296: =B1296&G1296 -> VPS26445942 | B1296: VPS264 | C1296: Akil K S | D1296: 45938 | E1296: Anusha | F1296: =VLOOKUP(B1296,'Agent wise'!A:E,5,0) -> Wireless | G1296: 45942 | H1296: =COUNTIFS('Audit Raw data'!J:J,B:B,'Audit Raw data'!E:E,G:G) -> 0 | I1296: =IFERROR((SUMIFS('Audit Raw data'!BZ:BZ,'Audit Raw data'!J:J,B:B,'Audit Raw data'!E:E,G:G)/H1296)/100,"-") -> - | J1296: =COUNTIFS('Audit Raw data'!AM:AM,"Yes",'Audit Raw data'!J:J,B:B,'Audit Raw data'!E:E,'Day wise agent'!G:G) -> 0 | K1296: =COUNTIFS('Audit Raw data'!AM:AM,"NO",'Audit Raw data'!J:J,B:B,'Audit Raw data'!E:E,'Day wise agent'!G:G) -> 0 | L1296: =IFERROR(J1296/H1296," ")
H1297: =COUNTIFS('Audit Raw data'!J:J,B:B,'Audit Raw data'!E:E,G:G) -> 0 | I1297: =IFERROR((SUMIFS('Audit Raw data'!BZ:BZ,'Audit Raw data'!J:J,B:B,'Audit Raw data'!E:E,G:G)/H1297)/100,"-") -> - | J1297: =COUNTIFS('Audit Raw data'!AM:AM,"Yes",'Audit Raw data'!J:J,B:B,'Audit Raw data'!E:E,'Day wise agent'!G:G) -> 0 | K1297: =COUNTIFS('Audit Raw data'!AM:AM,"NO",'Audit Raw data'!J:J,B:B,'Audit Raw data'!E:E,'Day wise agent'!G:G) -> 0 | L1297: =IFERROR(J1297/H1297," ")
H1298: =COUNTIFS('Audit Raw data'!J:J,B:B,'Audit Raw data'!E:E,G:G) -> 0 | I1298: =IFERROR((SUMIFS('Audit Raw data'!BZ:BZ,'Audit Raw data'!J:J,B:B,'Audit Raw data'!E:E,G:G)/H1298)/100,"-") -> - | J1298: =COUNTIFS('Audit Raw data'!AM:AM,"Yes",'Audit Raw data'!J:J,B:B,'Audit Raw data'!E:E,'Day wise agent'!G:G) -> 0 | K1298: =COUNTIFS('Audit Raw data'!AM:AM,"NO",'Audit Raw data'!J:J,B:B,'Audit Raw data'!E:E,'Day wise agent'!G:G) -> 0 | L1298: =IFERROR(J1298/H1298," ")
H1299: =COUNTIFS('Audit Raw data'!J:J,B:B,'Audit Raw data'!E:E,G:G) -> 0 | I1299: =IFERROR((SUMIFS('Audit Raw data'!BZ:BZ,'Audit Raw data'!J:J,B:B,'Audit Raw data'!E:E,G:G)/H1299)/100,"-") -> - | J1299: =COUNTIFS('Audit Raw data'!AM:AM,"Yes",'Audit Raw data'!J:J,B:B,'Audit Raw data'!E:E,'Day wise agent'!G:G) -> 0 | K1299: =COUNTIFS('Audit Raw data'!AM:AM,"NO",'Audit Raw data'!J:J,B:B,'Audit Raw data'!E:E,'Day wise agent'!G:G) -> 0 | L1299: =IFERROR(J1299/H1299," ")
H1300: =COUNTIFS('Audit Raw data'!J:J,B:B,'Audit Raw data'!E:E,G:G) -> 0 | I1300: =IFERROR((SUMIFS('Audit Raw data'!BZ:BZ,'Audit Raw data'!J:J,B:B,'Audit Raw data'!E:E,G:G)/H1300)/100,"-") -> - | J1300: =COUNTIFS('Audit Raw data'!AM:AM,"Yes",'Audit Raw data'!J:J,B:B,'Audit Raw data'!E:E,'Day wise agent'!G:G) -> 0 | K1300: =COUNTIFS('Audit Raw data'!AM:AM,"NO",'Audit Raw data'!J:J,B:B,'Audit Raw data'!E:E,'Day wise agent'!G:G) -> 0 | L1300: =IFERROR(J1300/H1300," ")
H1301: =COUNTIFS('Audit Raw data'!J:J,B:B,'Audit Raw data'!E:E,G:G) -> 0 | I1301: =IFERROR((SUMIFS('Audit Raw data'!BZ:BZ,'Audit Raw data'!J:J,B:B,'Audit Raw data'!E:E,G:G)/H1301)/100,"-") -> - | J1301: =COUNTIFS('Audit Raw data'!AM:AM,"Yes",'Audit Raw data'!J:J,B:B,'Audit Raw data'!E:E,'Day wise agent'!G:G) -> 0 | K1301: =COUNTIFS('Audit Raw data'!AM:AM,"NO",'Audit Raw data'!J:J,B:B,'Audit Raw data'!E:E,'Day wise agent'!G:G) -> 0 | L1301: =IFERROR(J1301/H1301," ")
H1302: =COUNTIFS('Audit Raw data'!J:J,B:B,'Audit Raw data'!E:E,G:G) -> 0 | I1302: =IFERROR((SUMIFS('Audit Raw data'!BZ:BZ,'Audit Raw data'!J:J,B:B,'Audit Raw data'!E:E,G:G)/H1302)/100,"-") -> - | J1302: =COUNTIFS('Audit Raw data'!AM:AM,"Yes",'Audit Raw data'!J:J,B:B,'Audit Raw data'!E:E,'Day wise agent'!G:G) -> 0 | K1302: =COUNTIFS('Audit Raw data'!AM:AM,"NO",'Audit Raw data'!J:J,B:B,'Audit Raw data'!E:E,'Day wise agent'!G:G) -> 0 | L1302: =IFERROR(J1302/H1302," ")
H1303: =COUNTIFS('Audit Raw data'!J:J,B:B,'Audit Raw data'!E:E,G:G) -> 0 | I1303: =IFERROR((SUMIFS('Audit Raw data'!BZ:BZ,'Audit Raw data'!J:J,B:B,'Audit Raw data'!E:E,G:G)/H1303)/100,"-") -> - | J1303: =COUNTIFS('Audit Raw data'!AM:AM,"Yes",'Audit Raw data'!J:J,B:B,'Audit Raw data'!E:E,'Day wise agent'!G:G) -> 0 | K1303: =COUNTIFS('Audit Raw data'!AM:AM,"NO",'Audit Raw data'!J:J,B:B,'Audit Raw data'!E:E,'Day wise agent'!G:G) -> 0 | L1303: =IFERROR(J1303/H1303," ")
H1304: =COUNTIFS('Audit Raw data'!J:J,B:B,'Audit Raw data'!E:E,G:G) -> 0 | I1304: =IFERROR((SUMIFS('Audit Raw data'!BZ:BZ,'Audit Raw data'!J:J,B:B,'Audit Raw data'!E:E,G:G)/H1304)/100,"-") -> - | J1304: =COUNTIFS('Audit Raw data'!AM:AM,"Yes",'Audit Raw data'!J:J,B:B,'Audit Raw data'!E:E,'Day wise agent'!G:G) -> 0 | K1304: =COUNTIFS('Audit Raw data'!AM:AM,"NO",'Audit Raw data'!J:J,B:B,'Audit Raw data'!E:E,'Day wise agent'!G:G) -> 0 | L1304: =IFERROR(J1304/H1304," ")
H1305: =COUNTIFS('Audit Raw data'!J:J,B:B,'Audit Raw data'!E:E,G:G) -> 0 | I1305: =IFERROR((SUMIFS('Audit Raw data'!BZ:BZ,'Audit Raw data'!J:J,B:B,'Audit Raw data'!E:E,G:G)/H1305)/100,"-") -> - | J1305: =COUNTIFS('Audit Raw data'!AM:AM,"Yes",'Audit Raw data'!J:J,B:B,'Audit Raw data'!E:E,'Day wise agent'!G:G) -> 0 | K1305: =COUNTIFS('Audit Raw data'!AM:AM,"NO",'Audit Raw data'!J:J,B:B,'Audit Raw data'!E:E,'Day wise agent'!G:G) -> 0 | L1305: =IFERROR(J1305/H1305," ")
H1306: =COUNTIFS('Audit Raw data'!J:J,B:B,'Audit Raw data'!E:E,G:G) -> 0 | I1306: =IFERROR((SUMIFS('Audit Raw data'!BZ:BZ,'Audit Raw data'!J:J,B:B,'Audit Raw data'!E:E,G:G)/H1306)/100,"-") -> - | J1306: =COUNTIFS('Audit Raw data'!AM:AM,"Yes",'Audit Raw data'!J:J,B:B,'Audit Raw data'!E:E,'Day wise agent'!G:G) -> 0 | K1306: =COUNTIFS('Audit Raw data'!AM:AM,"NO",'Audit Raw data'!J:J,B:B,'Audit Raw data'!E:E,'Day wise agent'!G:G) -> 0 | L1306: =IFERROR(J1306/H1306," ")
H1307: =COUNTIFS('Audit Raw data'!J:J,B:B,'Audit Raw data'!E:E,G:G) -> 0 | I1307: =IFERROR((SUMIFS('Audit Raw data'!BZ:BZ,'Audit Raw data'!J:J,B:B,'Audit Raw data'!E:E,G:G)/H1307)/100,"-") -> - | J1307: =COUNTIFS('Audit Raw data'!AM:AM,"Yes",'Audit Raw data'!J:J,B:B,'Audit Raw data'!E:E,'Day wise agent'!G:G) -> 0 | K1307: =COUNTIFS('Audit Raw data'!AM:AM,"NO",'Audit Raw data'!J:J,B:B,'Audit Raw data'!E:E,'Day wise agent'!G:G) -> 0 | L1307: =IFERROR(J1307/H1307," ")
H1308: =COUNTIFS('Audit Raw data'!J:J,B:B,'Audit Raw data'!E:E,G:G) -> 0 | I1308: =IFERROR((SUMIFS('Audit Raw data'!BZ:BZ,'Audit Raw data'!J:J,B:B,'Audit Raw data'!E:E,G:G)/H1308)/100,"-") -> - | J1308: =COUNTIFS('Audit Raw data'!AM:AM,"Yes",'Audit Raw data'!J:J,B:B,'Audit Raw data'!E:E,'Day wise agent'!G:G) -> 0 | K1308: =COUNTIFS('Audit Raw data'!AM:AM,"NO",'Audit Raw data'!J:J,B:B,'Audit Raw data'!E:E,'Day wise agent'!G:G) -> 0 | L1308: =IFERROR(J1308/H1308," ")
... H3214: =COUNTIFS('Audit Raw data'!J:J,B:B,'Audit Raw data'!E:E,G:G) -> 0 | I3214: =IFERROR((SUMIFS('Audit Raw data'!BZ:BZ,'Audit Raw data'!J:J,B:B,'Audit Raw data'!E:E,G:G)/H3214)/100,"-") -> - | J3214: =COUNTIFS('Audit Raw data'!AM:AM,"Yes",'Audit Raw data'!J:J,B:B,'Audit Raw data'!E:E,'Day wise agent'!G:G) -> 0 | K3214: =COUNTIFS('Audit Raw data'!AM:AM,"NO",'Audit Raw data'!J:J,B:B,'Audit Raw data'!E:E,'Day wise agent'!G:G) -> 0 | L3214: =IFERROR(J3214/H3214," ")

Sheet DASHBOARD
A1: =+"BSNL Quality-Wireless-Dashboard -"&TEXT(Q1,"MMM-YYYY") -> BSNL Quality-Wireless-Dashboard -Oct-2025 | Q1: 45931 | R1: =TODAY()-1 -> 45951
A5: Audit Count | D5: MTD Tagging Accuracy | I5: MTD - CQ Score | M5: =+"FTD CQ Score -"&TEXT(P3,"DD-MM") -> FTD CQ Score -00-01
A6: ='DAY WISE'!B2 -> 1246 | D6: ='DAY WISE'!F2 -> 0.97993579 | I6: ='DAY WISE'!C2 -> 91.05939 | M6: =VLOOKUP(R1,'DAY WISE'!A:F,3,0) -> 92.615385
A10: TL | B10: Count | C10: MTD Score | D10: FTD Score
A11: Anusha | B11: =COUNTIFS('Audit Raw data'!CA:CA,DASHBOARD!A11) -> 32 | C11: =SUMIFS('Audit Raw data'!BZ:BZ,'Audit Raw data'!CA:CA,A11)/B11 -> 85.0625 | D11: =COUNTIFS('Audit Raw data'!CA:CA,A11,'Audit Raw data'!CB:CB,$R$1) -> 0 | E11: =IFERROR(SUMIFS('Audit Raw data'!BZ:BZ,'Audit Raw data'!CA:CA,A11,'Audit Raw data'!CB:CB,$R$1)/D11,"")
A12: Saran S | B12: =COUNTIFS('Audit Raw data'!CA:CA,DASHBOARD!A12) -> 236 | C12: =SUMIFS('Audit Raw data'!BZ:BZ,'Audit Raw data'!CA:CA,A12)/B12 -> 90.457627 | D12: =COUNTIFS('Audit Raw data'!CA:CA,A12,'Audit Raw data'!CB:CB,$R$1) -> 13 | E12: =IFERROR(SUMIFS('Audit Raw data'!BZ:BZ,'Audit Raw data'!CA:CA,A12,'Audit Raw data'!CB:CB,$R$1)/D12,"") -> 91.538462
A13: Shakeer | B13: =COUNTIFS('Audit Raw data'!CA:CA,DASHBOARD!A13) -> 204 | C13: =SUMIFS('Audit Raw data'!BZ:BZ,'Audit Raw data'!CA:CA,A13)/B13 -> 90.45098 | D13: =COUNTIFS('Audit Raw data'!CA:CA,A13,'Audit Raw data'!CB:CB,$R$1) -> 12 | E13: =IFERROR(SUMIFS('Audit Raw data'!BZ:BZ,'Audit Raw data'!CA:CA,A13,'Audit Raw data'!CB:CB,$R$1)/D13,"") -> 92
A14: Adharsh | B14: =COUNTIFS('Audit Raw data'!CA:CA,DASHBOARD!A14) -> 181 | C14: =SUMIFS('Audit Raw data'!BZ:BZ,'Audit Raw data'!CA:CA,A14)/B14 -> 90.254144 | D14: =COUNTIFS('Audit Raw data'!CA:CA,A14,'Audit Raw data'!CB:CB,$R$1) -> 11 | E14: =IFERROR(SUMIFS('Audit Raw data'!BZ:BZ,'Audit Raw data'!CA:CA,A14,'Audit Raw data'!CB:CB,$R$1)/D14,"") -> 93.818182
A15: Shiny | B15: =COUNTIFS('Audit Raw data'!CA:CA,DASHBOARD!A15) -> 215 | C15: =SUMIFS('Audit Raw data'!BZ:BZ,'Audit Raw data'!CA:CA,A15)/B15 -> 92.074419 | D15: =COUNTIFS('Audit Raw data'!CA:CA,A15,'Audit Raw data'!CB:CB,$R$1) -> 2 | E15: =IFERROR(SUMIFS('Audit Raw data'!BZ:BZ,'Audit Raw data'!CA:CA,A15,'Audit Raw data'!CB:CB,$R$1)/D15,"") -> 94
A16: Amal | B16: =COUNTIFS('Audit Raw data'!CA:CA,DASHBOARD!A16) -> 280 | C16: =SUMIFS('Audit Raw data'!BZ:BZ,'Audit Raw data'!CA:CA,A16)/B16 -> 93.807143 | D16: =COUNTIFS('Audit Raw data'!CA:CA,A16,'Audit Raw data'!CB:CB,$R$1) -> 27 | E16: =IFERROR(SUMIFS('Audit Raw data'!BZ:BZ,'Audit Raw data'!CA:CA,A16,'Audit Raw data'!CB:CB,$R$1)/D16,"") -> 92.814815
A17: Total | B17: =SUM(B11:B16) -> 1148 | C17: =I6 -> 91.05939 | D17: =SUM(D11:D16) -> 65 | E17: =SUMIFS('Audit Raw data'!BZ:BZ,'Audit Raw data'!CB:CB,$R$1)/D17 -> 92.615385
A18: Date | B18: Count | C18: FTD Score | D18: Fatal Calls
A19: =TODAY()-1 -> 45951 | B19: =IFERROR(VLOOKUP(A19,'DAY WISE'!A:F,2,0),"") -> 65 | C19: =IFERROR(VLOOKUP(A19,'DAY WISE'!A:F,3,0),"") -> 92.615385 | D19: =COUNTIFS('Audit Raw data'!BZ:BZ,"<85",'Audit Raw data'!CB:CB,A19) -> 2
A20: =A19-1 -> 45950 | B20: =IFERROR(VLOOKUP(A20,'DAY WISE'!A:F,2,0),"") -> 47 | C20: =IFERROR(VLOOKUP(A20,'DAY WISE'!A:F,3,0),"") -> 89.276596 | D20: =COUNTIFS('Audit Raw data'!BZ:BZ,"<85",'Audit Raw data'!CB:CB,A20) -> 12
